Compiled from "test.java"
class test {
  public static int[] field1;

  test();
    Code:
       0: aload_0
       1: invokespecial #1                  // Method java/lang/Object."<init>":()V
       4: return

  public static int workload(int);
    Code:
       0: getstatic     #7                  // Field field1:[I
       3: iload_0
       4: iaload
       5: bipush        100
       7: iadd
       8: ireturn

  public static void main(java.lang.String[]);
    Code:
       0: iconst_0
       1: istore_1
       2: sipush        1024
       5: newarray       int
       7: putstatic     #7                  // Field field1:[I
      10: iconst_0
      11: istore_2
      12: iload_2
      13: sipush        1024
      16: if_icmpge     31
      19: getstatic     #7                  // Field field1:[I
      22: iload_2
      23: iload_2
      24: iastore
      25: iinc          2, 1
      28: goto          12
      31: iconst_0
      32: istore_2
      33: iload_2
      34: ldc           #13                 // int 1000000
      36: if_icmpge     56
      39: iload_1
      40: iload_2
      41: sipush        1024
      44: irem
      45: invokestatic  #14                 // Method workload:(I)I
      48: iadd
      49: istore_1
      50: iinc          2, 1
      53: goto          33
      56: getstatic     #18                 // Field java/lang/System.out:Ljava/io/PrintStream;
      59: iload_1
      60: invokedynamic #24,  0             // InvokeDynamic #0:makeConcatWithConstants:(I)Ljava/lang/String;
      65: invokevirtual #28                 // Method java/io/PrintStream.println:(Ljava/lang/String;)V
      68: return
}
