Classfile /home/intel/code/java/javacopt/test.class
  Last modified 17-Apr-2019; size 996 bytes
  MD5 checksum 0856980d4f196fa8ed1722cf0d1e4727
  Compiled from "const.java"
class test
  minor version: 0
  major version: 57
  flags: (0x0020) ACC_SUPER
  this_class: #3                          // test
  super_class: #9                         // java/lang/Object
  interfaces: 0, fields: 1, methods: 3, attributes: 3
Constant pool:
   #1 = Methodref          #9.#24         // java/lang/Object."<init>":()V
   #2 = Fieldref           #3.#25         // test.VAL:I
   #3 = Class              #26            // test
   #4 = Methodref          #3.#24         // test."<init>":()V
   #5 = Methodref          #3.#27         // test.getVal:()I
   #6 = Fieldref           #28.#29        // java/lang/System.out:Ljava/io/PrintStream;
   #7 = InvokeDynamic      #0:#33         // #0:makeConcatWithConstants:(I)Ljava/lang/String;
   #8 = Methodref          #34.#35        // java/io/PrintStream.println:(Ljava/lang/String;)V
   #9 = Class              #36            // java/lang/Object
  #10 = Utf8               VAL
  #11 = Utf8               I
  #12 = Utf8               ConstantValue
  #13 = Integer            10
  #14 = Utf8               <init>
  #15 = Utf8               ()V
  #16 = Utf8               Code
  #17 = Utf8               LineNumberTable
  #18 = Utf8               getVal
  #19 = Utf8               ()I
  #20 = Utf8               main
  #21 = Utf8               ([Ljava/lang/String;)V
  #22 = Utf8               SourceFile
  #23 = Utf8               const.java
  #24 = NameAndType        #14:#15        // "<init>":()V
  #25 = NameAndType        #10:#11        // VAL:I
  #26 = Utf8               test
  #27 = NameAndType        #18:#19        // getVal:()I
  #28 = Class              #37            // java/lang/System
  #29 = NameAndType        #38:#39        // out:Ljava/io/PrintStream;
  #30 = Utf8               BootstrapMethods
  #31 = MethodHandle       6:#40          // REF_invokeStatic java/lang/invoke/StringConcatFactory.makeConcatWithConstants:(Ljava/lang/invoke/MethodHandles$Lookup;Ljava/lang/String;Ljava/lang/invoke/MethodType;Ljava/lang/String;[Ljava/lang/Object;)Ljava/lang/invoke/CallSite;
  #32 = String             #41            // Res = \u0001
  #33 = NameAndType        #42:#43        // makeConcatWithConstants:(I)Ljava/lang/String;
  #34 = Class              #44            // java/io/PrintStream
  #35 = NameAndType        #45:#46        // println:(Ljava/lang/String;)V
  #36 = Utf8               java/lang/Object
  #37 = Utf8               java/lang/System
  #38 = Utf8               out
  #39 = Utf8               Ljava/io/PrintStream;
  #40 = Methodref          #47.#48        // java/lang/invoke/StringConcatFactory.makeConcatWithConstants:(Ljava/lang/invoke/MethodHandles$Lookup;Ljava/lang/String;Ljava/lang/invoke/MethodType;Ljava/lang/String;[Ljava/lang/Object;)Ljava/lang/invoke/CallSite;
  #41 = Utf8               Res = \u0001
  #42 = Utf8               makeConcatWithConstants
  #43 = Utf8               (I)Ljava/lang/String;
  #44 = Utf8               java/io/PrintStream
  #45 = Utf8               println
  #46 = Utf8               (Ljava/lang/String;)V
  #47 = Class              #49            // java/lang/invoke/StringConcatFactory
  #48 = NameAndType        #42:#53        // makeConcatWithConstants:(Ljava/lang/invoke/MethodHandles$Lookup;Ljava/lang/String;Ljava/lang/invoke/MethodType;Ljava/lang/String;[Ljava/lang/Object;)Ljava/lang/invoke/CallSite;
  #49 = Utf8               java/lang/invoke/StringConcatFactory
  #50 = Class              #55            // java/lang/invoke/MethodHandles$Lookup
  #51 = Utf8               Lookup
  #52 = Utf8               InnerClasses
  #53 = Utf8               (Ljava/lang/invoke/MethodHandles$Lookup;Ljava/lang/String;Ljava/lang/invoke/MethodType;Ljava/lang/String;[Ljava/lang/Object;)Ljava/lang/invoke/CallSite;
  #54 = Class              #56            // java/lang/invoke/MethodHandles
  #55 = Utf8               java/lang/invoke/MethodHandles$Lookup
  #56 = Utf8               java/lang/invoke/MethodHandles
{
  final int VAL;
    descriptor: I
    flags: (0x0010) ACC_FINAL
    ConstantValue: int 10

  test();
    descriptor: ()V
    flags: (0x0000)
    Code:
      stack=2, locals=1, args_size=1
         0: aload_0
         1: invokespecial #1                  // Method java/lang/Object."<init>":()V
         4: aload_0
         5: bipush        10
         7: putfield      #2                  // Field VAL:I
        10: return
      LineNumberTable:
        line 3: 0
        line 4: 4

  public int getVal();
    descriptor: ()I
    flags: (0x0001) ACC_PUBLIC
    Code:
      stack=1, locals=1, args_size=1
         0: bipush        10
         2: ireturn
      LineNumberTable:
        line 6: 0

  public static void main(java.lang.String[]);
    descriptor: ([Ljava/lang/String;)V
    flags: (0x0009) ACC_PUBLIC, ACC_STATIC
    Code:
      stack=2, locals=3, args_size=1
         0: new           #3                  // class test
         3: dup
         4: invokespecial #4                  // Method "<init>":()V
         7: astore_1
         8: aload_1
         9: invokevirtual #5                  // Method getVal:()I
        12: istore_2
        13: getstatic     #6                  // Field java/lang/System.out:Ljava/io/PrintStream;
        16: iload_2
        17: invokedynamic #7,  0              // InvokeDynamic #0:makeConcatWithConstants:(I)Ljava/lang/String;
        22: invokevirtual #8                  // Method java/io/PrintStream.println:(Ljava/lang/String;)V
        25: return
      LineNumberTable:
        line 9: 0
        line 10: 8
        line 11: 13
        line 12: 25
}
SourceFile: "const.java"
InnerClasses:
  public static final #51= #50 of #54;    // Lookup=class java/lang/invoke/MethodHandles$Lookup of class java/lang/invoke/MethodHandles
BootstrapMethods:
  0: #31 REF_invokeStatic java/lang/invoke/StringConcatFactory.makeConcatWithConstants:(Ljava/lang/invoke/MethodHandles$Lookup;Ljava/lang/String;Ljava/lang/invoke/MethodType;Ljava/lang/String;[Ljava/lang/Object;)Ljava/lang/invoke/CallSite;
    Method arguments:
      #32 Res = \u0001
