Classfile /home/jatinbha/code/java/lambda/test.class
  Last modified 05-May-2021; size 1932 bytes
  SHA-256 checksum 6abe0e2cb23bfc54fb8db3c94535c4f31ae799738a7262649d00f4381cc02feb
  Compiled from "test.java"
class test
  minor version: 0
  major version: 61
  flags: (0x0020) ACC_SUPER
  this_class: #17                         // test
  super_class: #2                         // java/lang/Object
  interfaces: 0, fields: 0, methods: 5, attributes: 3
Constant pool:
   #1 = Methodref          #2.#3          // java/lang/Object."<init>":()V
   #2 = Class              #4             // java/lang/Object
   #3 = NameAndType        #5:#6          // "<init>":()V
   #4 = Utf8               java/lang/Object
   #5 = Utf8               <init>
   #6 = Utf8               ()V
   #7 = InterfaceMethodref #8.#9          // FBinOp.apply:(I[I[I)I
   #8 = Class              #10            // FBinOp
   #9 = NameAndType        #11:#12        // apply:(I[I[I)I
  #10 = Utf8               FBinOp
  #11 = Utf8               apply
  #12 = Utf8               (I[I[I)I
  #13 = InvokeDynamic      #0:#14         // #0:apply:()LFBinOp;
  #14 = NameAndType        #11:#15        // apply:()LFBinOp;
  #15 = Utf8               ()LFBinOp;
  #16 = Methodref          #17.#18        // test.binOp:(LFBinOp;[I[I[I)V
  #17 = Class              #19            // test
  #18 = NameAndType        #20:#21        // binOp:(LFBinOp;[I[I[I)V
  #19 = Utf8               test
  #20 = Utf8               binOp
  #21 = Utf8               (LFBinOp;[I[I[I)V
  #22 = Integer            700000
  #23 = Methodref          #17.#24        // test.workload:([I[I[I)V
  #24 = NameAndType        #25:#26        // workload:([I[I[I)V
  #25 = Utf8               workload
  #26 = Utf8               ([I[I[I)V
  #27 = Methodref          #28.#29        // java/lang/System.currentTimeMillis:()J
  #28 = Class              #30            // java/lang/System
  #29 = NameAndType        #31:#32        // currentTimeMillis:()J
  #30 = Utf8               java/lang/System
  #31 = Utf8               currentTimeMillis
  #32 = Utf8               ()J
  #33 = Integer            100000
  #34 = Fieldref           #28.#35        // java/lang/System.out:Ljava/io/PrintStream;
  #35 = NameAndType        #36:#37        // out:Ljava/io/PrintStream;
  #36 = Utf8               out
  #37 = Utf8               Ljava/io/PrintStream;
  #38 = InvokeDynamic      #1:#39         // #1:makeConcatWithConstants:(J)Ljava/lang/String;
  #39 = NameAndType        #40:#41        // makeConcatWithConstants:(J)Ljava/lang/String;
  #40 = Utf8               makeConcatWithConstants
  #41 = Utf8               (J)Ljava/lang/String;
  #42 = Methodref          #43.#44        // java/io/PrintStream.println:(Ljava/lang/String;)V
  #43 = Class              #45            // java/io/PrintStream
  #44 = NameAndType        #46:#47        // println:(Ljava/lang/String;)V
  #45 = Utf8               java/io/PrintStream
  #46 = Utf8               println
  #47 = Utf8               (Ljava/lang/String;)V
  #48 = InvokeDynamic      #2:#49         // #2:makeConcatWithConstants:(I)Ljava/lang/String;
  #49 = NameAndType        #40:#50        // makeConcatWithConstants:(I)Ljava/lang/String;
  #50 = Utf8               (I)Ljava/lang/String;
  #51 = Utf8               Code
  #52 = Utf8               LineNumberTable
  #53 = Utf8               StackMapTable
  #54 = Utf8               main
  #55 = Utf8               ([Ljava/lang/String;)V
  #56 = Class              #57            // "[Ljava/lang/String;"
  #57 = Utf8               [Ljava/lang/String;
  #58 = Class              #59            // "[I"
  #59 = Utf8               [I
  #60 = Utf8               lambda$workload$0
  #61 = Utf8               SourceFile
  #62 = Utf8               test.java
  #63 = Utf8               BootstrapMethods
  #64 = MethodHandle       6:#65          // REF_invokeStatic java/lang/invoke/LambdaMetafactory.metafactory:(Ljava/lang/invoke/MethodHandles$Lookup;Ljava/lang/String;Ljava/lang/invoke/MethodType;Ljava/lang/invoke/MethodType;Ljava/lang/invoke/MethodHandle;Ljava/lang/invoke/MethodType;)Ljava/lang/invoke/CallSite;
  #65 = Methodref          #66.#67        // java/lang/invoke/LambdaMetafactory.metafactory:(Ljava/lang/invoke/MethodHandles$Lookup;Ljava/lang/String;Ljava/lang/invoke/MethodType;Ljava/lang/invoke/MethodType;Ljava/lang/invoke/MethodHandle;Ljava/lang/invoke/MethodType;)Ljava/lang/invoke/CallSite;
  #66 = Class              #68            // java/lang/invoke/LambdaMetafactory
  #67 = NameAndType        #69:#70        // metafactory:(Ljava/lang/invoke/MethodHandles$Lookup;Ljava/lang/String;Ljava/lang/invoke/MethodType;Ljava/lang/invoke/MethodType;Ljava/lang/invoke/MethodHandle;Ljava/lang/invoke/MethodType;)Ljava/lang/invoke/CallSite;
  #68 = Utf8               java/lang/invoke/LambdaMetafactory
  #69 = Utf8               metafactory
  #70 = Utf8               (Ljava/lang/invoke/MethodHandles$Lookup;Ljava/lang/String;Ljava/lang/invoke/MethodType;Ljava/lang/invoke/MethodType;Ljava/lang/invoke/MethodHandle;Ljava/lang/invoke/MethodType;)Ljava/lang/invoke/CallSite;
  #71 = MethodType         #12            //  (I[I[I)I
  #72 = MethodHandle       6:#73          // REF_invokeStatic test.lambda$workload$0:(I[I[I)I
  #73 = Methodref          #17.#74        // test.lambda$workload$0:(I[I[I)I
  #74 = NameAndType        #60:#12        // lambda$workload$0:(I[I[I)I
  #75 = MethodHandle       6:#76          // REF_invokeStatic java/lang/invoke/StringConcatFactory.makeConcatWithConstants:(Ljava/lang/invoke/MethodHandles$Lookup;Ljava/lang/String;Ljava/lang/invoke/MethodType;Ljava/lang/String;[Ljava/lang/Object;)Ljava/lang/invoke/CallSite;
  #76 = Methodref          #77.#78        // java/lang/invoke/StringConcatFactory.makeConcatWithConstants:(Ljava/lang/invoke/MethodHandles$Lookup;Ljava/lang/String;Ljava/lang/invoke/MethodType;Ljava/lang/String;[Ljava/lang/Object;)Ljava/lang/invoke/CallSite;
  #77 = Class              #79            // java/lang/invoke/StringConcatFactory
  #78 = NameAndType        #40:#80        // makeConcatWithConstants:(Ljava/lang/invoke/MethodHandles$Lookup;Ljava/lang/String;Ljava/lang/invoke/MethodType;Ljava/lang/String;[Ljava/lang/Object;)Ljava/lang/invoke/CallSite;
  #79 = Utf8               java/lang/invoke/StringConcatFactory
  #80 = Utf8               (Ljava/lang/invoke/MethodHandles$Lookup;Ljava/lang/String;Ljava/lang/invoke/MethodType;Ljava/lang/String;[Ljava/lang/Object;)Ljava/lang/invoke/CallSite;
  #81 = String             #82            // Time = \u0001
  #82 = Utf8               Time = \u0001
  #83 = String             #84            // \u0001
  #84 = Utf8               \u0001
  #85 = Utf8               InnerClasses
  #86 = Class              #87            // java/lang/invoke/MethodHandles$Lookup
  #87 = Utf8               java/lang/invoke/MethodHandles$Lookup
  #88 = Class              #89            // java/lang/invoke/MethodHandles
  #89 = Utf8               java/lang/invoke/MethodHandles
  #90 = Utf8               Lookup
{
  test();
    descriptor: ()V
    flags: (0x0000)
    Code:
      stack=1, locals=1, args_size=1
         0: aload_0
         1: invokespecial #1                  // Method java/lang/Object."<init>":()V
         4: return
      LineNumberTable:
        line 8: 0

  public static void binOp(FBinOp, int[], int[], int[]);
    descriptor: (LFBinOp;[I[I[I)V
    flags: (0x0009) ACC_PUBLIC, ACC_STATIC
    Code:
      stack=6, locals=5, args_size=4
         0: iconst_0
         1: istore        4
         3: iload         4
         5: aload_1
         6: arraylength
         7: if_icmpge     30
        10: aload_1
        11: iload         4
        13: aload_0
        14: iload         4
        16: aload_2
        17: aload_3
        18: invokeinterface #7,  4            // InterfaceMethod FBinOp.apply:(I[I[I)I
        23: iastore
        24: iinc          4, 1
        27: goto          3
        30: return
      LineNumberTable:
        line 10: 0
        line 11: 10
        line 10: 24
        line 13: 30
      StackMapTable: number_of_entries = 2
        frame_type = 252 /* append */
          offset_delta = 3
          locals = [ int ]
        frame_type = 250 /* chop */
          offset_delta = 26

  public static void workload(int[], int[], int[]);
    descriptor: ([I[I[I)V
    flags: (0x0009) ACC_PUBLIC, ACC_STATIC
    Code:
      stack=4, locals=3, args_size=3
         0: invokedynamic #13,  0             // InvokeDynamic #0:apply:()LFBinOp;
         5: aload_2
         6: aload_0
         7: aload_1
         8: invokestatic  #16                 // Method binOp:(LFBinOp;[I[I[I)V
        11: return
      LineNumberTable:
        line 15: 0
        line 16: 11

  public static void main(java.lang.String[]);
    descriptor: ([Ljava/lang/String;)V
    flags: (0x0009) ACC_PUBLIC, ACC_STATIC
    Code:
      stack=4, locals=12, args_size=1
         0: sipush        1024
         3: newarray       int
         5: astore_1
         6: sipush        1024
         9: newarray       int
        11: astore_2
        12: sipush        1024
        15: newarray       int
        17: astore_3
        18: iconst_0
        19: istore        4
        21: iload         4
        23: aload_1
        24: arraylength
        25: if_icmpge     50
        28: aload_1
        29: iload         4
        31: iload         4
        33: iconst_5
        34: isub
        35: iastore
        36: aload_2
        37: iload         4
        39: iload         4
        41: iconst_5
        42: iadd
        43: iastore
        44: iinc          4, 1
        47: goto          21
        50: iconst_0
        51: istore        4
        53: iload         4
        55: ldc           #22                 // int 700000
        57: if_icmpge     72
        60: aload_1
        61: aload_2
        62: aload_3
        63: invokestatic  #23                 // Method workload:([I[I[I)V
        66: iinc          4, 1
        69: goto          53
        72: invokestatic  #27                 // Method java/lang/System.currentTimeMillis:()J
        75: lstore        4
        77: iconst_0
        78: istore        6
        80: iload         6
        82: ldc           #33                 // int 100000
        84: if_icmpge     99
        87: aload_1
        88: aload_2
        89: aload_3
        90: invokestatic  #23                 // Method workload:([I[I[I)V
        93: iinc          6, 1
        96: goto          80
        99: invokestatic  #27                 // Method java/lang/System.currentTimeMillis:()J
       102: lload         4
       104: lsub
       105: lstore        6
       107: getstatic     #34                 // Field java/lang/System.out:Ljava/io/PrintStream;
       110: lload         6
       112: invokedynamic #38,  0             // InvokeDynamic #1:makeConcatWithConstants:(J)Ljava/lang/String;
       117: invokevirtual #42                 // Method java/io/PrintStream.println:(Ljava/lang/String;)V
       120: aload_3
       121: astore        8
       123: aload         8
       125: arraylength
       126: istore        9
       128: iconst_0
       129: istore        10
       131: iload         10
       133: iload         9
       135: if_icmpge     164
       138: aload         8
       140: iload         10
       142: iaload
       143: istore        11
       145: getstatic     #34                 // Field java/lang/System.out:Ljava/io/PrintStream;
       148: iload         11
       150: invokedynamic #48,  0             // InvokeDynamic #2:makeConcatWithConstants:(I)Ljava/lang/String;
       155: invokevirtual #42                 // Method java/io/PrintStream.println:(Ljava/lang/String;)V
       158: iinc          10, 1
       161: goto          131
       164: return
      LineNumberTable:
        line 19: 0
        line 20: 6
        line 21: 12
        line 22: 18
        line 23: 28
        line 24: 36
        line 22: 44
        line 28: 50
        line 29: 60
        line 28: 66
        line 32: 72
        line 33: 77
        line 34: 87
        line 33: 93
        line 36: 99
        line 37: 107
        line 39: 120
        line 40: 145
        line 39: 158
        line 42: 164
      StackMapTable: number_of_entries = 8
        frame_type = 255 /* full_frame */
          offset_delta = 21
          locals = [ class "[Ljava/lang/String;", class "[I", class "[I", class "[I", int ]
          stack = []
        frame_type = 250 /* chop */
          offset_delta = 28
        frame_type = 252 /* append */
          offset_delta = 2
          locals = [ int ]
        frame_type = 250 /* chop */
          offset_delta = 18
        frame_type = 253 /* append */
          offset_delta = 7
          locals = [ long, int ]
        frame_type = 250 /* chop */
          offset_delta = 18
        frame_type = 255 /* full_frame */
          offset_delta = 31
          locals = [ class "[Ljava/lang/String;", class "[I", class "[I", class "[I", long, long, class "[I", int, int ]
          stack = []
        frame_type = 248 /* chop */
          offset_delta = 32

  private static int lambda$workload$0(int, int[], int[]);
    descriptor: (I[I[I)I
    flags: (0x100a) ACC_PRIVATE, ACC_STATIC, ACC_SYNTHETIC
    Code:
      stack=3, locals=3, args_size=3
         0: aload_1
         1: iload_0
         2: iaload
         3: aload_2
         4: iload_0
         5: iaload
         6: iadd
         7: ireturn
      LineNumberTable:
        line 15: 0
}
SourceFile: "test.java"
BootstrapMethods:
  0: #64 REF_invokeStatic java/lang/invoke/LambdaMetafactory.metafactory:(Ljava/lang/invoke/MethodHandles$Lookup;Ljava/lang/String;Ljava/lang/invoke/MethodType;Ljava/lang/invoke/MethodType;Ljava/lang/invoke/MethodHandle;Ljava/lang/invoke/MethodType;)Ljava/lang/invoke/CallSite;
    Method arguments:
      #71 (I[I[I)I
      #72 REF_invokeStatic test.lambda$workload$0:(I[I[I)I
      #71 (I[I[I)I
  1: #75 REF_invokeStatic java/lang/invoke/StringConcatFactory.makeConcatWithConstants:(Ljava/lang/invoke/MethodHandles$Lookup;Ljava/lang/String;Ljava/lang/invoke/MethodType;Ljava/lang/String;[Ljava/lang/Object;)Ljava/lang/invoke/CallSite;
    Method arguments:
      #81 Time = \u0001
  2: #75 REF_invokeStatic java/lang/invoke/StringConcatFactory.makeConcatWithConstants:(Ljava/lang/invoke/MethodHandles$Lookup;Ljava/lang/String;Ljava/lang/invoke/MethodType;Ljava/lang/String;[Ljava/lang/Object;)Ljava/lang/invoke/CallSite;
    Method arguments:
      #83 \u0001
InnerClasses:
  public static final #90= #86 of #88;    // Lookup=class java/lang/invoke/MethodHandles$Lookup of class java/lang/invoke/MethodHandles
