public identity class test_larval version 69:65535
{
  public Method "<init>":"()V" 
    stack 1  locals 1
  {
         aload_0;
         invokespecial     Method java/lang/Object."<init>":"()V";
         return;
  }

  public static Method micro:"(II)LMyValue;" 
    stack 4  locals 3
  {
         aconst_null;
         astore_2;
         iload_0;
         iload_1;
         if_icmple         L20;
         new               class MyValue;
         astore_2;
         goto              L30;
  L20:   stack_frame_type  append;
           locals_map      class MyValue;
         new               class MyValue;
         dup;
         iload_1;
         iload_0;
         invokespecial     Method MyValue."<init>":"(II)V";
         astore_2;
  L30:   stack_frame_type  same;
         aload_2;
         areturn;
  }

  public static Method main:"([Ljava/lang/String;)V" 
    stack 2  locals 2
  {
         bipush            10;
         bipush            20;
         invokestatic      Method micro:"(II)LMyValue;";
         astore_1;
         getstatic         Field java/lang/System.out:"Ljava/io/PrintStream;";
         aload_1;
         invokestatic      Method java/lang/String.valueOf:"(Ljava/lang/Object;)Ljava/lang/String;";
         invokedynamic     InvokeDynamic REF_invokeStatic:Method java/lang/invoke/StringConcatFactory.makeConcatWithConstants:
                           "(Ljava/lang/invoke/MethodHandles$Lookup;Ljava/lang/String;Ljava/lang/invoke/MethodType;Ljava/lang/String;[Ljava/lang/Object;)Ljava/lang/invoke/CallSite;":
                           makeConcatWithConstants:"(Ljava/lang/String;)Ljava/lang/String;" {
                             String "obj => \u0001"
                           };
         invokevirtual     Method java/io/PrintStream.println:"(Ljava/lang/String;)V";
         getstatic         Field java/lang/System.out:"Ljava/io/PrintStream;";
         aload_1;
         getfield          Field MyValue.field1:"I";
         invokedynamic     InvokeDynamic REF_invokeStatic:Method java/lang/invoke/StringConcatFactory.makeConcatWithConstants:
                           "(Ljava/lang/invoke/MethodHandles$Lookup;Ljava/lang/String;Ljava/lang/invoke/MethodType;Ljava/lang/String;[Ljava/lang/Object;)Ljava/lang/invoke/CallSite;":
                           makeConcatWithConstants:"(I)Ljava/lang/String;" {
                             String "field1 => \u0001"
                           };
         invokevirtual     Method java/io/PrintStream.println:"(Ljava/lang/String;)V";
         return;
  }

  SourceFile               "test_larval.java";

  InnerClass               public static final identity Lookup = class java/lang/invoke/MethodHandles$Lookup of class java/lang/invoke/MethodHandles;

  LoadableDescriptors      "LMyValue;";

  BootstrapMethod          REF_invokeStatic:java/lang/invoke/StringConcatFactory.makeConcatWithConstants:
                           "(Ljava/lang/invoke/MethodHandles$Lookup;Ljava/lang/String;Ljava/lang/invoke/MethodType;Ljava/lang/String;[Ljava/lang/Object;)Ljava/lang/invoke/CallSite;";
                           { 
                             String "obj => \u0001"
                           }

  BootstrapMethod          REF_invokeStatic:java/lang/invoke/StringConcatFactory.makeConcatWithConstants:
                           "(Ljava/lang/invoke/MethodHandles$Lookup;Ljava/lang/String;Ljava/lang/invoke/MethodType;Ljava/lang/String;[Ljava/lang/Object;)Ljava/lang/invoke/CallSite;";
                           { 
                             String "field1 => \u0001"
                           }
} // end Class test_larval compiled from "test_larval.java"
