<?xml version='1.0' encoding='UTF-8'?>
<hotspot_log version='160 1' process='713779' time_ms='1660302326086'>
<vm_version>
<name>
OpenJDK 64-Bit Server VM
</name>
<release>
20-internal-adhoc.root.jdk
</release>
<info>
OpenJDK 64-Bit Server VM (slowdebug 20-internal-adhoc.root.jdk) for linux-amd64 JRE (20-internal-adhoc.root.jdk), built on 2022-08-03T08:06:13Z by &quot;root&quot; with gcc 9.3.0
</info>
</vm_version>
<vm_arguments>
<args>
-XX:+UnlockDiagnosticVMOptions -XX:-TieredCompilation -XX:CompileCommand=Print,polymorphic::* -XX:+PrintInlining -XX:CompileCommand=CompileOnly,polymorphic::doCall -XX:+AlwaysIncrementalInline </args>
<command>
polymorphic 1024 0
</command>
<launcher>
SUN_STANDARD
</launcher>
<properties>
java.vm.specification.name=Java Virtual Machine Specification
java.vm.version=20-internal-adhoc.root.jdk
java.vm.name=OpenJDK 64-Bit Server VM
jdk.debug=slowdebug
sun.boot.library.path=/home/jatinbha/sandboxes/jdk/jdk/build/linux-x86_64-server-slowdebug/jdk/lib
java.library.path=/home/jatinbha/softwares:/home/jatinbha/softwares::/usr/java/packages/lib:/usr/lib64:/lib64:/lib:/usr/lib
java.home=/home/jatinbha/sandboxes/jdk/jdk/build/linux-x86_64-server-slowdebug/jdk
java.class.path=.
java.vm.info=mixed mode, sharing
java.vm.specification.vendor=Oracle Corporation
java.vm.specification.version=20
java.vm.vendor=Oracle Corporation
sun.java.command=polymorphic 1024 0
sun.java.launcher=SUN_STANDARD
</properties>
</vm_arguments>
<tty>
<writer thread='713780'/>
CompileCommand: print polymorphic.* bool print = true
CompileCommand: compileonly polymorphic.doCall bool compileonly = true
<blob name='MethodHandlesAdapterBlob' size='10224'>
<sect index='1' size='10224' free='8326'/>
</blob>
<writer thread='713792'/>

============================= C2-compiled nmethod ==============================
#r018 rsi:rsi   : parm 0: polymorphic:NotNull *
#r016 rdx:rdx   : parm 1: myclassP *
#r010 rcx:rcx   : parm 2: int[int:&gt;=0]:exact *
# -- Old rsp -- Framesize: 48 --
#r591 rsp+44: in_preserve
#r590 rsp+40: return address
#r589 rsp+36: in_preserve
#r588 rsp+32: saved fp register
#r587 rsp+28: pad2, stack alignment
#r586 rsp+24: pad2, stack alignment
#r585 rsp+20: Fixed slot 1
#r584 rsp+16: Fixed slot 0
#r595 rsp+12: spill
#r594 rsp+ 8: spill
#r593 rsp+ 4: spill
#r592 rsp+ 0: spill
#
<opto_assembly compile_id='26'>
----------------------- MetaData before Compile_id = 26 ------------------------
{method}
 - this oop:          0x00007fc5bc511540
 - method holder:     &apos;polymorphic&apos;
 - constants:         0x00007fc5bc511068 constant pool [92]/operands[15] {0x00007fc5bc511068} for &apos;polymorphic&apos; cache=0x00007fc5bc700210
 - access:            0x81000001  public 
 - name:              &apos;doCall&apos;
 - signature:         &apos;(LmyclassP;[I)I&apos;
 - max stack:         3
 - max locals:        3
 - size of params:    3
 - method size:       14
 - vtable index:      5
 - i2i entry:         0x00007fc60501f340
 - adapters:          AHE@0x00007fc60837fef0: 0xbbb i2c: 0x00007fc6050c2a60 c2i: 0x00007fc6050c2b48 c2iUV: 0x00007fc6050c2b12 c2iNCI: 0x00007fc6050c2b82
 - compiled entry     0x00007fc6050c2b48
 - code size:         9
 - code start:        0x00007fc5bc511530
 - code end (excl):   0x00007fc5bc511539
 - method data:       0x00007fc5bc7007b8
 - checked ex length: 0
 - linenumber start:  0x00007fc5bc511539
 - localvar length:   0

------------------------ OptoAssembly for Compile_id = 26 -----------------------
#
#  int ( polymorphic:NotNull *, myclassP *, int[int:&gt;=0]:exact * )
#
000     N337: #	out( B1 ) &lt;- BLOCK HEAD IS JUNK  Freq: 1
000     movl    rscratch1, [j_rarg0 + oopDesc::klass_offset_in_bytes()]	# compressed klass
	decode_klass_not_null rscratch1, rscratch1
	cmpq    rax, rscratch1	 # Inline cache check
	jne     SharedRuntime::_ic_miss_stub
	nop	# nops to align entry point

        nop 	# 4 bytes pad for loops and calls

020     B1: #	out( B25 B2 ) &lt;- BLOCK HEAD IS JUNK  Freq: 1
020     # stack bang (264 bytes)
	pushq   rbp	# Save rbp
	subq    rsp, #32	# Create frame

02c     testq   RDX, RDX	# ptr
02f     je     B25  P=0.000001 C=-1.000000

035     B2: #	out( B34 B3 ) &lt;- in( B1 )  Freq: 0.999999
035     movl    RBP, [RCX + #12 (8-bit)]	# range
038     NullCheck RCX

038     B3: #	out( B24 B4 ) &lt;- in( B2 )  Freq: 0.999998
038     xorl    RAX, RAX	# int
03a     testl   RBP, RBP	# unsigned
        nop 	# 4 bytes pad for loops and calls
040     jbe,u   B24  P=0.000976 C=6968975.000000

046     B4: #	out( B26 B5 ) &lt;- in( B3 )  Freq: 0.999022
046     movl    RBX, RBP	# spill
048     decl    RBX	# int
04a     cmpl    RBX, RBP	# unsigned
04c     jae,u   B26  P=0.000001 C=-1.000000

052     B5: #	out( B6 ) &lt;- in( B4 )  Freq: 0.999021
052     movl    R10, RCX	# ptr -&gt; int
055     shrl    R10, #2
059     andl    R10, #7	# int
05d     movl    R8, #3	# int
063     subl    R8, R10	# int
066     andl    R8, #7	# int
06a     incl    R8	# int
06d     cmpl    R8, RBP
070     cmovlgt R8, RBP	# min
074     xorl    R10, R10	# int
077     xorl    RDI, RDI	# int

079     B6: #	out( B8 B7 ) &lt;- in( B5 B7 ) Loop( B6-B7 inner pre of N225 reduction) Freq: 1.99804
079     movl    R9, [RCX + #16 + R10 &lt;&lt; #2]	# int
07e     sall    R9, #10
082     addl    RDI, R9	# int
085     movl    R11, R10	# spill
088     incl    R11	# int
08b     cmpl    R11, R8
08e     jge,s   B8	# loop end  P=0.500000 C=6962176.000000

090     B7: #	out( B6 ) &lt;- in( B6 )  Freq: 0.999021
090     movl    R10, R11	# spill
093     jmp,s   B6

095     B8: #	out( B27 B9 ) &lt;- in( B6 )  Freq: 0.999021
095     movl    R9, RBP	# spill
098     addl    R9, #-63	# int
09c     movl    R8, #-2147483648	# int
0a2     cmpl    RBX, R9
0a5     cmovll R9, R8	# signed, int
0a9     cmpl    R11, R9
0ac     jge     B27  P=0.000001 C=-1.000000

0b2     B9: #	out( B28 B10 ) &lt;- in( B8 )  Freq: 0.99902
0b2     movl    RSI, R10	# spill
0b5     # castII of RSI
0b5     incl    RSI	# int
0b7     cmpl    RSI, RBP	# unsigned
0b9     jae,u   B28  P=0.000001 C=-1.000000

0bf     B10: #	out( B29 B11 ) &lt;- in( B9 )  Freq: 0.999019
        nop 	# 1 bytes pad for loops and calls
0c0     cmpl    R11, RBP	# unsigned
0c3     jae,u   B29  P=0.000001 C=-1.000000

0c9     B11: #	out( B30 B12 ) &lt;- in( B10 )  Freq: 0.999018
0c9     addl    R10, #64	# int
0cd     cmpl    R10, RBP	# unsigned
0d0     jae,u   B30  P=0.000001 C=-1.000000

0d6     B12: #	out( B13 ) &lt;- in( B11 )  Freq: 0.999017
0d6     movl    RDX, #64000	# int
0db     # TLS is in R15

0db     B13: #	out( B14 ) &lt;- in( B12 B15 ) Loop( B13-B15 ) Freq: 1023.99
0db     movl    R14, R9	# spill
0de     subl    R14, RSI	# int
0e1     cmpl    R9, RSI
0e4     cmovll R14, RAX	# signed, int
0e8     cmpl    R14, #64000	# unsigned
0ef     cmovla R14, RDX	# unsigned, int
0f3     addl    R14, RSI	# int
        nop 	# 10 bytes pad for loops and calls

100     B14: #	out( B14 B15 ) &lt;- in( B13 B14 ) Loop( B14-B14 inner main of N109 reduction strip mined) Freq: 1.04959e+06
100     load_vector XMM0,[RCX + #240 + RSI &lt;&lt; #2]
109     load_vector XMM1,[RCX + #208 + RSI &lt;&lt; #2]
112     load_vector XMM2,[RCX + #176 + RSI &lt;&lt; #2]
11b     load_vector XMM3,[RCX + #144 + RSI &lt;&lt; #2]
124     load_vector XMM4,[RCX + #112 + RSI &lt;&lt; #2]
12a     load_vector XMM5,[RCX + #80 + RSI &lt;&lt; #2]
130     load_vector XMM6,[RCX + #48 + RSI &lt;&lt; #2]
136     load_vector XMM7,[RCX + #16 + RSI &lt;&lt; #2]
13c     vshiftd_imm  XMM8,XMM0,#10	! shift packedI
141     vshiftd_imm  XMM7,XMM7,#10	! shift packedI
146     vshiftd_imm  XMM9,XMM1,#10	! shift packedI
14b     vshiftd_imm  XMM6,XMM6,#10	! shift packedI
150     vshiftd_imm  XMM5,XMM5,#10	! shift packedI
155     vshiftd_imm  XMM10,XMM4,#10	! shift packedI
15a     vshiftd_imm  XMM11,XMM3,#10	! shift packedI
15f     vshiftd_imm  XMM2,XMM2,#10	! shift packedI
164     vector_reduction_int R11,RDI,XMM7 ; using XMM0, XMM1 as TEMP
185     vector_reduction_int R10,R11,XMM6 ; using XMM0, XMM1 as TEMP
1a7     vector_reduction_int R10,R10,XMM5 ; using XMM0, XMM1 as TEMP
1c9     vector_reduction_int R11,R10,XMM10 ; using XMM0, XMM1 as TEMP
1eb     vector_reduction_int R10,R11,XMM11 ; using XMM0, XMM1 as TEMP
20d     vector_reduction_int R11,R10,XMM2 ; using XMM0, XMM1 as TEMP
22f     vector_reduction_int R10,R11,XMM9 ; using XMM0, XMM12 as TEMP
253     vector_reduction_int RDI,R10,XMM8 ; using XMM3, XMM4 as TEMP
274     addl    RSI, #64	# int
277     cmpl    RSI, R14
        nop 	# 6 bytes pad for loops and calls
280     jl     B14	# loop end  P=0.999024 C=6962176.000000

286     B15: #	out( B13 B16 ) &lt;- in( B14 )  Freq: 1023.99
286     movq    R10, [R15 + #976 (32-bit)]	# ptr
28d     testl   rax, [R10]	# Safepoint: poll for GC        # myclassP::doAction @ bci:22 (line 7) L[0]=_ L[1]=RCX L[2]=RDI L[3]=RSI
        # polymorphic::doCall @ bci:2 (line 35) L[0]=_ L[1]=_ L[2]=_
        # OopMap {rcx=Oop off=653/0x28d}
290     cmpl    RSI, R9
293     jl     B13  P=0.999024 C=6962176.000000

299     B16: #	out( B20 B17 ) &lt;- in( B15 )  Freq: 0.999017
299     movl    R11, RBP	# spill
29c     addl    R11, #-7	# int
2a0     cmpl    RBX, R11
2a3     cmovll R11, R8	# signed, int
2a7     cmpl    RSI, R11
2aa     jge     B20  P=0.500000 C=-1.000000

2b0     B17: #	out( B31 B18 ) &lt;- in( B16 )  Freq: 0.499509
2b0     # castII of RSI
2b0     cmpl    RSI, RBP	# unsigned
2b2     jae,u   B31  P=0.000001 C=-1.000000

2b8     B18: #	out( B33 B19 ) &lt;- in( B17 )  Freq: 0.499508
2b8     movl    R10, RSI	# spill
2bb     addl    R10, #7	# int
        nop 	# 1 bytes pad for loops and calls
2c0     cmpl    R10, RBP	# unsigned
2c3     jae,u   B33  P=0.000001 C=-1.000000
        nop 	# 3 bytes pad for loops and calls

2cc     B19: #	out( B19 B20 ) &lt;- in( B18 B19 ) Loop( B19-B19 inner post of N611 reduction) Freq: 0.999015
2cc     load_vector XMM0,[RCX + #16 + RSI &lt;&lt; #2]
2d2     vshiftd_imm  XMM0,XMM0,#10	! shift packedI
2d7     vector_reduction_int RDI,RDI,XMM0 ; using XMM2, XMM1 as TEMP
2f7     addl    RSI, #8	# int
        nop 	# 6 bytes pad for loops and calls
300     cmpl    RSI, R11
303     jl,s   B19	# loop end  P=0.500000 C=6962176.000000

305     B20: #	out( B23 B21 ) &lt;- in( B27 B19 B16 )  Freq: 0.999017
305     cmpl    RSI, RBP
307     jge,s   B23  P=0.500000 C=-1.000000

309     B21: #	out( B32 B22 ) &lt;- in( B20 )  Freq: 0.499509
309     # castII of RSI
309     cmpl    RSI, RBP	# unsigned
30b     jae,u   B32  P=0.000001 C=-1.000000
        nop 	# 3 bytes pad for loops and calls

314     B22: #	out( B22 B23 ) &lt;- in( B21 B22 ) Loop( B22-B22 inner post of N225 reduction) Freq: 0.999016
314     movl    R11, [RCX + #16 + RSI &lt;&lt; #2]	# int
319     sall    R11, #10
31d     addl    RDI, R11	# int
320     incl    RSI	# int
322     cmpl    RSI, RBP
324     jl,s   B22	# loop end  P=0.500000 C=6962176.000000

326     B23: #	out( B24 ) &lt;- in( B22 B20 )  Freq: 0.999017
326     imull   RAX, RDI, #100	# int

329     B24: #	out( N337 ) &lt;- in( B23 B3 )  Freq: 0.999992
329     vzeroupper
	addq    rsp, 32	# Destroy frame
	popq    rbp
	cmpq     rsp, poll_offset[r15_thread] 
	ja       #safepoint_stub	# Safepoint: poll for GC

33e     ret

33f     B25: #	out( N337 ) &lt;- in( B1 )  Freq: 1.01328e-06
33f     movl    RSI, #-10	# int
344     movq    RBP, RCX	# spill
        nop 	# 1 bytes pad for loops and calls
348     call,static  wrapper for: uncommon_trap(reason=&apos;null_check&apos; action=&apos;maybe_recompile&apos; debug_id=&apos;0&apos;)
        # polymorphic::doCall @ bci:2 (line 35) L[0]=_ L[1]=_ L[2]=_ STK[0]=#NULL STK[1]=RBP
        # OopMap {rbp=Oop off=848/0x350}
350     stop	# ShouldNotReachHere

364     B26: #	out( N337 ) &lt;- in( B4 )  Freq: 1.01229e-06
364     movl    RSI, #-138	# int
369     movq    [rsp + #0], RCX	# spill
        nop 	# 3 bytes pad for loops and calls
370     call,static  wrapper for: uncommon_trap(reason=&apos;predicate&apos; action=&apos;maybe_recompile&apos; debug_id=&apos;0&apos;)
        # myclassP::doAction @ bci:7 (line 7) L[0]=_ L[1]=rsp + #0 L[2]=#0 L[3]=#0 STK[0]=#0 STK[1]=RBP
        # polymorphic::doCall @ bci:2 (line 35) L[0]=_ L[1]=_ L[2]=_
        # OopMap {[1168882436]=Oop off=888/0x378}
378     stop	# ShouldNotReachHere

38c     B27: #	out( B20 ) &lt;- in( B8 )  Freq: 1.01229e-06
38c     movl    RSI, R11	# spill
38f     jmp     B20

394     B28: #	out( N337 ) &lt;- in( B9 )  Freq: 1.01229e-06
394     stop	# ShouldNotReachHere

3a8     B29: #	out( N337 ) &lt;- in( B10 )  Freq: 1.01229e-06
3a8     stop	# ShouldNotReachHere

3bc     B30: #	out( N337 ) &lt;- in( B11 )  Freq: 1.01228e-06
3bc     stop	# ShouldNotReachHere

3d0     B31: #	out( N337 ) &lt;- in( B17 )  Freq: 5.06142e-07
3d0     stop	# ShouldNotReachHere

3e4     B32: #	out( N337 ) &lt;- in( B21 )  Freq: 5.06142e-07
3e4     stop	# ShouldNotReachHere

3f8     B33: #	out( N337 ) &lt;- in( B18 )  Freq: 5.06141e-07
3f8     stop	# ShouldNotReachHere

40c     B34: #	out( N337 ) &lt;- in( B2 )  Freq: 1.01328e-06
40c     movl    RSI, #-10	# int
        nop 	# 3 bytes pad for loops and calls
414     call,static  wrapper for: uncommon_trap(reason=&apos;null_check&apos; action=&apos;maybe_recompile&apos; debug_id=&apos;0&apos;)
        # myclassP::doAction @ bci:6 (line 7) L[0]=_ L[1]=_ L[2]=_ L[3]=_ STK[0]=_ STK[1]=#NULL
        # polymorphic::doCall @ bci:2 (line 35) L[0]=_ L[1]=_ L[2]=_
        # OopMap {off=1052/0x41c}
41c     stop	# ShouldNotReachHere

--------------------------------------------------------------------------------
</opto_assembly>
                            @ 2   myclassP::doAction (27 bytes)   inline (hot)
<print_nmethod compile_id='26' compiler='c2' stamp='1.678'>
----------------------------------- Assembly -----------------------------------

Compiled method (c2)    1679   26             polymorphic::doCall (9 bytes)
 total in heap  [0x00007fc605077610,0x00007fc605077e20] = 2064
 relocation     [0x00007fc605077770,0x00007fc6050777f8] = 136
 main code      [0x00007fc605077800,0x00007fc605077c48] = 1096
 stub code      [0x00007fc605077c48,0x00007fc605077c60] = 24
 oops           [0x00007fc605077c60,0x00007fc605077c68] = 8
 metadata       [0x00007fc605077c68,0x00007fc605077c80] = 24
 scopes data    [0x00007fc605077c80,0x00007fc605077ce8] = 104
 scopes pcs     [0x00007fc605077ce8,0x00007fc605077e08] = 288
 dependencies   [0x00007fc605077e08,0x00007fc605077e10] = 8
 nul chk table  [0x00007fc605077e10,0x00007fc605077e20] = 16

[Disassembly]
--------------------------------------------------------------------------------
[Constant Pool (empty)]

--------------------------------------------------------------------------------

[Entry Point]
  # {method} {0x00007fc5bc511540} &apos;doCall&apos; &apos;(LmyclassP;[I)I&apos; in &apos;polymorphic&apos;
  # this:     rsi:rsi   = &apos;polymorphic&apos;
  # parm0:    rdx:rdx   = &apos;myclassP&apos;
  # parm1:    rcx:rcx   = &apos;[I&apos;
  #           [sp+0x30]  (sp of caller)
 ;; N337: #	out( B1 ) &lt;- BLOCK HEAD IS JUNK  Freq: 1
  0x00007fc605077800:   mov    0x8(%rsi),%r10d
  0x00007fc605077804:   movabs $0x800000000,%r11
  0x00007fc60507780e:   add    %r11,%r10
  0x00007fc605077811:   cmp    %r10,%rax
  0x00007fc605077814:   jne    0x00007fc60512a320           ;   {runtime_call ic_miss_stub}
  0x00007fc60507781a:   nop
  0x00007fc60507781b:   nop
  0x00007fc60507781c:   nop
  0x00007fc60507781d:   nop
  0x00007fc60507781e:   nop
  0x00007fc60507781f:   nop
[Verified Entry Point]
 ;; B1: #	out( B25 B2 ) &lt;- BLOCK HEAD IS JUNK  Freq: 1
  0x00007fc605077820:   mov    %eax,-0x18000(%rsp)
  0x00007fc605077827:   push   %rbp
  0x00007fc605077828:   sub    $0x20,%rsp
  0x00007fc60507782c:   test   %rdx,%rdx
  0x00007fc60507782f:   je     0x00007fc605077b3f
 ;; B2: #	out( B34 B3 ) &lt;- in( B1 )  Freq: 0.999999
  0x00007fc605077835:   mov    0xc(%rcx),%ebp               ; implicit exception: dispatches to 0x00007fc605077c0c
 ;; B3: #	out( B24 B4 ) &lt;- in( B2 )  Freq: 0.999998
  0x00007fc605077838:   xor    %eax,%eax
  0x00007fc60507783a:   test   %ebp,%ebp                    ;*synchronization entry
                                                            ; - polymorphic::doCall@-1 (line 35)
  0x00007fc60507783c:   nop
  0x00007fc60507783d:   nop
  0x00007fc60507783e:   nop
  0x00007fc60507783f:   nop
  0x00007fc605077840:   jbe    0x00007fc605077b29
 ;; B4: #	out( B26 B5 ) &lt;- in( B3 )  Freq: 0.999022
  0x00007fc605077846:   mov    %ebp,%ebx
  0x00007fc605077848:   dec    %ebx
  0x00007fc60507784a:   cmp    %ebp,%ebx
  0x00007fc60507784c:   jae    0x00007fc605077b64
 ;; B5: #	out( B6 ) &lt;- in( B4 )  Freq: 0.999021
  0x00007fc605077852:   mov    %ecx,%r10d
  0x00007fc605077855:   shr    $0x2,%r10d
  0x00007fc605077859:   and    $0x7,%r10d
  0x00007fc60507785d:   mov    $0x3,%r8d
  0x00007fc605077863:   sub    %r10d,%r8d
  0x00007fc605077866:   and    $0x7,%r8d
  0x00007fc60507786a:   inc    %r8d
  0x00007fc60507786d:   cmp    %ebp,%r8d
  0x00007fc605077870:   cmovg  %ebp,%r8d
  0x00007fc605077874:   xor    %r10d,%r10d
  0x00007fc605077877:   xor    %edi,%edi                    ;*iload_2 {reexecute=0 rethrow=0 return_oop=0}
                                                            ; - myclassP::doAction@10 (line 8)
                                                            ; - polymorphic::doCall@2 (line 35)
 ;; B6: #	out( B8 B7 ) &lt;- in( B5 B7 ) Loop( B6-B7 inner pre of N225 reduction) Freq: 1.99804
  0x00007fc605077879:   mov    0x10(%rcx,%r10,4),%r9d
  0x00007fc60507787e:   shl    $0xa,%r9d
  0x00007fc605077882:   add    %r9d,%edi
  0x00007fc605077885:   mov    %r10d,%r11d                  ;*synchronization entry
                                                            ; - polymorphic::doCall@-1 (line 35)
  0x00007fc605077888:   inc    %r11d
  0x00007fc60507788b:   cmp    %r8d,%r11d
  0x00007fc60507788e:   jge    0x00007fc605077895
 ;; B7: #	out( B6 ) &lt;- in( B6 )  Freq: 0.999021
  0x00007fc605077890:   mov    %r11d,%r10d
  0x00007fc605077893:   jmp    0x00007fc605077879
 ;; B8: #	out( B27 B9 ) &lt;- in( B6 )  Freq: 0.999021
  0x00007fc605077895:   mov    %ebp,%r9d
  0x00007fc605077898:   add    $0xffffffc1,%r9d
  0x00007fc60507789c:   mov    $0x80000000,%r8d
  0x00007fc6050778a2:   cmp    %r9d,%ebx
  0x00007fc6050778a5:   cmovl  %r8d,%r9d
  0x00007fc6050778a9:   cmp    %r9d,%r11d
  0x00007fc6050778ac:   jge    0x00007fc605077b8c
 ;; B9: #	out( B28 B10 ) &lt;- in( B8 )  Freq: 0.99902
  0x00007fc6050778b2:   mov    %r10d,%esi
  0x00007fc6050778b5:   inc    %esi
  0x00007fc6050778b7:   cmp    %ebp,%esi
  0x00007fc6050778b9:   jae    0x00007fc605077b94
 ;; B10: #	out( B29 B11 ) &lt;- in( B9 )  Freq: 0.999019
  0x00007fc6050778bf:   nop
  0x00007fc6050778c0:   cmp    %ebp,%r11d
  0x00007fc6050778c3:   jae    0x00007fc605077ba8
 ;; B11: #	out( B30 B12 ) &lt;- in( B10 )  Freq: 0.999018
  0x00007fc6050778c9:   add    $0x40,%r10d
  0x00007fc6050778cd:   cmp    %ebp,%r10d
  0x00007fc6050778d0:   jae    0x00007fc605077bbc
 ;; B12: #	out( B13 ) &lt;- in( B11 )  Freq: 0.999017
  0x00007fc6050778d6:   mov    $0xfa00,%edx
 ;; B13: #	out( B14 ) &lt;- in( B12 B15 ) Loop( B13-B15 ) Freq: 1023.99
  0x00007fc6050778db:   mov    %r9d,%r14d
  0x00007fc6050778de:   sub    %esi,%r14d
  0x00007fc6050778e1:   cmp    %esi,%r9d
  0x00007fc6050778e4:   cmovl  %eax,%r14d
  0x00007fc6050778e8:   cmp    $0xfa00,%r14d
  0x00007fc6050778ef:   cmova  %edx,%r14d
  0x00007fc6050778f3:   add    %esi,%r14d
  0x00007fc6050778f6:   nop
  0x00007fc6050778f7:   nop
  0x00007fc6050778f8:   nop
  0x00007fc6050778f9:   nop
  0x00007fc6050778fa:   nop
  0x00007fc6050778fb:   nop
  0x00007fc6050778fc:   nop
  0x00007fc6050778fd:   nop
  0x00007fc6050778fe:   nop
  0x00007fc6050778ff:   nop                                 ;*iload_2 {reexecute=0 rethrow=0 return_oop=0}
                                                            ; - myclassP::doAction@10 (line 8)
                                                            ; - polymorphic::doCall@2 (line 35)
 ;; B14: #	out( B14 B15 ) &lt;- in( B13 B14 ) Loop( B14-B14 inner main of N109 reduction strip mined) Freq: 1.04959e+06
  0x00007fc605077900:   vmovdqu 0xf0(%rcx,%rsi,4),%ymm0
  0x00007fc605077909:   vmovdqu 0xd0(%rcx,%rsi,4),%ymm1
  0x00007fc605077912:   vmovdqu 0xb0(%rcx,%rsi,4),%ymm2
  0x00007fc60507791b:   vmovdqu 0x90(%rcx,%rsi,4),%ymm3
  0x00007fc605077924:   vmovdqu 0x70(%rcx,%rsi,4),%ymm4
  0x00007fc60507792a:   vmovdqu 0x50(%rcx,%rsi,4),%ymm5
  0x00007fc605077930:   vmovdqu 0x30(%rcx,%rsi,4),%ymm6
  0x00007fc605077936:   vmovdqu 0x10(%rcx,%rsi,4),%ymm7
  0x00007fc60507793c:   vpslld $0xa,%ymm0,%ymm8
  0x00007fc605077941:   vpslld $0xa,%ymm7,%ymm7
  0x00007fc605077946:   vpslld $0xa,%ymm1,%ymm9
  0x00007fc60507794b:   vpslld $0xa,%ymm6,%ymm6
  0x00007fc605077950:   vpslld $0xa,%ymm5,%ymm5
  0x00007fc605077955:   vpslld $0xa,%ymm4,%ymm10
  0x00007fc60507795a:   vpslld $0xa,%ymm3,%ymm11
  0x00007fc60507795f:   vpslld $0xa,%ymm2,%ymm2
  0x00007fc605077964:   vphaddd %ymm7,%ymm7,%ymm0
  0x00007fc605077969:   vextracti128 $0x1,%ymm0,%xmm1
  0x00007fc60507796f:   vpaddd %xmm1,%xmm0,%xmm0
  0x00007fc605077973:   vphaddd %xmm0,%xmm0,%xmm0
  0x00007fc605077978:   vmovd  %edi,%xmm1
  0x00007fc60507797c:   vpaddd %xmm1,%xmm0,%xmm0
  0x00007fc605077980:   vmovd  %xmm0,%r11d
  0x00007fc605077985:   vphaddd %ymm6,%ymm6,%ymm0
  0x00007fc60507798a:   vextracti128 $0x1,%ymm0,%xmm1
  0x00007fc605077990:   vpaddd %xmm1,%xmm0,%xmm0
  0x00007fc605077994:   vphaddd %xmm0,%xmm0,%xmm0
  0x00007fc605077999:   vmovd  %r11d,%xmm1
  0x00007fc60507799e:   vpaddd %xmm1,%xmm0,%xmm0
  0x00007fc6050779a2:   vmovd  %xmm0,%r10d
  0x00007fc6050779a7:   vphaddd %ymm5,%ymm5,%ymm0
  0x00007fc6050779ac:   vextracti128 $0x1,%ymm0,%xmm1
  0x00007fc6050779b2:   vpaddd %xmm1,%xmm0,%xmm0
  0x00007fc6050779b6:   vphaddd %xmm0,%xmm0,%xmm0
  0x00007fc6050779bb:   vmovd  %r10d,%xmm1
  0x00007fc6050779c0:   vpaddd %xmm1,%xmm0,%xmm0
  0x00007fc6050779c4:   vmovd  %xmm0,%r10d
  0x00007fc6050779c9:   vphaddd %ymm10,%ymm10,%ymm0
  0x00007fc6050779ce:   vextracti128 $0x1,%ymm0,%xmm1
  0x00007fc6050779d4:   vpaddd %xmm1,%xmm0,%xmm0
  0x00007fc6050779d8:   vphaddd %xmm0,%xmm0,%xmm0
  0x00007fc6050779dd:   vmovd  %r10d,%xmm1
  0x00007fc6050779e2:   vpaddd %xmm1,%xmm0,%xmm0
  0x00007fc6050779e6:   vmovd  %xmm0,%r11d
  0x00007fc6050779eb:   vphaddd %ymm11,%ymm11,%ymm0
  0x00007fc6050779f0:   vextracti128 $0x1,%ymm0,%xmm1
  0x00007fc6050779f6:   vpaddd %xmm1,%xmm0,%xmm0
  0x00007fc6050779fa:   vphaddd %xmm0,%xmm0,%xmm0
  0x00007fc6050779ff:   vmovd  %r11d,%xmm1
  0x00007fc605077a04:   vpaddd %xmm1,%xmm0,%xmm0
  0x00007fc605077a08:   vmovd  %xmm0,%r10d
  0x00007fc605077a0d:   vphaddd %ymm2,%ymm2,%ymm0
  0x00007fc605077a12:   vextracti128 $0x1,%ymm0,%xmm1       ;   {no_reloc}
  0x00007fc605077a18:   vpaddd %xmm1,%xmm0,%xmm0
  0x00007fc605077a1c:   vphaddd %xmm0,%xmm0,%xmm0
  0x00007fc605077a21:   vmovd  %r10d,%xmm1
  0x00007fc605077a26:   vpaddd %xmm1,%xmm0,%xmm0
  0x00007fc605077a2a:   vmovd  %xmm0,%r11d
  0x00007fc605077a2f:   vphaddd %ymm9,%ymm9,%ymm0
  0x00007fc605077a34:   vextracti128 $0x1,%ymm0,%xmm12
  0x00007fc605077a3a:   vpaddd %xmm12,%xmm0,%xmm0
  0x00007fc605077a3f:   vphaddd %xmm0,%xmm0,%xmm0
  0x00007fc605077a44:   vmovd  %r11d,%xmm12
  0x00007fc605077a49:   vpaddd %xmm12,%xmm0,%xmm0
  0x00007fc605077a4e:   vmovd  %xmm0,%r10d
  0x00007fc605077a53:   vphaddd %ymm8,%ymm8,%ymm3
  0x00007fc605077a58:   vextracti128 $0x1,%ymm3,%xmm4
  0x00007fc605077a5e:   vpaddd %xmm4,%xmm3,%xmm3
  0x00007fc605077a62:   vphaddd %xmm3,%xmm3,%xmm3
  0x00007fc605077a67:   vmovd  %r10d,%xmm4
  0x00007fc605077a6c:   vpaddd %xmm4,%xmm3,%xmm3
  0x00007fc605077a70:   vmovd  %xmm3,%edi                   ;*synchronization entry
                                                            ; - polymorphic::doCall@-1 (line 35)
  0x00007fc605077a74:   add    $0x40,%esi
  0x00007fc605077a77:   cmp    %r14d,%esi
  0x00007fc605077a7a:   nop
  0x00007fc605077a7b:   nop
  0x00007fc605077a7c:   nop
  0x00007fc605077a7d:   nop
  0x00007fc605077a7e:   nop
  0x00007fc605077a7f:   nop
  0x00007fc605077a80:   jl     0x00007fc605077900
 ;; B15: #	out( B13 B16 ) &lt;- in( B14 )  Freq: 1023.99
  0x00007fc605077a86:   mov    0x3d0(%r15),%r10             ; ImmutableOopMap {rcx=Oop }
                                                            ;*goto {reexecute=1 rethrow=0 return_oop=0}
                                                            ; - (reexecute) myclassP::doAction@22 (line 7)
                                                            ; - polymorphic::doCall@2 (line 35)
  0x00007fc605077a8d:   test   %eax,(%r10)                  ;   {poll}
  0x00007fc605077a90:   cmp    %r9d,%esi
  0x00007fc605077a93:   jl     0x00007fc6050778db
 ;; B16: #	out( B20 B17 ) &lt;- in( B15 )  Freq: 0.999017
  0x00007fc605077a99:   mov    %ebp,%r11d
  0x00007fc605077a9c:   add    $0xfffffff9,%r11d
  0x00007fc605077aa0:   cmp    %r11d,%ebx
  0x00007fc605077aa3:   cmovl  %r8d,%r11d
  0x00007fc605077aa7:   cmp    %r11d,%esi
  0x00007fc605077aaa:   jge    0x00007fc605077b05
 ;; B17: #	out( B31 B18 ) &lt;- in( B16 )  Freq: 0.499509
  0x00007fc605077ab0:   cmp    %ebp,%esi
  0x00007fc605077ab2:   jae    0x00007fc605077bd0
 ;; B18: #	out( B33 B19 ) &lt;- in( B17 )  Freq: 0.499508
  0x00007fc605077ab8:   mov    %esi,%r10d
  0x00007fc605077abb:   add    $0x7,%r10d
  0x00007fc605077abf:   nop
  0x00007fc605077ac0:   cmp    %ebp,%r10d
  0x00007fc605077ac3:   jae    0x00007fc605077bf8
  0x00007fc605077ac9:   nop
  0x00007fc605077aca:   nop
  0x00007fc605077acb:   nop                                 ;*iload_2 {reexecute=0 rethrow=0 return_oop=0}
                                                            ; - myclassP::doAction@10 (line 8)
                                                            ; - polymorphic::doCall@2 (line 35)
 ;; B19: #	out( B19 B20 ) &lt;- in( B18 B19 ) Loop( B19-B19 inner post of N611 reduction) Freq: 0.999015
  0x00007fc605077acc:   vmovdqu 0x10(%rcx,%rsi,4),%ymm0
  0x00007fc605077ad2:   vpslld $0xa,%ymm0,%ymm0
  0x00007fc605077ad7:   vphaddd %ymm0,%ymm0,%ymm2
  0x00007fc605077adc:   vextracti128 $0x1,%ymm2,%xmm1
  0x00007fc605077ae2:   vpaddd %xmm1,%xmm2,%xmm2
  0x00007fc605077ae6:   vphaddd %xmm2,%xmm2,%xmm2
  0x00007fc605077aeb:   vmovd  %edi,%xmm1
  0x00007fc605077aef:   vpaddd %xmm1,%xmm2,%xmm2
  0x00007fc605077af3:   vmovd  %xmm2,%edi                   ;*synchronization entry
                                                            ; - polymorphic::doCall@-1 (line 35)
  0x00007fc605077af7:   add    $0x8,%esi
  0x00007fc605077afa:   nop
  0x00007fc605077afb:   nop
  0x00007fc605077afc:   nop
  0x00007fc605077afd:   nop
  0x00007fc605077afe:   nop
  0x00007fc605077aff:   nop
  0x00007fc605077b00:   cmp    %r11d,%esi
  0x00007fc605077b03:   jl     0x00007fc605077acc
 ;; B20: #	out( B23 B21 ) &lt;- in( B27 B19 B16 )  Freq: 0.999017
  0x00007fc605077b05:   cmp    %ebp,%esi
  0x00007fc605077b07:   jge    0x00007fc605077b26
 ;; B21: #	out( B32 B22 ) &lt;- in( B20 )  Freq: 0.499509
  0x00007fc605077b09:   cmp    %ebp,%esi
  0x00007fc605077b0b:   jae    0x00007fc605077be4
  0x00007fc605077b11:   nop
  0x00007fc605077b12:   nop
  0x00007fc605077b13:   nop                                 ;*iload_2 {reexecute=0 rethrow=0 return_oop=0}
                                                            ; - myclassP::doAction@10 (line 8)
                                                            ; - polymorphic::doCall@2 (line 35)
 ;; B22: #	out( B22 B23 ) &lt;- in( B21 B22 ) Loop( B22-B22 inner post of N225 reduction) Freq: 0.999016
  0x00007fc605077b14:   mov    0x10(%rcx,%rsi,4),%r11d
  0x00007fc605077b19:   shl    $0xa,%r11d
  0x00007fc605077b1d:   add    %r11d,%edi
  0x00007fc605077b20:   inc    %esi
  0x00007fc605077b22:   cmp    %ebp,%esi
  0x00007fc605077b24:   jl     0x00007fc605077b14
 ;; B23: #	out( B24 ) &lt;- in( B22 B20 )  Freq: 0.999017
  0x00007fc605077b26:   imul   $0x64,%edi,%eax
 ;; B24: #	out( N337 ) &lt;- in( B23 B3 )  Freq: 0.999992
  0x00007fc605077b29:   vzeroupper 
  0x00007fc605077b2c:   add    $0x20,%rsp
  0x00007fc605077b30:   pop    %rbp
  0x00007fc605077b31:   cmp    0x3c8(%r15),%rsp             ;   {poll_return}
  0x00007fc605077b38:   ja     0x00007fc605077c30
  0x00007fc605077b3e:   retq   
 ;; B25: #	out( N337 ) &lt;- in( B1 )  Freq: 1.01328e-06
  0x00007fc605077b3f:   mov    $0xfffffff6,%esi
  0x00007fc605077b44:   mov    %rcx,%rbp                    ;*synchronization entry
                                                            ; - polymorphic::doCall@-1 (line 35)
  0x00007fc605077b47:   nop
  0x00007fc605077b48:   vzeroupper 
  0x00007fc605077b4b:   callq  0x00007fc605132820           ; ImmutableOopMap {rbp=Oop }
                                                            ;*invokevirtual doAction {reexecute=0 rethrow=0 return_oop=0}
                                                            ; - polymorphic::doCall@2 (line 35)
                                                            ;   {runtime_call UncommonTrapBlob}
  0x00007fc605077b50:   movabs $0x7fc610abb548,%rdi         ;   {external_word}
  0x00007fc605077b5a:   and    $0xfffffffffffffff0,%rsp
  0x00007fc605077b5e:   callq  0x00007fc6101dbbb4           ;   {runtime_call MacroAssembler::debug64(char*, long, long*)}
  0x00007fc605077b63:   hlt    
 ;; B26: #	out( N337 ) &lt;- in( B4 )  Freq: 1.01229e-06
  0x00007fc605077b64:   mov    $0xffffff76,%esi
  0x00007fc605077b69:   mov    %rcx,(%rsp)                  ;*synchronization entry
                                                            ; - polymorphic::doCall@-1 (line 35)
  0x00007fc605077b6d:   nop
  0x00007fc605077b6e:   nop
  0x00007fc605077b6f:   nop
  0x00007fc605077b70:   vzeroupper 
  0x00007fc605077b73:   callq  0x00007fc605132820           ; ImmutableOopMap {[1168882436]=Oop }
                                                            ;*if_icmpge {reexecute=1 rethrow=0 return_oop=0}
                                                            ; - (reexecute) myclassP::doAction@7 (line 7)
                                                            ; - polymorphic::doCall@2 (line 35)
                                                            ;   {runtime_call UncommonTrapBlob}
  0x00007fc605077b78:   movabs $0x7fc610abb548,%rdi         ;   {external_word}
  0x00007fc605077b82:   and    $0xfffffffffffffff0,%rsp
  0x00007fc605077b86:   callq  0x00007fc6101dbbb4           ;   {runtime_call MacroAssembler::debug64(char*, long, long*)}
  0x00007fc605077b8b:   hlt    
 ;; B27: #	out( B20 ) &lt;- in( B8 )  Freq: 1.01229e-06
  0x00007fc605077b8c:   mov    %r11d,%esi
  0x00007fc605077b8f:   jmpq   0x00007fc605077b05
 ;; B28: #	out( N337 ) &lt;- in( B9 )  Freq: 1.01229e-06
  0x00007fc605077b94:   movabs $0x7fc610c66268,%rdi         ;   {external_word}
  0x00007fc605077b9e:   and    $0xfffffffffffffff0,%rsp
  0x00007fc605077ba2:   callq  0x00007fc6101dbbb4           ;   {runtime_call MacroAssembler::debug64(char*, long, long*)}
  0x00007fc605077ba7:   hlt    
 ;; B29: #	out( N337 ) &lt;- in( B10 )  Freq: 1.01229e-06
  0x00007fc605077ba8:   movabs $0x7fc610c66268,%rdi         ;   {external_word}
  0x00007fc605077bb2:   and    $0xfffffffffffffff0,%rsp
  0x00007fc605077bb6:   callq  0x00007fc6101dbbb4           ;   {runtime_call MacroAssembler::debug64(char*, long, long*)}
  0x00007fc605077bbb:   hlt    
 ;; B30: #	out( N337 ) &lt;- in( B11 )  Freq: 1.01228e-06
  0x00007fc605077bbc:   movabs $0x7fc610c66268,%rdi         ;   {external_word}
  0x00007fc605077bc6:   and    $0xfffffffffffffff0,%rsp
  0x00007fc605077bca:   callq  0x00007fc6101dbbb4           ;   {runtime_call MacroAssembler::debug64(char*, long, long*)}
  0x00007fc605077bcf:   hlt    
 ;; B31: #	out( N337 ) &lt;- in( B17 )  Freq: 5.06142e-07
  0x00007fc605077bd0:   movabs $0x7fc610c66268,%rdi         ;   {external_word}
  0x00007fc605077bda:   and    $0xfffffffffffffff0,%rsp
  0x00007fc605077bde:   callq  0x00007fc6101dbbb4           ;   {runtime_call MacroAssembler::debug64(char*, long, long*)}
  0x00007fc605077be3:   hlt    
 ;; B32: #	out( N337 ) &lt;- in( B21 )  Freq: 5.06142e-07
  0x00007fc605077be4:   movabs $0x7fc610c66268,%rdi         ;   {external_word}
  0x00007fc605077bee:   and    $0xfffffffffffffff0,%rsp
  0x00007fc605077bf2:   callq  0x00007fc6101dbbb4           ;   {runtime_call MacroAssembler::debug64(char*, long, long*)}
  0x00007fc605077bf7:   hlt    
 ;; B33: #	out( N337 ) &lt;- in( B18 )  Freq: 5.06141e-07
  0x00007fc605077bf8:   movabs $0x7fc610c66268,%rdi         ;   {external_word}
  0x00007fc605077c02:   and    $0xfffffffffffffff0,%rsp
  0x00007fc605077c06:   callq  0x00007fc6101dbbb4           ;   {runtime_call MacroAssembler::debug64(char*, long, long*)}
  0x00007fc605077c0b:   hlt    
 ;; B34: #	out( N337 ) &lt;- in( B2 )  Freq: 1.01328e-06
  0x00007fc605077c0c:   mov    $0xfffffff6,%esi             ;*synchronization entry
                                                            ; - polymorphic::doCall@-1 (line 35)
  0x00007fc605077c11:   nop
  0x00007fc605077c12:   nop
  0x00007fc605077c13:   nop
  0x00007fc605077c14:   vzeroupper 
  0x00007fc605077c17:   callq  0x00007fc605132820           ; ImmutableOopMap {}
                                                            ;*arraylength {reexecute=0 rethrow=0 return_oop=0}
                                                            ; - myclassP::doAction@6 (line 7)
                                                            ; - polymorphic::doCall@2 (line 35)
                                                            ;   {runtime_call UncommonTrapBlob}
  0x00007fc605077c1c:   movabs $0x7fc610abb548,%rdi         ;   {external_word}
  0x00007fc605077c26:   and    $0xfffffffffffffff0,%rsp
  0x00007fc605077c2a:   callq  0x00007fc6101dbbb4           ;   {runtime_call MacroAssembler::debug64(char*, long, long*)}
  0x00007fc605077c2f:   hlt                                 ;*synchronization entry
                                                            ; - polymorphic::doCall@-1 (line 35)
  0x00007fc605077c30:   movabs $0x7fc605077b31,%r10         ;   {internal_word}
  0x00007fc605077c3a:   mov    %r10,0x3e0(%r15)
  0x00007fc605077c41:   jmpq   0x00007fc605131720           ;   {runtime_call SafepointBlob}
  0x00007fc605077c46:   hlt    
  0x00007fc605077c47:   hlt    
[Exception Handler]
  0x00007fc605077c48:   jmpq   0x00007fc6050c77a0           ;   {no_reloc}
[Deopt Handler Code]
  0x00007fc605077c4d:   callq  0x00007fc605077c52
  0x00007fc605077c52:   subq   $0x5,(%rsp)
  0x00007fc605077c57:   jmpq   0x00007fc605132b40           ;   {runtime_call DeoptimizationBlob}
  0x00007fc605077c5c:   hlt    
  0x00007fc605077c5d:   hlt    
  0x00007fc605077c5e:   hlt    
  0x00007fc605077c5f:   hlt    
--------------------------------------------------------------------------------
[/Disassembly]
- - - - - - - - - - - - - - - - - - - - - - - - - - - - - - - - - - - - - - - - 
Oops:
  0x00007fc605077c60:   0x000000011f8a7ec8 a &apos;jdk/internal/loader/ClassLoaders$AppClassLoader&apos;{0x000000011f8a7ec8}
- - - - - - - - - - - - - - - - - - - - - - - - - - - - - - - - - - - - - - - - 
Metadata:
  0x00007fc605077c68:   0x00007fc5bc511540 {method} {0x00007fc5bc511540} &apos;doCall&apos; &apos;(LmyclassP;[I)I&apos; in &apos;polymorphic&apos;
  0x00007fc605077c70:   0x00007fc5bc511bf0 {method} {0x00007fc5bc511bf0} &apos;doAction&apos; &apos;([I)I&apos; in &apos;myclassP&apos;
  0x00007fc605077c78:   0x00000008000c1210 &apos;myclassP&apos;
- - - - - - - - - - - - - - - - - - - - - - - - - - - - - - - - - - - - - - - - 
pc-bytecode offsets:
PcDesc(pc=0x00007fc6050777ff offset=ffffffff bits=0):
PcDesc(pc=0x00007fc60507783c offset=3c bits=0):
   polymorphic::doCall@-1 (line 35)
PcDesc(pc=0x00007fc605077879 offset=79 bits=0):
   myclassP::doAction@10 (line 8)
   polymorphic::doCall@2 (line 35)
PcDesc(pc=0x00007fc605077888 offset=88 bits=0):
   polymorphic::doCall@-1 (line 35)
PcDesc(pc=0x00007fc605077900 offset=100 bits=0):
   myclassP::doAction@10 (line 8)
   polymorphic::doCall@2 (line 35)
PcDesc(pc=0x00007fc605077a74 offset=274 bits=0):
   polymorphic::doCall@-1 (line 35)
PcDesc(pc=0x00007fc605077a8d offset=28d bits=1):
   myclassP::doAction@22 (line 7)  reexecute=true
   Locals
    - l0: empty
    - l1: reg rcx [2],oop
    - l2: reg rdi [14],int
    - l3: reg rsi [12],int
   polymorphic::doCall@2 (line 35)
   Locals
    - l0: empty
    - l1: empty
    - l2: empty
PcDesc(pc=0x00007fc605077acc offset=2cc bits=0):
   myclassP::doAction@10 (line 8)
   polymorphic::doCall@2 (line 35)
PcDesc(pc=0x00007fc605077af7 offset=2f7 bits=0):
   polymorphic::doCall@-1 (line 35)
PcDesc(pc=0x00007fc605077b14 offset=314 bits=0):
   myclassP::doAction@10 (line 8)
   polymorphic::doCall@2 (line 35)
PcDesc(pc=0x00007fc605077b47 offset=347 bits=0):
   polymorphic::doCall@-1 (line 35)
PcDesc(pc=0x00007fc605077b50 offset=350 bits=0):
   polymorphic::doCall@2 (line 35)
   Locals
    - l0: empty
    - l1: empty
    - l2: empty
   Expression stack
    - @0: NULL
    - @1: reg rbp [10],oop
PcDesc(pc=0x00007fc605077b6d offset=36d bits=0):
   polymorphic::doCall@-1 (line 35)
PcDesc(pc=0x00007fc605077b78 offset=378 bits=1):
   myclassP::doAction@7 (line 7)  reexecute=true
   Locals
    - l0: empty
    - l1: stack[0],oop
    - l2: 0
    - l3: 0
   Expression stack
    - @0: 0
    - @1: reg rbp [10],int
   polymorphic::doCall@2 (line 35)
   Locals
    - l0: empty
    - l1: empty
    - l2: empty
PcDesc(pc=0x00007fc605077c11 offset=411 bits=0):
   polymorphic::doCall@-1 (line 35)
PcDesc(pc=0x00007fc605077c1c offset=41c bits=0):
   myclassP::doAction@6 (line 7)
   Locals
    - l0: empty
    - l1: empty
    - l2: empty
    - l3: empty
   Expression stack
    - @0: empty
    - @1: NULL
   polymorphic::doCall@2 (line 35)
   Locals
    - l0: empty
    - l1: empty
    - l2: empty
PcDesc(pc=0x00007fc605077c30 offset=430 bits=0):
   polymorphic::doCall@-1 (line 35)
PcDesc(pc=0x00007fc605077c61 offset=461 bits=0):
- - - - - - - - - - - - - - - - - - - - - - - - - - - - - - - - - - - - - - - - 
oop maps:ImmutableOopMapSet contains 4 OopMaps

ImmutableOopMap {rcx=Oop } pc offsets: 653 
ImmutableOopMap {rbp=Oop } pc offsets: 848 
ImmutableOopMap {[1168882436]=Oop } pc offsets: 888 
ImmutableOopMap {} pc offsets: 1052 
- - - - - - - - - - - - - - - - - - - - - - - - - - - - - - - - - - - - - - - - 
scopes:
ScopeDesc(pc=0x00007fc60507783c offset=3c):
   polymorphic::doCall@-1 (line 35)
ScopeDesc(pc=0x00007fc605077879 offset=79):
   myclassP::doAction@10 (line 8)
ScopeDesc(pc=0x00007fc605077879 offset=79):
   polymorphic::doCall@2 (line 35)
ScopeDesc(pc=0x00007fc605077888 offset=88):
   polymorphic::doCall@-1 (line 35)
ScopeDesc(pc=0x00007fc605077900 offset=100):
   myclassP::doAction@10 (line 8)
ScopeDesc(pc=0x00007fc605077900 offset=100):
   polymorphic::doCall@2 (line 35)
ScopeDesc(pc=0x00007fc605077a74 offset=274):
   polymorphic::doCall@-1 (line 35)
ScopeDesc(pc=0x00007fc605077a8d offset=28d):
   myclassP::doAction@22 (line 7)  reexecute=true
   Locals
    - l0: empty
    - l1: reg rcx [2],oop
    - l2: reg rdi [14],int
    - l3: reg rsi [12],int
ScopeDesc(pc=0x00007fc605077a8d offset=28d):
   polymorphic::doCall@2 (line 35)
   Locals
    - l0: empty
    - l1: empty
    - l2: empty
ScopeDesc(pc=0x00007fc605077acc offset=2cc):
   myclassP::doAction@10 (line 8)
ScopeDesc(pc=0x00007fc605077acc offset=2cc):
   polymorphic::doCall@2 (line 35)
ScopeDesc(pc=0x00007fc605077af7 offset=2f7):
   polymorphic::doCall@-1 (line 35)
ScopeDesc(pc=0x00007fc605077b14 offset=314):
   myclassP::doAction@10 (line 8)
ScopeDesc(pc=0x00007fc605077b14 offset=314):
   polymorphic::doCall@2 (line 35)
ScopeDesc(pc=0x00007fc605077b47 offset=347):
   polymorphic::doCall@-1 (line 35)
ScopeDesc(pc=0x00007fc605077b50 offset=350):
   polymorphic::doCall@2 (line 35)
   Locals
    - l0: empty
    - l1: empty
    - l2: empty
   Expression stack
    - @0: NULL
    - @1: reg rbp [10],oop
ScopeDesc(pc=0x00007fc605077b6d offset=36d):
   polymorphic::doCall@-1 (line 35)
ScopeDesc(pc=0x00007fc605077b78 offset=378):
   myclassP::doAction@7 (line 7)  reexecute=true
   Locals
    - l0: empty
    - l1: stack[0],oop
    - l2: 0
    - l3: 0
   Expression stack
    - @0: 0
    - @1: reg rbp [10],int
ScopeDesc(pc=0x00007fc605077b78 offset=378):
   polymorphic::doCall@2 (line 35)
   Locals
    - l0: empty
    - l1: empty
    - l2: empty
ScopeDesc(pc=0x00007fc605077c11 offset=411):
   polymorphic::doCall@-1 (line 35)
ScopeDesc(pc=0x00007fc605077c1c offset=41c):
   myclassP::doAction@6 (line 7)
   Locals
    - l0: empty
    - l1: empty
    - l2: empty
    - l3: empty
   Expression stack
    - @0: empty
    - @1: NULL
ScopeDesc(pc=0x00007fc605077c1c offset=41c):
   polymorphic::doCall@2 (line 35)
   Locals
    - l0: empty
    - l1: empty
    - l2: empty
ScopeDesc(pc=0x00007fc605077c30 offset=430):
   polymorphic::doCall@-1 (line 35)
- - - - - - - - - - - - - - - - - - - - - - - - - - - - - - - - - - - - - - - - 
relocations:
         @0x00007fc605077770: 3014
relocInfo@0x00007fc605077770 [type=6(runtime_call) addr=0x00007fc605077814 offset=20] | [destination=0x00007fc60512a320]
         @0x00007fc605077772: 01ff
relocInfo@0x00007fc605077772 [type=0(none) addr=0x00007fc605077a13 offset=511]
         @0x00007fc605077774: 507a
relocInfo@0x00007fc605077774 [type=10(poll) addr=0x00007fc605077a8d offset=122]
         @0x00007fc605077776: 58a4
relocInfo@0x00007fc605077776 [type=11(poll_return) addr=0x00007fc605077b31 offset=164]
         @0x00007fc605077778: 321a
relocInfo@0x00007fc605077778 [type=6(runtime_call) addr=0x00007fc605077b4b offset=26 format=1] | [destination=0x00007fc605132820]
         @0x00007fc60507777a: 7c0310abb5487fc63805
relocInfo@0x00007fc605077782 [type=7(external_word) addr=0x00007fc605077b50 offset=5 data={10abb5487fc6}] | [target=0x00007fc610abb548]
         @0x00007fc605077784: 320e
relocInfo@0x00007fc605077784 [type=6(runtime_call) addr=0x00007fc605077b5e offset=14 format=1] | [destination=0x00007fc6101dbbb4]
         @0x00007fc605077786: 3215
relocInfo@0x00007fc605077786 [type=6(runtime_call) addr=0x00007fc605077b73 offset=21 format=1] | [destination=0x00007fc605132820]
         @0x00007fc605077788: 7c0310abb5487fc63805
relocInfo@0x00007fc605077790 [type=7(external_word) addr=0x00007fc605077b78 offset=5 data={10abb5487fc6}] | [target=0x00007fc610abb548]
         @0x00007fc605077792: 320e
relocInfo@0x00007fc605077792 [type=6(runtime_call) addr=0x00007fc605077b86 offset=14 format=1] | [destination=0x00007fc6101dbbb4]
         @0x00007fc605077794: 7c0310c662687fc6380e
relocInfo@0x00007fc60507779c [type=7(external_word) addr=0x00007fc605077b94 offset=14 data={10c662687fc6}] | [target=0x00007fc610c66268]
         @0x00007fc60507779e: 320e
relocInfo@0x00007fc60507779e [type=6(runtime_call) addr=0x00007fc605077ba2 offset=14 format=1] | [destination=0x00007fc6101dbbb4]
         @0x00007fc6050777a0: 7c0310c662687fc63806
relocInfo@0x00007fc6050777a8 [type=7(external_word) addr=0x00007fc605077ba8 offset=6 data={10c662687fc6}] | [target=0x00007fc610c66268]
         @0x00007fc6050777aa: 320e
relocInfo@0x00007fc6050777aa [type=6(runtime_call) addr=0x00007fc605077bb6 offset=14 format=1] | [destination=0x00007fc6101dbbb4]
         @0x00007fc6050777ac: 7c0310c662687fc63806
relocInfo@0x00007fc6050777b4 [type=7(external_word) addr=0x00007fc605077bbc offset=6 data={10c662687fc6}] | [target=0x00007fc610c66268]
         @0x00007fc6050777b6: 320e
relocInfo@0x00007fc6050777b6 [type=6(runtime_call) addr=0x00007fc605077bca offset=14 format=1] | [destination=0x00007fc6101dbbb4]
         @0x00007fc6050777b8: 7c0310c662687fc63806
relocInfo@0x00007fc6050777c0 [type=7(external_word) addr=0x00007fc605077bd0 offset=6 data={10c662687fc6}] | [target=0x00007fc610c66268]
         @0x00007fc6050777c2: 320e
relocInfo@0x00007fc6050777c2 [type=6(runtime_call) addr=0x00007fc605077bde offset=14 format=1] | [destination=0x00007fc6101dbbb4]
         @0x00007fc6050777c4: 7c0310c662687fc63806
relocInfo@0x00007fc6050777cc [type=7(external_word) addr=0x00007fc605077be4 offset=6 data={10c662687fc6}] | [target=0x00007fc610c66268]
         @0x00007fc6050777ce: 320e
relocInfo@0x00007fc6050777ce [type=6(runtime_call) addr=0x00007fc605077bf2 offset=14 format=1] | [destination=0x00007fc6101dbbb4]
         @0x00007fc6050777d0: 7c0310c662687fc63806
relocInfo@0x00007fc6050777d8 [type=7(external_word) addr=0x00007fc605077bf8 offset=6 data={10c662687fc6}] | [target=0x00007fc610c66268]
         @0x00007fc6050777da: 320e
relocInfo@0x00007fc6050777da [type=6(runtime_call) addr=0x00007fc605077c06 offset=14 format=1] | [destination=0x00007fc6101dbbb4]
         @0x00007fc6050777dc: 3211
relocInfo@0x00007fc6050777dc [type=6(runtime_call) addr=0x00007fc605077c17 offset=17 format=1] | [destination=0x00007fc605132820]
         @0x00007fc6050777de: 7c0310abb5487fc63805
relocInfo@0x00007fc6050777e6 [type=7(external_word) addr=0x00007fc605077c1c offset=5 data={10abb5487fc6}] | [target=0x00007fc610abb548]
         @0x00007fc6050777e8: 320e
relocInfo@0x00007fc6050777e8 [type=6(runtime_call) addr=0x00007fc605077c2a offset=14 format=1] | [destination=0x00007fc6101dbbb4]
         @0x00007fc6050777ea: 78ff4006
relocInfo@0x00007fc6050777ec [type=8(internal_word) addr=0x00007fc605077c30 offset=6 data=255] | [target=0x00007fc605077b31]
         @0x00007fc6050777ee: 3211
relocInfo@0x00007fc6050777ee [type=6(runtime_call) addr=0x00007fc605077c41 offset=17 format=1] | [destination=0x00007fc605131720]
         @0x00007fc6050777f0: 0007
relocInfo@0x00007fc6050777f0 [type=0(none) addr=0x00007fc605077c48 offset=7]
         @0x00007fc6050777f2: 3200
relocInfo@0x00007fc6050777f2 [type=6(runtime_call) addr=0x00007fc605077c48 offset=0 format=1] | [destination=0x00007fc6050c77a0]
         @0x00007fc6050777f4: 320f
relocInfo@0x00007fc6050777f4 [type=6(runtime_call) addr=0x00007fc605077c57 offset=15 format=1] | [destination=0x00007fc605132b40]
         @0x00007fc6050777f6: 0000
relocInfo@0x00007fc6050777f6 [type=0(none) addr=0x00007fc605077c57 offset=0]
         @0x00007fc6050777f8: 
- - - - - - - - - - - - - - - - - - - - - - - - - - - - - - - - - - - - - - - - 
Dependencies:
Dependency of type unique_concrete_method_4
  context = myclassP
  method  = {method} {0x00007fc5bc511bf0} &apos;doAction&apos; &apos;([I)I&apos; in &apos;myclassP&apos;
  class   = myclassP
  method  = {method} {0x00007fc5bc511bf0} &apos;doAction&apos; &apos;([I)I&apos; in &apos;myclassP&apos;
   [nmethod&lt;=klass]myclassP
<dependency type='unique_concrete_method_4' ctxk='myclassP' x='myclassP doAction ([I)I' x2='myclassP' x3='myclassP doAction ([I)I'/>
- - - - - - - - - - - - - - - - - - - - - - - - - - - - - - - - - - - - - - - - 
ExceptionHandlerTable (size = 0 bytes)
- - - - - - - - - - - - - - - - - - - - - - - - - - - - - - - - - - - - - - - - 
ImplicitExceptionTable (size = 1 entries, 12 bytes):
{
   &lt; 0x00007fc605077835, 0x00007fc605077c0c &gt; 
}
- - - - - - - - - - - - - - - - - - - - - - - - - - - - - - - - - - - - - - - - 
Recorded oops:
#0: 0x0000000000000000 NULL-oop
#1: 0x000000011f8a7ec8 a &apos;jdk/internal/loader/ClassLoaders$AppClassLoader&apos;{0x000000011f8a7ec8}
- - - - - - - - - - - - - - - - - - - - - - - - - - - - - - - - - - - - - - - - 
Recorded metadata:
#0: 0x0000000000000000 NULL-oop
#1: 0x00007fc5bc511540 {method} {0x00007fc5bc511540} &apos;doCall&apos; &apos;(LmyclassP;[I)I&apos; in &apos;polymorphic&apos;
#2: 0x00007fc5bc511bf0 {method} {0x00007fc5bc511bf0} &apos;doAction&apos; &apos;([I)I&apos; in &apos;myclassP&apos;
#3: 0x00000008000c1210 &apos;myclassP&apos;
- - - - - - - - - - - - - - - - - - - - - - - - - - - - - - - - - - - - - - - - 
</print_nmethod>
<writer thread='713780'/>
C1 Runtime statistics:
 _resolve_invoke_virtual_cnt:     0
 _resolve_invoke_opt_virtual_cnt: 0
 _resolve_invoke_static_cnt:      0
 _handle_wrong_method_cnt:        0
 _ic_miss_cnt:                    0
 _generic_arraycopystub_cnt:      0
 _byte_arraycopy_cnt:             0
 _short_arraycopy_cnt:            0
 _int_arraycopy_cnt:              0
 _long_arraycopy_cnt:             0
 _oop_arraycopy_cnt:              0
 _arraycopy_slowcase_cnt:         0
 _arraycopy_checkcast_cnt:        0
 _arraycopy_checkcast_attempt_cnt:0
 _new_type_array_slowcase_cnt:    0
 _new_object_array_slowcase_cnt:  0
 _new_instance_slowcase_cnt:      0
 _new_multi_array_slowcase_cnt:   0
 _monitorenter_slowcase_cnt:      0
 _monitorexit_slowcase_cnt:       0
 _patch_code_slowcase_cnt:        0
 _throw_range_check_exception_count:            0:
 _throw_index_exception_count:                  0:
 _throw_div0_exception_count:                   0:
 _throw_null_pointer_exception_count:           0:
 _throw_class_cast_exception_count:             0:
 _throw_incompatible_class_change_error_count:  0:
 _throw_count:                                  0:

<statistics type='SharedRuntime'>
    0 inline cache miss in compiled
    0 wrong method
    0 unresolved static call site
    0 unresolved virtual call site
    0 unresolved opt virtual call site
  285 slow partial subtype
  187 byte array copies
   80 short array copies
   56 int array copies
   50 long array copies
  325 unsafe array copies
AdapterHandlerTable: empty 110 longest 4 total 268 average 1.464481
AdapterHandlerTable: lookups 4717 buckets 5210 equals 4037 hits 4037 compact 4037
</statistics>
<statistics type='opto'>
--- Compiler Statistics ---
Methods seen: 2  Methods parsed: 2  Nodes created: 3314
Blocks parsed: 6  Blocks seen: 6
6 original NULL checks - 6 elided (100%); optimizer leaves 16,
1 made implicit ( 6%)
StringConcat:    0/   0/   0(replaced/merged/total)
CCP: 1  constants found: 0
Total frameslots = 12, Max frameslots = 4
Inserted 0 spill loads, 0 spill stores, 0 mem-mem moves and 0 copies.
Total load cost=      0, store cost =      0, mem-mem cost =  0.00, copy cost =     0.
Adjusted spill cost =       0.
Conservatively coalesced 36 copies, 0 pairs, 0 post alloc.
Used cisc instruction  0,  remained in register 29
Average allocation trips 1.000000
High Pressure Blocks = 0, Low Pressure Blocks = 0
Nops added 0 bytes to total of 2447 bytes, for 0.00%
Peephole: peephole rules applied: 0
PhaseIdealLoop=13, sum _unique=8586, long loops=0/0/0
No escape = 0, Arg escape = 0, Global escape = 0
Objects scalar replaced = 0, Monitor objects removed = 0, GC barriers removed = 0, Memory barriers removed = 0
</statistics>
------------------------------------------------------------------------
polymorphic::doCall(LmyclassP;[I)I
  interpreter_invocation_count:        7888
  invocation_counter:                  7888
  backedge_counter:                       0
  decompile_count:                        0
  mdo size: 504 bytes

0 aload_1
1 aload_2
2 invokevirtual 7 &lt;myclassP.doAction([I)I&gt; 
  0   bci: 2    VirtualCallData     count(0) nonprofiled_count(0) entries(1)
                                    &apos;myclassP&apos;(6225 1.00)
5 bipush 100
7 imul
8 ireturn
------------------------------------------------------------------------
static polymorphic::main([Ljava/lang/String;)V
  interpreter_invocation_count:           1
  invocation_counter:                     1
  backedge_counter:                  200000
  decompile_count:                        0
  mdo size: 2344 bytes

0 fast_aload_0
1 iconst_0
2 aaload
3 invokestatic 13 &lt;java/lang/Integer.parseInt(Ljava/lang/String;)I&gt; 
  0   bci: 3    CounterData         count(0)
6 istore_1
7 fast_aload_0
8 iconst_1
9 aaload
10 invokestatic 13 &lt;java/lang/Integer.parseInt(Ljava/lang/String;)I&gt; 
  16  bci: 10   CounterData         count(0)
13 istore_2
14 iload_1
15 newarray int
17 astore_3
18 aload_3
19 iconst_1
20 invokestatic 19 &lt;java/util/Arrays.fill([II)V&gt; 
  32  bci: 20   CounterData         count(0)
23 new 25 &lt;polymorphic&gt;
26 dup
27 invokespecial 27 &lt;polymorphic.&lt;init&gt;()V&gt; 
  48  bci: 27   CounterData         count(0)
30 astore #4
32 iload_2
33 ifne 140
  64  bci: 33   BranchData          taken(0) displacement(416)
                                    not taken(0)
36 iconst_0
37 istore #5
39 new 8 &lt;myclassP&gt;
42 dup
43 invokespecial 28 &lt;myclassP.&lt;init&gt;()V&gt; 
  96  bci: 43   CounterData         count(0)
46 astore #6
48 iconst_0
49 istore #7
51 fast_iload #7
53 ldc 100000
55 if_icmpge 77
  112 bci: 55   BranchData          taken(1) displacement(112)
                                    not taken(94880)
58 fast_iload #5
60 aload #4
62 aload #6
64 aload_3
65 invokevirtual 30 &lt;polymorphic.doCall(LmyclassP;[I)I&gt; 
  144 bci: 65   VirtualCallData     count(0) nonprofiled_count(0) entries(1)
                                    &apos;polymorphic&apos;(94880 1.00)
68 iadd
69 istore #5
71 iinc #7 1
74 goto 51
  200 bci: 74   JumpData            taken(94880) displacement(-88)
77 iconst_0
78 istore #5
80 invokestatic 34 &lt;java/lang/System.currentTimeMillis()J&gt; 
  224 bci: 80   CounterData         count(1)
83 lstore #7
85 iconst_0
86 istore #9
88 fast_iload #9
90 ldc 100000
92 if_icmpge 114
  240 bci: 92   BranchData          taken(1) displacement(112)
                                    not taken(100000)
95 fast_iload #5
97 aload #4
99 aload #6
101 aload_3
102 invokevirtual 30 &lt;polymorphic.doCall(LmyclassP;[I)I&gt; 
  272 bci: 102  VirtualCallData     count(0) nonprofiled_count(0) entries(1)
                                    &apos;polymorphic&apos;(100000 1.00)
105 iadd
106 istore #5
108 iinc #9 1
111 goto 88
  328 bci: 111  JumpData            taken(100000) displacement(-88)
114 invokestatic 34 &lt;java/lang/System.currentTimeMillis()J&gt; 
  352 bci: 114  CounterData         count(1)
117 lstore #9
119 getstatic 40 &lt;java/lang/System.out/Ljava/io/PrintStream;&gt; 
122 fast_iload #5
124 lload #9
126 lload #7
128 lsub
129 invokedynamic bsm=74 44 &lt;makeConcatWithConstants(IJ)Ljava/lang/String;&gt;
  368 bci: 129  CounterData         count(1)
                return type         &apos;java/lang/String&apos;
134 invokevirtual 48 &lt;java/io/PrintStream.println(Ljava/lang/String;)V&gt; 
  400 bci: 134  VirtualCallData     count(0) nonprofiled_count(0) entries(1)
                                    &apos;java/io/PrintStream&apos;(1 1.00)
137 goto 544
  456 bci: 137  JumpData            taken(1) displacement(1456)
140 iload_2
141 iconst_1
142 if_icmpne 308
  480 bci: 142  BranchData          taken(0) displacement(656)
                                    not taken(0)
145 iconst_0
146 istore #5
148 new 54 &lt;myclassC1&gt;
151 dup
152 invokespecial 56 &lt;myclassC1.&lt;init&gt;()V&gt; 
  512 bci: 152  CounterData         count(0)
155 astore #6
157 new 57 &lt;myclassC2&gt;
160 dup
161 invokespecial 59 &lt;myclassC2.&lt;init&gt;()V&gt; 
  528 bci: 161  CounterData         count(0)
164 astore #7
166 iconst_0
167 istore #8
169 iload #8
171 ldc 100000
173 if_icmpge 220
  544 bci: 173  BranchData          taken(0) displacement(224)
                                    not taken(0)
176 iload #8
178 sipush 128
181 iand
182 ifne 201
  576 bci: 182  BranchData          taken(0) displacement(112)
                                    not taken(0)
185 iload #5
187 aload #4
189 aload #6
191 aload_3
192 invokevirtual 30 &lt;polymorphic.doCall(LmyclassP;[I)I&gt; 
  608 bci: 192  VirtualCallData     count(0) nonprofiled_count(0) entries(0)
195 iadd
196 istore #5
198 goto 214
  664 bci: 198  JumpData            taken(0) displacement(80)
201 iload #5
203 aload #4
205 aload #7
207 aload_3
208 invokevirtual 30 &lt;polymorphic.doCall(LmyclassP;[I)I&gt; 
  688 bci: 208  VirtualCallData     count(0) nonprofiled_count(0) entries(0)
211 iadd
212 istore #5
214 iinc #8 1
217 goto 169
  744 bci: 217  JumpData            taken(0) displacement(-200)
220 iconst_0
221 istore #5
223 invokestatic 34 &lt;java/lang/System.currentTimeMillis()J&gt; 
  768 bci: 223  CounterData         count(0)
226 lstore #8
228 iconst_0
229 istore #10
231 iload #10
233 ldc 100000
235 if_icmpge 282
  784 bci: 235  BranchData          taken(0) displacement(224)
                                    not taken(0)
238 iload #10
240 sipush 128
243 iand
244 ifne 263
  816 bci: 244  BranchData          taken(0) displacement(112)
                                    not taken(0)
247 iload #5
249 aload #4
251 aload #6
253 aload_3
254 invokevirtual 30 &lt;polymorphic.doCall(LmyclassP;[I)I&gt; 
  848 bci: 254  VirtualCallData     count(0) nonprofiled_count(0) entries(0)
257 iadd
258 istore #5
260 goto 276
  904 bci: 260  JumpData            taken(0) displacement(80)
263 iload #5
265 aload #4
267 aload #7
269 aload_3
270 invokevirtual 30 &lt;polymorphic.doCall(LmyclassP;[I)I&gt; 
  928 bci: 270  VirtualCallData     count(0) nonprofiled_count(0) entries(0)
273 iadd
274 istore #5
276 iinc #10 1
279 goto 231
  984 bci: 279  JumpData            taken(0) displacement(-200)
282 invokestatic 34 &lt;java/lang/System.currentTimeMillis()J&gt; 
  1008bci: 282  CounterData         count(0)
285 lstore #10
287 getstatic 40 &lt;java/lang/System.out/Ljava/io/PrintStream;&gt; 
290 iload #5
292 lload #10
294 lload #8
296 lsub
297 invokedynamic bsm=74 60 &lt;makeConcatWithConstants(IJ)Ljava/lang/String;&gt;
  1024bci: 297  CounterData         count(0)
                return type         none
302 invokevirtual 48 &lt;java/io/PrintStream.println(Ljava/lang/String;)V&gt; 
  1056bci: 302  VirtualCallData     count(0) nonprofiled_count(0) entries(0)
305 goto 544
  1112bci: 305  JumpData            taken(0) displacement(800)
308 iload_2
309 iconst_2
310 if_icmpne 544
  1136bci: 310  BranchData          taken(0) displacement(776)
                                    not taken(0)
313 iconst_0
314 istore #5
316 new 54 &lt;myclassC1&gt;
319 dup
320 invokespecial 56 &lt;myclassC1.&lt;init&gt;()V&gt; 
  1168bci: 320  CounterData         count(0)
323 astore #6
325 new 57 &lt;myclassC2&gt;
328 dup
329 invokespecial 59 &lt;myclassC2.&lt;init&gt;()V&gt; 
  1184bci: 329  CounterData         count(0)
332 astore #7
334 new 8 &lt;myclassP&gt;
337 dup
338 invokespecial 28 &lt;myclassP.&lt;init&gt;()V&gt; 
  1200bci: 338  CounterData         count(0)
341 astore #8
343 iconst_0
344 istore #9
346 iload #9
348 ldc 100000
350 if_icmpge 429
  1216bci: 350  BranchData          taken(0) displacement(288)
                                    not taken(0)
353 iload #9
355 iconst_3
356 iand
357 fast_linearswitch 423 2  0:384, 1:397
  1248bci: 357  MultiBranchData     default_count(0) displacement(232)
                                    count(0) displacement(64)
                                    count(0) displacement(120)
384 iload #5
386 aload #4
388 aload #6
390 aload_3
391 invokevirtual 30 &lt;polymorphic.doCall(LmyclassP;[I)I&gt; 
  1312bci: 391  VirtualCallData     count(0) nonprofiled_count(0) entries(0)
394 iadd
395 istore #5
397 iload #5
399 aload #4
401 aload #7
403 aload_3
404 invokevirtual 30 &lt;polymorphic.doCall(LmyclassP;[I)I&gt; 
  1368bci: 404  VirtualCallData     count(0) nonprofiled_count(0) entries(0)
407 iadd
408 istore #5
410 iload #5
412 aload #4
414 aload #8
416 aload_3
417 invokevirtual 30 &lt;polymorphic.doCall(LmyclassP;[I)I&gt; 
  1424bci: 417  VirtualCallData     count(0) nonprofiled_count(0) entries(0)
420 iadd
421 istore #5
423 iinc #9 1
426 goto 346
  1480bci: 426  JumpData            taken(0) displacement(-264)
429 iconst_0
430 istore #5
432 invokestatic 34 &lt;java/lang/System.currentTimeMillis()J&gt; 
  1504bci: 432  CounterData         count(0)
435 lstore #9
437 iconst_0
438 istore #11
440 iload #11
442 ldc 100000
444 if_icmpge 521
  1520bci: 444  BranchData          taken(0) displacement(288)
                                    not taken(0)
447 iload #11
449 iconst_3
450 iand
451 fast_linearswitch 515 2  0:476, 1:489
  1552bci: 451  MultiBranchData     default_count(0) displacement(232)
                                    count(0) displacement(64)
                                    count(0) displacement(120)
476 iload #5
478 aload #4
480 aload #6
482 aload_3
483 invokevirtual 30 &lt;polymorphic.doCall(LmyclassP;[I)I&gt; 
  1616bci: 483  VirtualCallData     count(0) nonprofiled_count(0) entries(0)
486 iadd
487 istore #5
489 iload #5
491 aload #4
493 aload #7
495 aload_3
496 invokevirtual 30 &lt;polymorphic.doCall(LmyclassP;[I)I&gt; 
  1672bci: 496  VirtualCallData     count(0) nonprofiled_count(0) entries(0)
499 iadd
500 istore #5
502 iload #5
504 aload #4
506 aload #8
508 aload_3
509 invokevirtual 30 &lt;polymorphic.doCall(LmyclassP;[I)I&gt; 
  1728bci: 509  VirtualCallData     count(0) nonprofiled_count(0) entries(0)
512 iadd
513 istore #5
515 iinc #11 1
518 goto 440
  1784bci: 518  JumpData            taken(0) displacement(-264)
521 invokestatic 34 &lt;java/lang/System.currentTimeMillis()J&gt; 
  1808bci: 521  CounterData         count(0)
524 lstore #11
526 getstatic 40 &lt;java/lang/System.out/Ljava/io/PrintStream;&gt; 
529 iload #5
531 lload #11
533 lload #9
535 lsub
536 invokedynamic bsm=74 61 &lt;makeConcatWithConstants(IJ)Ljava/lang/String;&gt;
  1824bci: 536  CounterData         count(0)
                return type         none
541 invokevirtual 48 &lt;java/io/PrintStream.println(Ljava/lang/String;)V&gt; 
  1856bci: 541  VirtualCallData     count(0) nonprofiled_count(0) entries(0)
544 return
------------------------------------------------------------------------
Total MDO size: 2848 bytes
<writer thread='713786'/>
<destroy_vm stamp='1.931'/>
<tty_done stamp='2.863'/>
</tty>
<hotspot_log_done stamp='2.863'/>
</hotspot_log>
