CompileCommand: print callchain.* bool print = true
CompileCommand: dontinline callchain.* bool dontinline = true
CompileCommand: compileonly callchain.* bool compileonly = true

============================= C2-compiled nmethod ==============================
#r050 rsi:rsi   : parm 0: rawptr:BotPTR
# -- Old rsp -- Framesize: 48 --
#r623 rsp+44: in_preserve
#r622 rsp+40: return address
#r621 rsp+36: in_preserve
#r620 rsp+32: saved fp register
#r619 rsp+28: pad2, stack alignment
#r618 rsp+24: pad2, stack alignment
#r617 rsp+20: Fixed slot 1
#r616 rsp+16: Fixed slot 0
#r627 rsp+12: spill
#r626 rsp+ 8: spill
#r625 rsp+ 4: spill
#r624 rsp+ 0: spill
#
----------------------- MetaData before Compile_id = 24 ------------------------
{method}
 - this oop:          0x00007f1c5c6054c0
 - method holder:     'callchain'
 - constants:         0x00007f1c5c605058 constant pool [77]/operands[5] {0x00007f1c5c605058} for 'callchain' cache=0x00007f1c5c6059a8
 - access:            0x9  public static 
 - flags:             0x6080  queued_for_compilation has_loops_flag has_loops_flag_init 
 - name:              'leaf'
 - signature:         '(I)I'
 - max stack:         4
 - max locals:        4
 - size of params:    1
 - method size:       14
 - vtable index:      -2
 - i2i entry:         0x00007f1cb79afbe0
 - adapters:          AHE@0x00007f1cbc24c460: 0xa i2c: 0x00007f1cb7ac0fe0 c2i: 0x00007f1cb7ac1099 c2iUV: 0x00007f1cb7ac1074 c2iNCI: 0x00007f1cb7ac10d3
 - compiled entry     0x00007f1cb7ac1099
 - code size:         51
 - code start:        0x00007f1c5c605480
 - code end (excl):   0x00007f1c5c6054b3
 - method data:       0x00007f1c5c606348
 - checked ex length: 0
 - linenumber start:  0x00007f1c5c6054b3
 - localvar length:   0

------------------------ OptoAssembly for Compile_id = 24 -----------------------
#
#  int ( rawptr:BotPTR )
#
000     N191: #	out( B1 ) <- BLOCK HEAD IS JUNK  Freq: 1
000     # breakpoint
        nop 	# 11 bytes pad for loops and calls

010     B1: #	out( B14 B2 ) <- BLOCK HEAD IS JUNK  Freq: 1
010     # stack bang (152 bytes)
	pushq   rbp	# Save rbp
	movq    rbp, rsp	# Save the caller's SP into rbp
	subq    rsp, #32	# Create frame

02e     movl    R13, [RSI + #24 (8-bit)]	# int
032     movl    R14, [RSI + #8 (8-bit)]	# int
036     movl    RBX, [RSI + #16 (8-bit)]	# int
039     movq    RDI, RSI	# spill
03c     call_leaf,runtime  OSR_migration_end
        No JVM State Info
        # 
051     cmpl    R13, #9997
058     jg     B14  P=0.000001 C=-1.000000

05e     B2: #	out( B13 B3 ) <- in( B1 )  Freq: 0.999999
05e     cmpl    R14, #100
062     jge     B13  P=0.009863 C=20785.000000

068     B3: #	out( B4 ) <- in( B2 )  Freq: 0.990136
068     leal    R10, [R14 + #1]

06c     B4: #	out( B4 B5 ) <- in( B3 B4 ) Loop( B4-B4 inner pre of N313) Freq: 1.98027
06c     leal    R16, [R14 + R14]
071     leal RBX, [RBX + R16 + #40]	# int
077     incl    R14	# int
07a     cmpl    R14, R10
07d     jl,s   B4	# loop end  P=0.500000 C=20785.000000

07f     B5: #	out( B10 B6 ) <- in( B4 )  Freq: 0.990136
07f     cmpl    R14, #93
083     jge     B10  P=0.000001 C=-1.000000

089     B6: #	out( B7 ) <- in( B5 )  Freq: 0.990135
089     # castII of R14
089     movl    R16, #8000	# int
090     # TLS is in R15
090     xorl    R10, R10	# int

093     B7: #	out( B8 ) <- in( B6 B9 ) Loop( B7-B9 ) Freq: 100.39
093     movl    R17, #93	# int
09a     subl    R17, R14	# int
09e     cmpl    R14, #93
0a2     cmovlg R17, R10	# signed, int
0a6     cmpl    R17, #8000	# unsigned
0ae     cmovla R17, R16	# unsigned, int
0b2     addl    R17, R14	# int
        nop 	# 10 bytes pad for loops and calls

0c0     B8: #	out( B8 B9 ) <- in( B7 B8 ) Loop( B8-B8 inner main of N57 strip mined) Freq: 10178.5
0c0     leal    R19, [R14 + R14]
0c5     addl    RBX, R19	# int
0c9     addl    RBX, R19	# int
0cd     addl    RBX, R19	# int
0d1     addl    RBX, R19	# int
0d5     leal    R19, [R14 + #6]
0da     addl    R19, R19	# int
0de     leal    R18, [R14 + #4]
0e3     addl    R18, R18	# int
0e7     addl    RBX, R18	# int
0eb     addl    RBX, R18	# int
0ef     addl    RBX, R19	# int
0f3     leal RBX, [RBX + R19 + #336]	# int
0fc     addl    R14, #8	# int
100     cmpl    R14, R17
104     jl,s   B8	# loop end  P=0.990137 C=20785.000000

106     B9: #	out( B7 B10 ) <- in( B8 )  Freq: 100.39
106     movq    R17, [R15 + #1184 (32-bit)]	# ptr
10e     testl   rax, [R17]	# Safepoint: poll for GC        # callchain::leaf @ bci:46 (line 20) L[0]=R13 L[1]=RBX L[2]=R14 L[3]=_
        # OopMap {off=270/0x10e}
112     cmpl    R14, #93
116     jl     B7  P=0.990137 C=20785.000000

11c     B10: #	out( B13 B11 ) <- in( B5 B9 )  Freq: 0.990136
11c     cmpl    R14, #100
120     jge,s   B13  P=0.500000 C=-1.000000

122     B11: #	out( B12 ) <- in( B10 )  Freq: 0.495068
122     # castII of R14
        nop 	# 2 bytes pad for loops and calls

124     B12: #	out( B12 B13 ) <- in( B11 B12 ) Loop( B12-B12 inner post of N313) Freq: 0.990136
124     leal    R16, [R14 + R14]
129     leal RBX, [RBX + R16 + #40]	# int
12f     incl    R14	# int
132     cmpl    R14, #100
136     jl,s   B12	# loop end  P=0.500000 C=20785.000000

138     B13: #	out( N191 ) <- in( B2 B12 B10 )  Freq: 0.999999
138     movl    RAX, RBX	# spill
13a     addq    rsp, 32	# Destroy frame
	popq    rbp
	cmpq    rsp, poll_offset[r15_thread] 
	ja      #safepoint_stub	# Safepoint: poll for GC

14c     ret

14d     B14: #	out( N191 ) <- in( B1 )  Freq: 1.01328e-06
14d     movl    RSI, #-66	# int
152     movl    [rsp + #0], R13	# spill
156     movl    [rsp + #4], RBX	# spill
15a     movl    [rsp + #8], R14	# spill
15f     call,static  wrapper for: uncommon_trap(reason='profile_predicate' action='maybe_recompile' debug_id='0')
        # callchain::leaf @ bci:4 (line 20) L[0]=rsp + #0 L[1]=rsp + #4 L[2]=rsp + #8 L[3]=_
        # OopMap {off=356/0x164}
16c     stop	# ShouldNotReachHere

--------------------------------------------------------------------------------
----------------------------------- Assembly -----------------------------------

Compiled method (c2) 24250   24 %           callchain::leaf @ 4 (51 bytes)
 total in heap  [0x00007f1cb7b2fc90,0x00007f1cb7b30188] = 1272
 relocation     [0x00007f1cb7b2fdf8,0x00007f1cb7b2fe20] = 40
 main code      [0x00007f1cb7b2fe20,0x00007f1cb7b2ffc0] = 416
 stub code      [0x00007f1cb7b2ffc0,0x00007f1cb7b2ffd8] = 24
 oops           [0x00007f1cb7b2ffd8,0x00007f1cb7b2ffe0] = 8
 metadata       [0x00007f1cb7b2ffe0,0x00007f1cb7b30000] = 32
 scopes data    [0x00007f1cb7b30000,0x00007f1cb7b30050] = 80
 scopes pcs     [0x00007f1cb7b30050,0x00007f1cb7b30180] = 304
 dependencies   [0x00007f1cb7b30180,0x00007f1cb7b30188] = 8

[Disassembly]
--------------------------------------------------------------------------------
[Constant Pool (empty)]

--------------------------------------------------------------------------------

[Verified Entry Point]
  # {method} {0x00007f1c5c6054c0} 'leaf' '(I)I' in 'callchain'
 ;; N191: #	out( B1 ) <- BLOCK HEAD IS JUNK  Freq: 1
  0x00007f1cb7b2fe20:   callq  0x00007f1cd48a07ce           ;   {runtime_call os::breakpoint()}
  0x00007f1cb7b2fe25:   nop
  0x00007f1cb7b2fe26:   nop
  0x00007f1cb7b2fe27:   nop
  0x00007f1cb7b2fe28:   nop
  0x00007f1cb7b2fe29:   nop
  0x00007f1cb7b2fe2a:   nop
  0x00007f1cb7b2fe2b:   nop
  0x00007f1cb7b2fe2c:   nop
  0x00007f1cb7b2fe2d:   nop
  0x00007f1cb7b2fe2e:   nop
  0x00007f1cb7b2fe2f:   nop
 ;; B1: #	out( B14 B2 ) <- BLOCK HEAD IS JUNK  Freq: 1
  0x00007f1cb7b2fe30:   mov    %eax,-0x18000(%rsp)
  0x00007f1cb7b2fe37:   push   %rbp
  0x00007f1cb7b2fe38:   mov    %rsp,%rbp
  0x00007f1cb7b2fe3b:   sub    $0x20,%rsp
  0x00007f1cb7b2fe3f:   nop
  0x00007f1cb7b2fe40:   cmpl   $0x0,0x20(%r15)
  0x00007f1cb7b2fe48:   jne    0x00007f1cb7b2ffb6
  0x00007f1cb7b2fe4e:   mov    0x18(%rsi),%r13d
  0x00007f1cb7b2fe52:   mov    0x8(%rsi),%r14d
  0x00007f1cb7b2fe56:   mov    0x10(%rsi),%ebx
  0x00007f1cb7b2fe59:   mov    %rsi,%rdi
  0x00007f1cb7b2fe5c:   movabs $0x7f1cd49b90c6,%r10
  0x00007f1cb7b2fe66:   callq  *%r10
  0x00007f1cb7b2fe69:   nopl   0x0(%rax,%rax,1)             ;*iload_2 {reexecute=0 rethrow=0 return_oop=0}
                                                            ; - callchain::leaf@4 (line 20)
                                                            ;   {other}
  0x00007f1cb7b2fe71:   cmp    $0x270d,%r13d
  0x00007f1cb7b2fe78:   jg     0x00007f1cb7b2ff6d
 ;; B2: #	out( B13 B3 ) <- in( B1 )  Freq: 0.999999
  0x00007f1cb7b2fe7e:   cmp    $0x64,%r14d
  0x00007f1cb7b2fe82:   jge    0x00007f1cb7b2ff58           ;*if_icmpge {reexecute=0 rethrow=0 return_oop=0}
                                                            ; - callchain::leaf@7 (line 20)
 ;; B3: #	out( B4 ) <- in( B2 )  Freq: 0.990136
  0x00007f1cb7b2fe88:   lea    0x1(%r14),%r10d              ;*goto {reexecute=0 rethrow=0 return_oop=0}
                                                            ; - callchain::leaf@46 (line 20)
 ;; B4: #	out( B4 B5 ) <- in( B3 B4 ) Loop( B4-B4 inner pre of N313) Freq: 1.98027
  0x00007f1cb7b2fe8c:   (bad)  
  0x00007f1cb7b2fe8d:   lea    (%r14,%r14,1),%eax
  0x00007f1cb7b2fe91:   (bad)  
  0x00007f1cb7b2fe92:   and    %cl,0x4128035c(%rbp)         ;*iadd {reexecute=0 rethrow=0 return_oop=0}
                                                            ; - callchain::leaf@41 (line 25)
  0x00007f1cb7b2fe98:   inc    %esi                         ;*iinc {reexecute=0 rethrow=0 return_oop=0}
                                                            ; - callchain::leaf@43 (line 20)
  0x00007f1cb7b2fe9a:   cmp    %r10d,%r14d
  0x00007f1cb7b2fe9d:   jl     0x00007f1cb7b2fe8c           ;*if_icmpge {reexecute=0 rethrow=0 return_oop=0}
                                                            ; - callchain::leaf@7 (line 20)
 ;; B5: #	out( B10 B6 ) <- in( B4 )  Freq: 0.990136
  0x00007f1cb7b2fe9f:   cmp    $0x5d,%r14d
  0x00007f1cb7b2fea3:   jge    0x00007f1cb7b2ff3c
 ;; B6: #	out( B7 ) <- in( B5 )  Freq: 0.990135
  0x00007f1cb7b2fea9:   (bad)  
  0x00007f1cb7b2feaa:   adc    %bh,0x1f40(%rax)
  0x00007f1cb7b2feb0:   xor    %r10d,%r10d
 ;; B7: #	out( B8 ) <- in( B6 B9 ) Loop( B7-B9 ) Freq: 100.39
  0x00007f1cb7b2feb3:   (bad)  
  0x00007f1cb7b2feb4:   adc    %bh,0x5d(%rcx)
  0x00007f1cb7b2feba:   (bad)  
  0x00007f1cb7b2febb:   sub    %r14d,%ecx
  0x00007f1cb7b2febe:   cmp    $0x5d,%r14d
  0x00007f1cb7b2fec2:   (bad)  
  0x00007f1cb7b2fec3:   rorl   $0xd5,-0x36(%rdi)
  0x00007f1cb7b2fec7:   adc    %al,0x1f40f9(%rcx)
  0x00007f1cb7b2fecd:   add    %dl,%ch
  0x00007f1cb7b2fecf:   rolb   -0x38(%rdi)
  0x00007f1cb7b2fed2:   (bad)  
  0x00007f1cb7b2fed3:   add    %r14d,%ecx
  0x00007f1cb7b2fed6:   nop
  0x00007f1cb7b2fed7:   nop
  0x00007f1cb7b2fed8:   nop
  0x00007f1cb7b2fed9:   nop
  0x00007f1cb7b2feda:   nop
  0x00007f1cb7b2fedb:   nop
  0x00007f1cb7b2fedc:   nop
  0x00007f1cb7b2fedd:   nop
  0x00007f1cb7b2fede:   nop
  0x00007f1cb7b2fedf:   nop                                 ;*goto {reexecute=0 rethrow=0 return_oop=0}
                                                            ; - callchain::leaf@46 (line 20)
 ;; B8: #	out( B8 B9 ) <- in( B7 B8 ) Loop( B8-B8 inner main of N57 strip mined) Freq: 10178.5
  0x00007f1cb7b2fee0:   (bad)  
  0x00007f1cb7b2fee1:   lea    (%r14,%r14,1),%ebx
  0x00007f1cb7b2fee5:   (bad)  
  0x00007f1cb7b2fee6:   adc    %al,(%rbx)
  0x00007f1cb7b2fee8:   fcmovnbe %st(5),%st
  0x00007f1cb7b2feea:   adc    %al,(%rbx)
  0x00007f1cb7b2feec:   fcmovnbe %st(5),%st
  0x00007f1cb7b2feee:   adc    %al,(%rbx)
  0x00007f1cb7b2fef0:   fcmovnbe %st(5),%st
  0x00007f1cb7b2fef2:   adc    %al,(%rbx)
  0x00007f1cb7b2fef4:   fcmovnbe %st(5),%st
  0x00007f1cb7b2fef6:   lea    0x6(%r14),%ebx
  0x00007f1cb7b2fefa:   (bad)  
  0x00007f1cb7b2fefb:   push   %rax
  0x00007f1cb7b2fefc:   add    %ebx,%ebx
  0x00007f1cb7b2fefe:   (bad)  
  0x00007f1cb7b2feff:   lea    0x4(%r14),%edx
  0x00007f1cb7b2ff03:   (bad)  
  0x00007f1cb7b2ff04:   push   %rax
  0x00007f1cb7b2ff05:   add    %edx,%edx                    ;*iadd {reexecute=0 rethrow=0 return_oop=0}
                                                            ; - Packet::<init>@29 (line 10)
                                                            ; - callchain::leaf@15 (line 21)
  0x00007f1cb7b2ff07:   (bad)  
  0x00007f1cb7b2ff08:   adc    %al,(%rbx)
  0x00007f1cb7b2ff0a:   fcmovbe %st(5),%st
  0x00007f1cb7b2ff0c:   adc    %al,(%rbx)
  0x00007f1cb7b2ff0e:   fcmovbe %st(5),%st
  0x00007f1cb7b2ff10:   adc    %al,(%rbx)
  0x00007f1cb7b2ff12:   fcmovnbe %st(5),%st
  0x00007f1cb7b2ff14:   and    %cl,0x1501b9c(%rbp)
  0x00007f1cb7b2ff1a:   add    %al,(%rax)                   ;*iadd {reexecute=0 rethrow=0 return_oop=0}
                                                            ; - callchain::leaf@41 (line 25)
  0x00007f1cb7b2ff1c:   add    $0x8,%r14d                   ;*iinc {reexecute=0 rethrow=0 return_oop=0}
                                                            ; - callchain::leaf@43 (line 20)
  0x00007f1cb7b2ff20:   (bad)  
  0x00007f1cb7b2ff21:   adc    $0x3b,%al
  0x00007f1cb7b2ff23:   icebp  
  0x00007f1cb7b2ff24:   jl     0x00007f1cb7b2fee0           ;*if_icmpge {reexecute=0 rethrow=0 return_oop=0}
                                                            ; - callchain::leaf@7 (line 20)
 ;; B9: #	out( B7 B10 ) <- in( B8 )  Freq: 100.39
  0x00007f1cb7b2ff26:   (bad)  
  0x00007f1cb7b2ff27:   mov    0x4a0(%r15),%rcx             ; ImmutableOopMap {}
                                                            ;*goto {reexecute=1 rethrow=0 return_oop=0}
                                                            ; - (reexecute) callchain::leaf@46 (line 20)
  0x00007f1cb7b2ff2e:   (bad)                               ;   {poll}
  0x00007f1cb7b2ff2f:   adc    %al,-0x17cbeff(%rbp)
  0x00007f1cb7b2ff35:   pop    %rbp
  0x00007f1cb7b2ff36:   jl     0x00007f1cb7b2feb3
 ;; B10: #	out( B13 B11 ) <- in( B5 B9 )  Freq: 0.990136
  0x00007f1cb7b2ff3c:   cmp    $0x64,%r14d
  0x00007f1cb7b2ff40:   jge    0x00007f1cb7b2ff58
 ;; B11: #	out( B12 ) <- in( B10 )  Freq: 0.495068
  0x00007f1cb7b2ff42:   nop
  0x00007f1cb7b2ff43:   nop                                 ;*goto {reexecute=0 rethrow=0 return_oop=0}
                                                            ; - callchain::leaf@46 (line 20)
 ;; B12: #	out( B12 B13 ) <- in( B11 B12 ) Loop( B12-B12 inner post of N313) Freq: 0.990136
  0x00007f1cb7b2ff44:   (bad)  
  0x00007f1cb7b2ff45:   lea    (%r14,%r14,1),%eax
  0x00007f1cb7b2ff49:   (bad)  
  0x00007f1cb7b2ff4a:   and    %cl,0x4128035c(%rbp)         ;*iadd {reexecute=0 rethrow=0 return_oop=0}
                                                            ; - callchain::leaf@41 (line 25)
  0x00007f1cb7b2ff50:   inc    %esi                         ;*iinc {reexecute=0 rethrow=0 return_oop=0}
                                                            ; - callchain::leaf@43 (line 20)
  0x00007f1cb7b2ff52:   cmp    $0x64,%r14d
  0x00007f1cb7b2ff56:   jl     0x00007f1cb7b2ff44
 ;; B13: #	out( N191 ) <- in( B2 B12 B10 )  Freq: 0.999999
  0x00007f1cb7b2ff58:   mov    %ebx,%eax
  0x00007f1cb7b2ff5a:   add    $0x20,%rsp
  0x00007f1cb7b2ff5e:   pop    %rbp
  0x00007f1cb7b2ff5f:   cmp    0x498(%r15),%rsp             ;   {poll_return}
  0x00007f1cb7b2ff66:   ja     0x00007f1cb7b2ffa0
  0x00007f1cb7b2ff6c:   retq   
 ;; B14: #	out( N191 ) <- in( B1 )  Freq: 1.01328e-06
  0x00007f1cb7b2ff6d:   mov    $0xffffffbe,%esi
  0x00007f1cb7b2ff72:   mov    %r13d,(%rsp)
  0x00007f1cb7b2ff76:   mov    %ebx,0x4(%rsp)
  0x00007f1cb7b2ff7a:   mov    %r14d,0x8(%rsp)
  0x00007f1cb7b2ff7f:   callq  0x00007f1cb79a9fa0           ; ImmutableOopMap {}
                                                            ;*iload_2 {reexecute=0 rethrow=0 return_oop=0}
                                                            ; - callchain::leaf@4 (line 20)
                                                            ;   {runtime_call UncommonTrapBlob}
  0x00007f1cb7b2ff84:   nopl   0x10002f4(%rax,%rax,1)       ;   {other}
  0x00007f1cb7b2ff8c:   movabs $0x7f1cd522ac30,%rdi         ;   {external_word}
  0x00007f1cb7b2ff96:   and    $0xfffffffffffffff0,%rsp
  0x00007f1cb7b2ff9a:   callq  0x00007f1cd473df02           ;   {runtime_call MacroAssembler::debug64(char*, long, long*)}
  0x00007f1cb7b2ff9f:   hlt                                 ;*if_icmpge {reexecute=0 rethrow=0 return_oop=0}
                                                            ; - callchain::leaf@7 (line 20)
  0x00007f1cb7b2ffa0:   movabs $0x7f1cb7b2ff5f,%r10         ;   {internal_word}
  0x00007f1cb7b2ffaa:   mov    %r10,0x4b0(%r15)
  0x00007f1cb7b2ffb1:   jmpq   0x00007f1cb7ac3f20           ;   {runtime_call SafepointBlob}
  0x00007f1cb7b2ffb6:   callq  Stub::nmethod_entry_barrier  ;   {runtime_call StubRoutines (final stubs)}
  0x00007f1cb7b2ffbb:   jmpq   0x00007f1cb7b2fe4e
[Exception Handler]
  0x00007f1cb7b2ffc0:   jmpq   0x00007f1cb7ac4620           ;   {no_reloc}
[Deopt Handler Code]
  0x00007f1cb7b2ffc5:   callq  0x00007f1cb7b2ffca
  0x00007f1cb7b2ffca:   subq   $0x5,(%rsp)
  0x00007f1cb7b2ffcf:   jmpq   0x00007f1cb7ac56e0           ;   {runtime_call DeoptimizationBlob}
  0x00007f1cb7b2ffd4:   hlt    
  0x00007f1cb7b2ffd5:   hlt    
  0x00007f1cb7b2ffd6:   hlt    
  0x00007f1cb7b2ffd7:   hlt    
--------------------------------------------------------------------------------
[/Disassembly]
- - - - - - - - - - - - - - - - - - - - - - - - - - - - - - - - - - - - - - - - 
Oops:
  0x00007f1cb7b2ffd8:   0x000000011f81bf60 a 'jdk/internal/loader/ClassLoaders$AppClassLoader'{0x000000011f81bf60}
- - - - - - - - - - - - - - - - - - - - - - - - - - - - - - - - - - - - - - - - 
Metadata:
  0x00007f1cb7b2ffe0:   0x00007f1c5c6054c0 {method} {0x00007f1c5c6054c0} 'leaf' '(I)I' in 'callchain'
  0x00007f1cb7b2ffe8:   0x00007f1c5c605c60 {method} {0x00007f1c5c605c60} '<init>' '(I)V' in 'Packet'
  0x00007f1cb7b2fff0:   0x00007f1c5c605d20 {method} {0x00007f1c5c605d20} 'accum' '()I' in 'Packet'
  0x00007f1cb7b2fff8:   0x00000000380c4a10 'Packet'
- - - - - - - - - - - - - - - - - - - - - - - - - - - - - - - - - - - - - - - - 
pc-bytecode offsets:
PcDesc(pc=0x00007f1cb7b2fe1f offset=ffffffff bits=0):
PcDesc(pc=0x00007f1cb7b2fe71 offset=51 bits=0):
   callchain::leaf@4 (line 20)
PcDesc(pc=0x00007f1cb7b2fe88 offset=68 bits=0):
   callchain::leaf@7 (line 20)
PcDesc(pc=0x00007f1cb7b2fe8c offset=6c bits=0):
   callchain::leaf@46 (line 20)
PcDesc(pc=0x00007f1cb7b2fe97 offset=77 bits=0):
   callchain::leaf@41 (line 25)
PcDesc(pc=0x00007f1cb7b2fe9a offset=7a bits=0):
   callchain::leaf@43 (line 20)
PcDesc(pc=0x00007f1cb7b2fe9f offset=7f bits=0):
   callchain::leaf@7 (line 20)
PcDesc(pc=0x00007f1cb7b2fee0 offset=c0 bits=0):
   callchain::leaf@46 (line 20)
PcDesc(pc=0x00007f1cb7b2ff07 offset=e7 bits=0):
   Packet::<init>@29 (line 10)
   callchain::leaf@15 (line 21)
PcDesc(pc=0x00007f1cb7b2ff1c offset=fc bits=0):
   callchain::leaf@41 (line 25)
PcDesc(pc=0x00007f1cb7b2ff20 offset=100 bits=0):
   callchain::leaf@43 (line 20)
PcDesc(pc=0x00007f1cb7b2ff26 offset=106 bits=0):
   callchain::leaf@7 (line 20)
PcDesc(pc=0x00007f1cb7b2ff2e offset=10e bits=1):
   callchain::leaf@46 (line 20)  reexecute=true
   Locals
    - l0: reg r13 [26],int
    - l1: reg rbx [6],int
    - l2: reg r14 [28],int
    - l3: empty
PcDesc(pc=0x00007f1cb7b2ff44 offset=124 bits=0):
   callchain::leaf@46 (line 20)
PcDesc(pc=0x00007f1cb7b2ff4f offset=12f bits=0):
   callchain::leaf@41 (line 25)
PcDesc(pc=0x00007f1cb7b2ff52 offset=132 bits=0):
   callchain::leaf@43 (line 20)
PcDesc(pc=0x00007f1cb7b2ff84 offset=164 bits=0):
   callchain::leaf@4 (line 20)
   Locals
    - l0: stack[0]
    - l1: stack[4]
    - l2: stack[8]
    - l3: empty
PcDesc(pc=0x00007f1cb7b2ffa0 offset=180 bits=0):
   callchain::leaf@7 (line 20)
PcDesc(pc=0x00007f1cb7b2ffd9 offset=1b9 bits=0):
- - - - - - - - - - - - - - - - - - - - - - - - - - - - - - - - - - - - - - - - 
oop maps:ImmutableOopMapSet contains 2 OopMaps

ImmutableOopMap {} pc offsets: 270 356 
- - - - - - - - - - - - - - - - - - - - - - - - - - - - - - - - - - - - - - - - 
scopes:
ScopeDesc(pc=0x00007f1cb7b2fe71 offset=51):
   callchain::leaf@4 (line 20)
ScopeDesc(pc=0x00007f1cb7b2fe88 offset=68):
   callchain::leaf@7 (line 20)
ScopeDesc(pc=0x00007f1cb7b2fe8c offset=6c):
   callchain::leaf@46 (line 20)
ScopeDesc(pc=0x00007f1cb7b2fe97 offset=77):
   callchain::leaf@41 (line 25)
ScopeDesc(pc=0x00007f1cb7b2fe9a offset=7a):
   callchain::leaf@43 (line 20)
ScopeDesc(pc=0x00007f1cb7b2fe9f offset=7f):
   callchain::leaf@7 (line 20)
ScopeDesc(pc=0x00007f1cb7b2fee0 offset=c0):
   callchain::leaf@46 (line 20)
ScopeDesc(pc=0x00007f1cb7b2ff07 offset=e7):
   Packet::<init>@29 (line 10)
ScopeDesc(pc=0x00007f1cb7b2ff07 offset=e7):
   callchain::leaf@15 (line 21)
ScopeDesc(pc=0x00007f1cb7b2ff1c offset=fc):
   callchain::leaf@41 (line 25)
ScopeDesc(pc=0x00007f1cb7b2ff20 offset=100):
   callchain::leaf@43 (line 20)
ScopeDesc(pc=0x00007f1cb7b2ff26 offset=106):
   callchain::leaf@7 (line 20)
ScopeDesc(pc=0x00007f1cb7b2ff2e offset=10e):
   callchain::leaf@46 (line 20)  reexecute=true
   Locals
    - l0: reg r13 [26],int
    - l1: reg rbx [6],int
    - l2: reg r14 [28],int
    - l3: empty
ScopeDesc(pc=0x00007f1cb7b2ff44 offset=124):
   callchain::leaf@46 (line 20)
ScopeDesc(pc=0x00007f1cb7b2ff4f offset=12f):
   callchain::leaf@41 (line 25)
ScopeDesc(pc=0x00007f1cb7b2ff52 offset=132):
   callchain::leaf@43 (line 20)
ScopeDesc(pc=0x00007f1cb7b2ff84 offset=164):
   callchain::leaf@4 (line 20)
   Locals
    - l0: stack[0]
    - l1: stack[4]
    - l2: stack[8]
    - l3: empty
ScopeDesc(pc=0x00007f1cb7b2ffa0 offset=180):
   callchain::leaf@7 (line 20)
- - - - - - - - - - - - - - - - - - - - - - - - - - - - - - - - - - - - - - - - 
relocations:
         @0x00007f1cb7b2fdf8: 3100
relocInfo@0x00007f1cb7b2fdf8 [type=6(runtime_call) addr=0x00007f1cb7b2fe20 offset=0 format=1] | [destination=0x00007f1cd48a07ce]
         @0x00007f1cb7b2fdfa: 8049
relocInfo@0x00007f1cb7b2fdfa [type=16(post_call_nop) addr=0x00007f1cb7b2fe69 offset=73]
         @0x00007f1cb7b2fdfc: 50c5
relocInfo@0x00007f1cb7b2fdfc [type=10(poll) addr=0x00007f1cb7b2ff2e offset=197]
         @0x00007f1cb7b2fdfe: 5831
relocInfo@0x00007f1cb7b2fdfe [type=11(poll_return) addr=0x00007f1cb7b2ff5f offset=49]
         @0x00007f1cb7b2fe00: 3120
relocInfo@0x00007f1cb7b2fe00 [type=6(runtime_call) addr=0x00007f1cb7b2ff7f offset=32 format=1] | [destination=0x00007f1cb79a9fa0]
         @0x00007f1cb7b2fe02: 8005
relocInfo@0x00007f1cb7b2fe02 [type=16(post_call_nop) addr=0x00007f1cb7b2ff84 offset=5]
         @0x00007f1cb7b2fe04: 7c03d522ac307f1c3808
relocInfo@0x00007f1cb7b2fe0c [type=7(external_word) addr=0x00007f1cb7b2ff8c offset=8 data={d522ac307f1c}] | [target=0x00007f1cd522ac30]
         @0x00007f1cb7b2fe0e: 310e
relocInfo@0x00007f1cb7b2fe0e [type=6(runtime_call) addr=0x00007f1cb7b2ff9a offset=14 format=1] | [destination=0x00007f1cd473df02]
         @0x00007f1cb7b2fe10: 78414006
relocInfo@0x00007f1cb7b2fe12 [type=8(internal_word) addr=0x00007f1cb7b2ffa0 offset=6 data=65] | [target=0x00007f1cb7b2ff5f]
         @0x00007f1cb7b2fe14: 3111
relocInfo@0x00007f1cb7b2fe14 [type=6(runtime_call) addr=0x00007f1cb7b2ffb1 offset=17 format=1] | [destination=0x00007f1cb7ac3f20]
         @0x00007f1cb7b2fe16: 3105
relocInfo@0x00007f1cb7b2fe16 [type=6(runtime_call) addr=0x00007f1cb7b2ffb6 offset=5 format=1] | [destination=0x00007f1cb7a08dc0]
         @0x00007f1cb7b2fe18: 000a
relocInfo@0x00007f1cb7b2fe18 [type=0(none) addr=0x00007f1cb7b2ffc0 offset=10]
         @0x00007f1cb7b2fe1a: 3100
relocInfo@0x00007f1cb7b2fe1a [type=6(runtime_call) addr=0x00007f1cb7b2ffc0 offset=0 format=1] | [destination=0x00007f1cb7ac4620]
         @0x00007f1cb7b2fe1c: 310f
relocInfo@0x00007f1cb7b2fe1c [type=6(runtime_call) addr=0x00007f1cb7b2ffcf offset=15 format=1] | [destination=0x00007f1cb7ac56e0]
         @0x00007f1cb7b2fe1e: 0000
relocInfo@0x00007f1cb7b2fe1e [type=0(none) addr=0x00007f1cb7b2ffcf offset=0]
         @0x00007f1cb7b2fe20: 
- - - - - - - - - - - - - - - - - - - - - - - - - - - - - - - - - - - - - - - - 
Dependencies:
Dependency of type unique_concrete_method_4
  context = Packet
  method  = {method} {0x00007f1c5c605d20} 'accum' '()I' in 'Packet'
  class   = Packet
  method  = {method} {0x00007f1c5c605d20} 'accum' '()I' in 'Packet'
   [nmethod<=klass]Packet
- - - - - - - - - - - - - - - - - - - - - - - - - - - - - - - - - - - - - - - - 
ExceptionHandlerTable (size = 0 bytes)
- - - - - - - - - - - - - - - - - - - - - - - - - - - - - - - - - - - - - - - - 
ImplicitExceptionTable is empty
- - - - - - - - - - - - - - - - - - - - - - - - - - - - - - - - - - - - - - - - 
Recorded oops:
#0: 0x0000000000000000 nullptr-oop
#1: 0x000000011f81bf60 a 'jdk/internal/loader/ClassLoaders$AppClassLoader'{0x000000011f81bf60}
- - - - - - - - - - - - - - - - - - - - - - - - - - - - - - - - - - - - - - - - 
Recorded metadata:
#0: 0x0000000000000000 nullptr-oop
#1: 0x00007f1c5c6054c0 {method} {0x00007f1c5c6054c0} 'leaf' '(I)I' in 'callchain'
#2: 0x00007f1c5c605c60 {method} {0x00007f1c5c605c60} '<init>' '(I)V' in 'Packet'
#3: 0x00007f1c5c605d20 {method} {0x00007f1c5c605d20} 'accum' '()I' in 'Packet'
#4: 0x00000000380c4a10 'Packet'
- - - - - - - - - - - - - - - - - - - - - - - - - - - - - - - - - - - - - - - - 

============================= C2-compiled nmethod ==============================
#r050 rsi   : parm 0: int
# -- Old rsp -- Framesize: 48 --
#r623 rsp+44: in_preserve
#r622 rsp+40: return address
#r621 rsp+36: in_preserve
#r620 rsp+32: saved fp register
#r619 rsp+28: pad2, stack alignment
#r618 rsp+24: pad2, stack alignment
#r617 rsp+20: Fixed slot 1
#r616 rsp+16: Fixed slot 0
#r627 rsp+12: spill
#r626 rsp+ 8: spill
#r625 rsp+ 4: spill
#r624 rsp+ 0: spill
#
----------------------- MetaData before Compile_id = 25 ------------------------
{method}
 - this oop:          0x00007f1c5c6054c0
 - method holder:     'callchain'
 - constants:         0x00007f1c5c605058 constant pool [77]/operands[5] {0x00007f1c5c605058} for 'callchain' cache=0x00007f1c5c6059a8
 - access:            0x9  public static 
 - flags:             0x6080  queued_for_compilation has_loops_flag has_loops_flag_init 
 - name:              'leaf'
 - signature:         '(I)I'
 - max stack:         4
 - max locals:        4
 - size of params:    1
 - method size:       14
 - vtable index:      -2
 - i2i entry:         0x00007f1cb79afbe0
 - adapters:          AHE@0x00007f1cbc24c460: 0xa i2c: 0x00007f1cb7ac0fe0 c2i: 0x00007f1cb7ac1099 c2iUV: 0x00007f1cb7ac1074 c2iNCI: 0x00007f1cb7ac10d3
 - compiled entry     0x00007f1cb7ac1099
 - code size:         51
 - code start:        0x00007f1c5c605480
 - code end (excl):   0x00007f1c5c6054b3
 - method data:       0x00007f1c5c606348
 - checked ex length: 0
 - linenumber start:  0x00007f1c5c6054b3
 - localvar length:   0

------------------------ OptoAssembly for Compile_id = 25 -----------------------
#
#  int ( int )
#
000     N1: #	out( B1 ) <- in( B8 B7 )  Freq: 1

000     B1: #	out( B8 B2 ) <- BLOCK HEAD IS JUNK  Freq: 1
000     # stack bang (152 bytes)
	pushq   rbp	# Save rbp
	movq    rbp, rsp	# Save the caller's SP into rbp
	subq    rsp, #32	# Create frame

01e     movl    R16, RSI	# spill
022     cmpl    RSI, #9997
028     jg     B8  P=0.000001 C=-1.000000

02e     B2: #	out( B4 ) <- in( B1 )  Freq: 0.999999
02e     movl    RAX, #40	# int
033     movl    R10, #1	# int
039     jmp,s   B4
        nop 	# 5 bytes pad for loops and calls

040     B3: #	out( B4 ) <- in( B4 ) top-of-loop Freq: 100.39
040     movl    R10, R16	# spill

044     B4: #	out( B3 B5 ) <- in( B2 B3 ) Loop( B4-B3 inner main of N29) Freq: 101.39
044     leal    R17, [R10 + R10]
049     addl    RAX, R17	# int
04d     addl    RAX, R17	# int
051     addl    RAX, R17	# int
055     addl    RAX, R17	# int
059     leal    R18, [R10 + #4]
05e     addl    R18, R18	# int
062     addl    RAX, R18	# int
066     addl    RAX, R18	# int
06a     addl    RAX, R17	# int
06e     leal    R17, [R10 + #7]
073     addl    R17, R17	# int
077     leal RAX, [R17 + RAX + #346]	# int
080     leal    R16, [R10 + #8]
085     cmpl    R16, #97
08a     jl,s   B3	# loop end  P=0.990137 C=20580.000000

08c     B5: #	out( B6 ) <- in( B4 )  Freq: 0.999999
08c     # castII of R10
08c     addl    R10, #8	# int

090     B6: #	out( B6 B7 ) <- in( B5 B6 ) Loop( B6-B6 inner post of N277) Freq: 2
090     leal    R16, [R10 + R10]
095     leal RAX, [R16 + RAX + #40]	# int
09b     incl    R10	# int
09e     cmpl    R10, #100
0a2     jl,s   B6	# loop end  P=0.500000 C=20580.000000

0a4     B7: #	out( N1 ) <- in( B6 )  Freq: 0.999999
0a4     addq    rsp, 32	# Destroy frame
	popq    rbp
	cmpq    rsp, poll_offset[r15_thread] 
	ja      #safepoint_stub	# Safepoint: poll for GC

0b6     ret

0b7     B8: #	out( N1 ) <- in( B1 )  Freq: 1.01328e-06
0b7     movl    RSI, #-138	# int
0bc     movl    [rsp + #0], R16	# spill
        nop 	# 2 bytes pad for loops and calls
0c3     call,static  wrapper for: uncommon_trap(reason='predicate' action='maybe_recompile' debug_id='0')
        # callchain::leaf @ bci:7 (line 20) L[0]=rsp + #0 L[1]=#0 L[2]=#0 L[3]=_ STK[0]=#0 STK[1]=#100
        # OopMap {off=200/0xc8}
0d0     stop	# ShouldNotReachHere

--------------------------------------------------------------------------------
----------------------------------- Assembly -----------------------------------

Compiled method (c2) 24836   25             callchain::leaf (51 bytes)
 total in heap  [0x00007f1cb7b30210,0x00007f1cb7b30600] = 1008
 relocation     [0x00007f1cb7b30378,0x00007f1cb7b30398] = 32
 main code      [0x00007f1cb7b303a0,0x00007f1cb7b304a8] = 264
 stub code      [0x00007f1cb7b304a8,0x00007f1cb7b304c0] = 24
 oops           [0x00007f1cb7b304c0,0x00007f1cb7b304c8] = 8
 metadata       [0x00007f1cb7b304c8,0x00007f1cb7b304e8] = 32
 scopes data    [0x00007f1cb7b304e8,0x00007f1cb7b30528] = 64
 scopes pcs     [0x00007f1cb7b30528,0x00007f1cb7b305f8] = 208
 dependencies   [0x00007f1cb7b305f8,0x00007f1cb7b30600] = 8

[Disassembly]
--------------------------------------------------------------------------------
[Constant Pool (empty)]

--------------------------------------------------------------------------------

[Verified Entry Point]
  # {method} {0x00007f1c5c6054c0} 'leaf' '(I)I' in 'callchain'
  # parm0:    rsi       = int
  #           [sp+0x30]  (sp of caller)
 ;; N1: #	out( B1 ) <- in( B8 B7 )  Freq: 1
 ;; B1: #	out( B8 B2 ) <- BLOCK HEAD IS JUNK  Freq: 1
  0x00007f1cb7b303a0:   mov    %eax,-0x18000(%rsp)
  0x00007f1cb7b303a7:   push   %rbp
  0x00007f1cb7b303a8:   mov    %rsp,%rbp
  0x00007f1cb7b303ab:   sub    $0x20,%rsp
  0x00007f1cb7b303af:   nop
  0x00007f1cb7b303b0:   cmpl   $0x0,0x20(%r15)
  0x00007f1cb7b303b8:   jne    0x00007f1cb7b3049a           ;*synchronization entry
                                                            ; - callchain::leaf@-1 (line 19)
  0x00007f1cb7b303be:   (bad)  
  0x00007f1cb7b303bf:   rex mov %esi,%eax
  0x00007f1cb7b303c2:   cmp    $0x270d,%esi
  0x00007f1cb7b303c8:   jg     0x00007f1cb7b30457
 ;; B2: #	out( B4 ) <- in( B1 )  Freq: 0.999999
  0x00007f1cb7b303ce:   mov    $0x28,%eax
  0x00007f1cb7b303d3:   mov    $0x1,%r10d
  0x00007f1cb7b303d9:   jmp    0x00007f1cb7b303e4
  0x00007f1cb7b303db:   nop
  0x00007f1cb7b303dc:   nop
  0x00007f1cb7b303dd:   nop
  0x00007f1cb7b303de:   nop
  0x00007f1cb7b303df:   nop
 ;; B3: #	out( B4 ) <- in( B4 ) top-of-loop Freq: 100.39
  0x00007f1cb7b303e0:   (bad)  
  0x00007f1cb7b303e1:   adc    $0x8b,%al
  0x00007f1cb7b303e3:   rcl    %ch                          ;*new {reexecute=0 rethrow=0 return_oop=0}
                                                            ; - callchain::leaf@10 (line 21)
  0x00007f1cb7b303e5:   lea    (%r10,%r10,1),%ecx
  0x00007f1cb7b303e9:   (bad)  
  0x00007f1cb7b303ea:   adc    %al,(%rbx)
  0x00007f1cb7b303ec:   rcl    $0x10,%ebp
  0x00007f1cb7b303ef:   add    %ecx,%eax
  0x00007f1cb7b303f1:   (bad)  
  0x00007f1cb7b303f2:   adc    %al,(%rbx)
  0x00007f1cb7b303f4:   rcl    $0x10,%ebp
  0x00007f1cb7b303f7:   add    %ecx,%eax
  0x00007f1cb7b303f9:   (bad)  
  0x00007f1cb7b303fa:   lea    0x4(%r10),%edx
  0x00007f1cb7b303fe:   (bad)  
  0x00007f1cb7b303ff:   push   %rax
  0x00007f1cb7b30400:   add    %edx,%edx                    ;*iadd {reexecute=0 rethrow=0 return_oop=0}
                                                            ; - Packet::<init>@29 (line 10)
                                                            ; - callchain::leaf@15 (line 21)
  0x00007f1cb7b30402:   (bad)  
  0x00007f1cb7b30403:   adc    %al,(%rbx)
  0x00007f1cb7b30405:   retq   $0x10d5
  0x00007f1cb7b30408:   add    %edx,%eax
  0x00007f1cb7b3040a:   (bad)  
  0x00007f1cb7b3040b:   adc    %al,(%rbx)
  0x00007f1cb7b3040d:   rcl    $0x41,%ebp
  0x00007f1cb7b30410:   lea    0x7(%rdx),%ecx
  0x00007f1cb7b30413:   (bad)  
  0x00007f1cb7b30414:   push   %rax
  0x00007f1cb7b30415:   add    %ecx,%ecx
  0x00007f1cb7b30417:   (bad)  
  0x00007f1cb7b30418:   adc    %cl,0x15a0184(%rbp)
  0x00007f1cb7b3041e:   add    %al,(%rax)                   ;*iadd {reexecute=0 rethrow=0 return_oop=0}
                                                            ; - callchain::leaf@41 (line 25)
  0x00007f1cb7b30420:   (bad)  
  0x00007f1cb7b30421:   lea    0x8(%r10),%eax
  0x00007f1cb7b30425:   (bad)  
  0x00007f1cb7b30426:   adc    %al,-0x4b839e08(%rbx)        ;*if_icmpge {reexecute=0 rethrow=0 return_oop=0}
                                                            ; - callchain::leaf@7 (line 20)
 ;; B5: #	out( B6 ) <- in( B4 )  Freq: 0.999999
  0x00007f1cb7b3042c:   add    $0x8,%r10d                   ;*new {reexecute=0 rethrow=0 return_oop=0}
                                                            ; - callchain::leaf@10 (line 21)
 ;; B6: #	out( B6 B7 ) <- in( B5 B6 ) Loop( B6-B6 inner post of N277) Freq: 2
  0x00007f1cb7b30430:   (bad)  
  0x00007f1cb7b30431:   lea    (%r10,%r10,1),%eax
  0x00007f1cb7b30435:   (bad)  
  0x00007f1cb7b30436:   adc    %cl,0x41280044(%rbp)         ;*iadd {reexecute=0 rethrow=0 return_oop=0}
                                                            ; - callchain::leaf@41 (line 25)
  0x00007f1cb7b3043c:   inc    %edx                         ;*iinc {reexecute=0 rethrow=0 return_oop=0}
                                                            ; - callchain::leaf@43 (line 20)
  0x00007f1cb7b3043e:   cmp    $0x64,%r10d
  0x00007f1cb7b30442:   jl     0x00007f1cb7b30430           ;*if_icmpge {reexecute=0 rethrow=0 return_oop=0}
                                                            ; - callchain::leaf@7 (line 20)
 ;; B7: #	out( N1 ) <- in( B6 )  Freq: 0.999999
  0x00007f1cb7b30444:   add    $0x20,%rsp
  0x00007f1cb7b30448:   pop    %rbp
  0x00007f1cb7b30449:   cmp    0x498(%r15),%rsp             ;   {poll_return}
  0x00007f1cb7b30450:   ja     0x00007f1cb7b30484
  0x00007f1cb7b30456:   retq   
 ;; B8: #	out( N1 ) <- in( B1 )  Freq: 1.01328e-06
  0x00007f1cb7b30457:   mov    $0xffffff76,%esi
  0x00007f1cb7b3045c:   (bad)  
  0x00007f1cb7b3045d:   rex mov %eax,(%rsp)
  0x00007f1cb7b30461:   nop
  0x00007f1cb7b30462:   nop
  0x00007f1cb7b30463:   callq  0x00007f1cb79a9fa0           ; ImmutableOopMap {}
                                                            ;*if_icmpge {reexecute=1 rethrow=0 return_oop=0}
                                                            ; - (reexecute) callchain::leaf@7 (line 20)
                                                            ;   {runtime_call UncommonTrapBlob}
  0x00007f1cb7b30468:   nopl   0x258(%rax,%rax,1)           ;   {other}
  0x00007f1cb7b30470:   movabs $0x7f1cd522ac30,%rdi         ;   {external_word}
  0x00007f1cb7b3047a:   and    $0xfffffffffffffff0,%rsp
  0x00007f1cb7b3047e:   callq  0x00007f1cd473df02           ;   {runtime_call MacroAssembler::debug64(char*, long, long*)}
  0x00007f1cb7b30483:   hlt                                 ;*if_icmpge {reexecute=0 rethrow=0 return_oop=0}
                                                            ; - callchain::leaf@7 (line 20)
  0x00007f1cb7b30484:   movabs $0x7f1cb7b30449,%r10         ;   {internal_word}
  0x00007f1cb7b3048e:   mov    %r10,0x4b0(%r15)
  0x00007f1cb7b30495:   jmpq   0x00007f1cb7ac3f20           ;   {runtime_call SafepointBlob}
  0x00007f1cb7b3049a:   callq  Stub::nmethod_entry_barrier  ;   {runtime_call StubRoutines (final stubs)}
  0x00007f1cb7b3049f:   jmpq   0x00007f1cb7b303be
  0x00007f1cb7b304a4:   hlt    
  0x00007f1cb7b304a5:   hlt    
  0x00007f1cb7b304a6:   hlt    
  0x00007f1cb7b304a7:   hlt    
[Exception Handler]
  0x00007f1cb7b304a8:   jmpq   0x00007f1cb7ac4620           ;   {no_reloc}
[Deopt Handler Code]
  0x00007f1cb7b304ad:   callq  0x00007f1cb7b304b2
  0x00007f1cb7b304b2:   subq   $0x5,(%rsp)
  0x00007f1cb7b304b7:   jmpq   0x00007f1cb7ac56e0           ;   {runtime_call DeoptimizationBlob}
  0x00007f1cb7b304bc:   hlt    
  0x00007f1cb7b304bd:   hlt    
  0x00007f1cb7b304be:   hlt    
  0x00007f1cb7b304bf:   hlt    
--------------------------------------------------------------------------------
[/Disassembly]
- - - - - - - - - - - - - - - - - - - - - - - - - - - - - - - - - - - - - - - - 
Oops:
  0x00007f1cb7b304c0:   0x000000011f81bf60 a 'jdk/internal/loader/ClassLoaders$AppClassLoader'{0x000000011f81bf60}
- - - - - - - - - - - - - - - - - - - - - - - - - - - - - - - - - - - - - - - - 
Metadata:
  0x00007f1cb7b304c8:   0x00007f1c5c6054c0 {method} {0x00007f1c5c6054c0} 'leaf' '(I)I' in 'callchain'
  0x00007f1cb7b304d0:   0x00007f1c5c605c60 {method} {0x00007f1c5c605c60} '<init>' '(I)V' in 'Packet'
  0x00007f1cb7b304d8:   0x00007f1c5c605d20 {method} {0x00007f1c5c605d20} 'accum' '()I' in 'Packet'
  0x00007f1cb7b304e0:   0x00000000380c4a10 'Packet'
- - - - - - - - - - - - - - - - - - - - - - - - - - - - - - - - - - - - - - - - 
pc-bytecode offsets:
PcDesc(pc=0x00007f1cb7b3039f offset=ffffffff bits=0):
PcDesc(pc=0x00007f1cb7b303be offset=1e bits=0):
   callchain::leaf@-1 (line 19)
PcDesc(pc=0x00007f1cb7b303e4 offset=44 bits=0):
   callchain::leaf@10 (line 21)
PcDesc(pc=0x00007f1cb7b30402 offset=62 bits=0):
   Packet::<init>@29 (line 10)
   callchain::leaf@15 (line 21)
PcDesc(pc=0x00007f1cb7b30420 offset=80 bits=0):
   callchain::leaf@41 (line 25)
PcDesc(pc=0x00007f1cb7b3042c offset=8c bits=0):
   callchain::leaf@7 (line 20)
PcDesc(pc=0x00007f1cb7b30430 offset=90 bits=0):
   callchain::leaf@10 (line 21)
PcDesc(pc=0x00007f1cb7b3043b offset=9b bits=0):
   callchain::leaf@41 (line 25)
PcDesc(pc=0x00007f1cb7b3043e offset=9e bits=0):
   callchain::leaf@43 (line 20)
PcDesc(pc=0x00007f1cb7b30444 offset=a4 bits=0):
   callchain::leaf@7 (line 20)
PcDesc(pc=0x00007f1cb7b30468 offset=c8 bits=1):
   callchain::leaf@7 (line 20)  reexecute=true
   Locals
    - l0: stack[0]
    - l1: 0
    - l2: 0
    - l3: empty
   Expression stack
    - @0: 0
    - @1: 100
PcDesc(pc=0x00007f1cb7b30484 offset=e4 bits=0):
   callchain::leaf@7 (line 20)
PcDesc(pc=0x00007f1cb7b304c1 offset=121 bits=0):
- - - - - - - - - - - - - - - - - - - - - - - - - - - - - - - - - - - - - - - - 
oop maps:ImmutableOopMapSet contains 1 OopMaps

ImmutableOopMap {} pc offsets: 200 
- - - - - - - - - - - - - - - - - - - - - - - - - - - - - - - - - - - - - - - - 
scopes:
ScopeDesc(pc=0x00007f1cb7b303be offset=1e):
   callchain::leaf@-1 (line 19)
ScopeDesc(pc=0x00007f1cb7b303e4 offset=44):
   callchain::leaf@10 (line 21)
ScopeDesc(pc=0x00007f1cb7b30402 offset=62):
   Packet::<init>@29 (line 10)
ScopeDesc(pc=0x00007f1cb7b30402 offset=62):
   callchain::leaf@15 (line 21)
ScopeDesc(pc=0x00007f1cb7b30420 offset=80):
   callchain::leaf@41 (line 25)
ScopeDesc(pc=0x00007f1cb7b3042c offset=8c):
   callchain::leaf@7 (line 20)
ScopeDesc(pc=0x00007f1cb7b30430 offset=90):
   callchain::leaf@10 (line 21)
ScopeDesc(pc=0x00007f1cb7b3043b offset=9b):
   callchain::leaf@41 (line 25)
ScopeDesc(pc=0x00007f1cb7b3043e offset=9e):
   callchain::leaf@43 (line 20)
ScopeDesc(pc=0x00007f1cb7b30444 offset=a4):
   callchain::leaf@7 (line 20)
ScopeDesc(pc=0x00007f1cb7b30468 offset=c8):
   callchain::leaf@7 (line 20)  reexecute=true
   Locals
    - l0: stack[0]
    - l1: 0
    - l2: 0
    - l3: empty
   Expression stack
    - @0: 0
    - @1: 100
ScopeDesc(pc=0x00007f1cb7b30484 offset=e4):
   callchain::leaf@7 (line 20)
- - - - - - - - - - - - - - - - - - - - - - - - - - - - - - - - - - - - - - - - 
relocations:
         @0x00007f1cb7b30378: 58a9
relocInfo@0x00007f1cb7b30378 [type=11(poll_return) addr=0x00007f1cb7b30449 offset=169]
         @0x00007f1cb7b3037a: 311a
relocInfo@0x00007f1cb7b3037a [type=6(runtime_call) addr=0x00007f1cb7b30463 offset=26 format=1] | [destination=0x00007f1cb79a9fa0]
         @0x00007f1cb7b3037c: 8005
relocInfo@0x00007f1cb7b3037c [type=16(post_call_nop) addr=0x00007f1cb7b30468 offset=5]
         @0x00007f1cb7b3037e: 7c03d522ac307f1c3808
relocInfo@0x00007f1cb7b30386 [type=7(external_word) addr=0x00007f1cb7b30470 offset=8 data={d522ac307f1c}] | [target=0x00007f1cd522ac30]
         @0x00007f1cb7b30388: 310e
relocInfo@0x00007f1cb7b30388 [type=6(runtime_call) addr=0x00007f1cb7b3047e offset=14 format=1] | [destination=0x00007f1cd473df02]
         @0x00007f1cb7b3038a: 783b4006
relocInfo@0x00007f1cb7b3038c [type=8(internal_word) addr=0x00007f1cb7b30484 offset=6 data=59] | [target=0x00007f1cb7b30449]
         @0x00007f1cb7b3038e: 3111
relocInfo@0x00007f1cb7b3038e [type=6(runtime_call) addr=0x00007f1cb7b30495 offset=17 format=1] | [destination=0x00007f1cb7ac3f20]
         @0x00007f1cb7b30390: 3105
relocInfo@0x00007f1cb7b30390 [type=6(runtime_call) addr=0x00007f1cb7b3049a offset=5 format=1] | [destination=0x00007f1cb7a08dc0]
         @0x00007f1cb7b30392: 000e
relocInfo@0x00007f1cb7b30392 [type=0(none) addr=0x00007f1cb7b304a8 offset=14]
         @0x00007f1cb7b30394: 3100
relocInfo@0x00007f1cb7b30394 [type=6(runtime_call) addr=0x00007f1cb7b304a8 offset=0 format=1] | [destination=0x00007f1cb7ac4620]
         @0x00007f1cb7b30396: 310f
relocInfo@0x00007f1cb7b30396 [type=6(runtime_call) addr=0x00007f1cb7b304b7 offset=15 format=1] | [destination=0x00007f1cb7ac56e0]
         @0x00007f1cb7b30398: 
- - - - - - - - - - - - - - - - - - - - - - - - - - - - - - - - - - - - - - - - 
Dependencies:
Dependency of type unique_concrete_method_4
  context = Packet
  method  = {method} {0x00007f1c5c605d20} 'accum' '()I' in 'Packet'
  class   = Packet
  method  = {method} {0x00007f1c5c605d20} 'accum' '()I' in 'Packet'
   [nmethod<=klass]Packet
- - - - - - - - - - - - - - - - - - - - - - - - - - - - - - - - - - - - - - - - 
ExceptionHandlerTable (size = 0 bytes)
- - - - - - - - - - - - - - - - - - - - - - - - - - - - - - - - - - - - - - - - 
ImplicitExceptionTable is empty
- - - - - - - - - - - - - - - - - - - - - - - - - - - - - - - - - - - - - - - - 
Recorded oops:
#0: 0x0000000000000000 nullptr-oop
#1: 0x000000011f81bf60 a 'jdk/internal/loader/ClassLoaders$AppClassLoader'{0x000000011f81bf60}
- - - - - - - - - - - - - - - - - - - - - - - - - - - - - - - - - - - - - - - - 
Recorded metadata:
#0: 0x0000000000000000 nullptr-oop
#1: 0x00007f1c5c6054c0 {method} {0x00007f1c5c6054c0} 'leaf' '(I)I' in 'callchain'
#2: 0x00007f1c5c605c60 {method} {0x00007f1c5c605c60} '<init>' '(I)V' in 'Packet'
#3: 0x00007f1c5c605d20 {method} {0x00007f1c5c605d20} 'accum' '()I' in 'Packet'
#4: 0x00000000380c4a10 'Packet'
- - - - - - - - - - - - - - - - - - - - - - - - - - - - - - - - - - - - - - - - 

============================= C2-compiled nmethod ==============================
#r050 rsi   : parm 0: int
# -- Old rsp -- Framesize: 64 --
#r623 rsp+60: in_preserve
#r622 rsp+56: return address
#r621 rsp+52: in_preserve
#r620 rsp+48: saved fp register
#r619 rsp+44: pad2, stack alignment
#r618 rsp+40: pad2, stack alignment
#r617 rsp+36: Fixed slot 1
#r616 rsp+32: Fixed slot 0
#r631 rsp+28: spill
#r630 rsp+24: spill
#r629 rsp+20: spill
#r628 rsp+16: spill
#r627 rsp+12: spill
#r626 rsp+ 8: spill
#r625 rsp+ 4: spill
#r624 rsp+ 0: spill
#
----------------------- MetaData before Compile_id = 26 ------------------------
{method}
 - this oop:          0x00007f1c5c605690
 - method holder:     'callchain'
 - constants:         0x00007f1c5c605058 constant pool [77]/operands[5] {0x00007f1c5c605058} for 'callchain' cache=0x00007f1c5c6059a8
 - access:            0x9  public static 
 - flags:             0x4080  queued_for_compilation has_loops_flag_init 
 - name:              'highleaf'
 - signature:         '(I)I'
 - max stack:         5
 - max locals:        5
 - size of params:    1
 - method size:       14
 - vtable index:      -2
 - i2i entry:         0x00007f1cb79afbe0
 - adapters:          AHE@0x00007f1cbc24c460: 0xa i2c: 0x00007f1cb7ac0fe0 c2i: 0x00007f1cb7ac1099 c2iUV: 0x00007f1cb7ac1074 c2iNCI: 0x00007f1cb7ac10d3
 - compiled entry     0x00007f1cb7ac1099
 - code size:         62
 - code start:        0x00007f1c5c605648
 - code end (excl):   0x00007f1c5c605686
 - method data:       0x00007f1c5c606598
 - checked ex length: 0
 - linenumber start:  0x00007f1c5c605686
 - localvar length:   0

------------------------ OptoAssembly for Compile_id = 26 -----------------------
#
#  int ( int )
#
000     N1: #	out( B1 ) <- in( B2 B3 )  Freq: 1

000     B1: #	out( B3 B2 ) <- BLOCK HEAD IS JUNK  Freq: 1
000     # stack bang (168 bytes)
	pushq   rbp	# Save rbp
	movq    rbp, rsp	# Save the caller's SP into rbp
	subq    rsp, #48	# Create frame

01e     movl    [rsp + #24], RSI	# spill
022     incl    RSI	# int
024     movl    R10, [rsp + #24]	# spill
029     addl    R10, #32	# int
02d     movl    R16, [rsp + #24]	# spill
033     addl    R16, #12	# int
038     movl    R17, [rsp + #24]	# spill
03e     addl    R17, #31	# int
043     movl    R18, [rsp + #24]	# spill
049     addl    R18, #11	# int
04e     movl    R19, [rsp + #24]	# spill
054     addl    R19, #30	# int
059     movl    R20, [rsp + #24]	# spill
05f     addl    R20, #10	# int
064     movl    [rsp + #0], R10	# spill
068     movl    [rsp + #4], R16	# spill
06e     movl    [rsp + #8], R17	# spill
074     movl    [rsp + #12], R18	# spill
07a     movl    [rsp + #16], R19	# spill
080     movl    [rsp + #20], R20	# spill
        nop 	# 1 bytes pad for loops and calls
087     call,static  callchain::midleaf
        # callchain::highleaf @ bci:34 (line 40) L[0]=_ L[1]=#ScObj0 L[2]=#ScObj1 L[3]=#ScObj2 L[4]=_
        # ScObj0 Packet={ [field1 :0]=rsp + #16, [field2 :1]=rsp + #20, [field3 :2]=#0, [field4 :3]=#0 }
        # ScObj1 Packet={ [field1 :0]=rsp + #8, [field2 :1]=rsp + #12, [field3 :2]=#0, [field4 :3]=#0 }
        # ScObj2 Packet={ [field1 :0]=rsp + #0, [field2 :1]=rsp + #4, [field3 :2]=#0, [field4 :3]=#0 }
        # OopMap {off=140/0x8c}

094     B2: #	out( N1 ) <- in( B1 )  Freq: 0.99998
        # Block is sole successor of call
094     addl    RAX, [RSP + #24 (32-bit)]	# int
098     movl    R10, [rsp + #24]	# spill
09d     addl    R10, R10	# int
0a0     addl    RAX, R10	# int
0a3     addl    RAX, R10	# int
0a6     leal RAX, [RAX + R10 + #156]	# int
0ae     addq    rsp, 48	# Destroy frame
	popq    rbp
	cmpq    rsp, poll_offset[r15_thread] 
	ja      #safepoint_stub	# Safepoint: poll for GC

0c0     ret

0c1     B3: #	out( N1 ) <- in( B1 )  Freq: 1e-05
0c1     # exception oop is in rax; no code emitted
0c1     movq    RSI, RAX	# spill
0c4     addq    rsp, 48	# Destroy frame
	popq    rbp

0c9     jmp     rethrow_stub

--------------------------------------------------------------------------------
----------------------------------- Assembly -----------------------------------

Compiled method (c2) 25434   26             callchain::highleaf (62 bytes)
 total in heap  [0x00007f1cb7b30610,0x00007f1cb7b30a90] = 1152
 relocation     [0x00007f1cb7b30778,0x00007f1cb7b30798] = 32
 main code      [0x00007f1cb7b307a0,0x00007f1cb7b30890] = 240
 stub code      [0x00007f1cb7b30890,0x00007f1cb7b308b8] = 40
 oops           [0x00007f1cb7b308b8,0x00007f1cb7b308c8] = 16
 metadata       [0x00007f1cb7b308c8,0x00007f1cb7b308e8] = 32
 scopes data    [0x00007f1cb7b308e8,0x00007f1cb7b30980] = 152
 scopes pcs     [0x00007f1cb7b30980,0x00007f1cb7b30a70] = 240
 dependencies   [0x00007f1cb7b30a70,0x00007f1cb7b30a78] = 8
 handler table  [0x00007f1cb7b30a78,0x00007f1cb7b30a90] = 24

[Disassembly]
--------------------------------------------------------------------------------
[Constant Pool (empty)]

--------------------------------------------------------------------------------

[Verified Entry Point]
  # {method} {0x00007f1c5c605690} 'highleaf' '(I)I' in 'callchain'
  # parm0:    rsi       = int
  #           [sp+0x40]  (sp of caller)
 ;; N1: #	out( B1 ) <- in( B2 B3 )  Freq: 1
 ;; B1: #	out( B3 B2 ) <- BLOCK HEAD IS JUNK  Freq: 1
  0x00007f1cb7b307a0:   mov    %eax,-0x18000(%rsp)
  0x00007f1cb7b307a7:   push   %rbp
  0x00007f1cb7b307a8:   mov    %rsp,%rbp
  0x00007f1cb7b307ab:   sub    $0x30,%rsp
  0x00007f1cb7b307af:   nop
  0x00007f1cb7b307b0:   cmpl   $0x0,0x20(%r15)
  0x00007f1cb7b307b8:   jne    0x00007f1cb7b30884           ;*synchronization entry
                                                            ; - callchain::highleaf@-1 (line 37)
  0x00007f1cb7b307be:   mov    %esi,0x18(%rsp)
  0x00007f1cb7b307c2:   inc    %esi                         ;*iadd {reexecute=0 rethrow=0 return_oop=0}
                                                            ; - callchain::highleaf@15 (line 38)
  0x00007f1cb7b307c4:   mov    0x18(%rsp),%r10d
  0x00007f1cb7b307c9:   add    $0x20,%r10d                  ;*iadd {reexecute=0 rethrow=0 return_oop=0}
                                                            ; - Packet::<init>@29 (line 10)
                                                            ; - callchain::highleaf@27 (line 39)
  0x00007f1cb7b307cd:   (bad)  
  0x00007f1cb7b307ce:   rex mov 0x18(%rsp),%eax
  0x00007f1cb7b307d3:   (bad)  
  0x00007f1cb7b307d4:   adc    %al,0x40d50cc0(%rbx)         ;*iadd {reexecute=0 rethrow=0 return_oop=0}
                                                            ; - Packet::<init>@13 (line 8)
                                                            ; - callchain::highleaf@27 (line 39)
  0x00007f1cb7b307da:   mov    0x18(%rsp),%ecx
  0x00007f1cb7b307de:   (bad)  
  0x00007f1cb7b307df:   adc    %al,0x40d51fc1(%rbx)         ;*iadd {reexecute=0 rethrow=0 return_oop=0}
                                                            ; - Packet::<init>@29 (line 10)
                                                            ; - callchain::highleaf@16 (line 38)
  0x00007f1cb7b307e5:   mov    0x18(%rsp),%edx
  0x00007f1cb7b307e9:   (bad)  
  0x00007f1cb7b307ea:   adc    %al,0x40d50bc2(%rbx)         ;*iadd {reexecute=0 rethrow=0 return_oop=0}
                                                            ; - Packet::<init>@13 (line 8)
                                                            ; - callchain::highleaf@16 (line 38)
  0x00007f1cb7b307f0:   mov    0x18(%rsp),%ebx
  0x00007f1cb7b307f4:   (bad)  
  0x00007f1cb7b307f5:   adc    %al,0x40d51ec3(%rbx)         ;*iadd {reexecute=0 rethrow=0 return_oop=0}
                                                            ; - Packet::<init>@29 (line 10)
                                                            ; - callchain::highleaf@5 (line 37)
  0x00007f1cb7b307fb:   mov    0x18(%rsp),%esp
  0x00007f1cb7b307ff:   (bad)  
  0x00007f1cb7b30800:   adc    %al,-0x76bbf53c(%rbx)        ;*iadd {reexecute=0 rethrow=0 return_oop=0}
                                                            ; - Packet::<init>@13 (line 8)
                                                            ; - callchain::highleaf@5 (line 37)
  0x00007f1cb7b30806:   adc    $0x24,%al
  0x00007f1cb7b30808:   (bad)  
  0x00007f1cb7b30809:   rex mov %eax,0x4(%rsp)
  0x00007f1cb7b3080e:   (bad)  
  0x00007f1cb7b3080f:   rex mov %ecx,0x8(%rsp)
  0x00007f1cb7b30814:   (bad)  
  0x00007f1cb7b30815:   rex mov %edx,0xc(%rsp)
  0x00007f1cb7b3081a:   (bad)  
  0x00007f1cb7b3081b:   rex mov %ebx,0x10(%rsp)
  0x00007f1cb7b30820:   (bad)  
  0x00007f1cb7b30821:   rex mov %esp,0x14(%rsp)
  0x00007f1cb7b30826:   nop
  0x00007f1cb7b30827:   callq  0x00007f1cb7abc1a0           ; ImmutableOopMap {}
                                                            ;*invokestatic midleaf {reexecute=0 rethrow=0 return_oop=0}
                                                            ; - callchain::highleaf@34 (line 40)
                                                            ;   {static_call}
  0x00007f1cb7b3082c:   nopl   0x21c(%rax,%rax,1)           ;*invokestatic midleaf {reexecute=0 rethrow=0 return_oop=0}
                                                            ; - callchain::highleaf@34 (line 40)
                                                            ;   {other}
 ;; B2: #	out( N1 ) <- in( B1 )  Freq: 0.99998
  0x00007f1cb7b30834:   add    0x18(%rsp),%eax
  0x00007f1cb7b30838:   mov    0x18(%rsp),%r10d
  0x00007f1cb7b3083d:   add    %r10d,%r10d                  ;*iadd {reexecute=0 rethrow=0 return_oop=0}
                                                            ; - Packet::<init>@29 (line 10)
                                                            ; - callchain::highleaf@16 (line 38)
  0x00007f1cb7b30840:   add    %r10d,%eax
  0x00007f1cb7b30843:   add    %r10d,%eax
  0x00007f1cb7b30846:   lea    0x9c(%rax,%r10,1),%eax       ;*iadd {reexecute=0 rethrow=0 return_oop=0}
                                                            ; - callchain::highleaf@60 (line 41)
  0x00007f1cb7b3084e:   add    $0x30,%rsp
  0x00007f1cb7b30852:   pop    %rbp
  0x00007f1cb7b30853:   cmp    0x498(%r15),%rsp             ;   {poll_return}
  0x00007f1cb7b3085a:   ja     0x00007f1cb7b3086e
  0x00007f1cb7b30860:   retq                                ;*new {reexecute=0 rethrow=0 return_oop=0}
                                                            ; - callchain::highleaf@0 (line 37)
 ;; B3: #	out( N1 ) <- in( B1 )  Freq: 1e-05
  0x00007f1cb7b30861:   mov    %rax,%rsi
  0x00007f1cb7b30864:   add    $0x30,%rsp
  0x00007f1cb7b30868:   pop    %rbp
  0x00007f1cb7b30869:   jmpq   0x00007f1cb7b01d20           ;   {runtime_call _rethrow_Java}
  0x00007f1cb7b3086e:   movabs $0x7f1cb7b30853,%r10         ;   {internal_word}
  0x00007f1cb7b30878:   mov    %r10,0x4b0(%r15)
  0x00007f1cb7b3087f:   jmpq   0x00007f1cb7ac3f20           ;   {runtime_call SafepointBlob}
  0x00007f1cb7b30884:   callq  Stub::nmethod_entry_barrier  ;   {runtime_call StubRoutines (final stubs)}
  0x00007f1cb7b30889:   jmpq   0x00007f1cb7b307be
  0x00007f1cb7b3088e:   hlt    
  0x00007f1cb7b3088f:   hlt    
[Stub Code]
  0x00007f1cb7b30890:   movabs $0x0,%rbx                    ;   {no_reloc}
  0x00007f1cb7b3089a:   jmpq   0x00007f1cb7b3089a           ;   {runtime_call}
[Exception Handler]
  0x00007f1cb7b3089f:   jmpq   0x00007f1cb7ac4620           ;   {runtime_call ExceptionBlob}
[Deopt Handler Code]
  0x00007f1cb7b308a4:   callq  0x00007f1cb7b308a9
  0x00007f1cb7b308a9:   subq   $0x5,(%rsp)
  0x00007f1cb7b308ae:   jmpq   0x00007f1cb7ac56e0           ;   {runtime_call DeoptimizationBlob}
  0x00007f1cb7b308b3:   hlt    
  0x00007f1cb7b308b4:   hlt    
  0x00007f1cb7b308b5:   hlt    
  0x00007f1cb7b308b6:   hlt    
  0x00007f1cb7b308b7:   hlt    
--------------------------------------------------------------------------------
[/Disassembly]
- - - - - - - - - - - - - - - - - - - - - - - - - - - - - - - - - - - - - - - - 
Oops:
  0x00007f1cb7b308b8:   0x000000011f920fa0 a 'java/lang/Class'{0x000000011f920fa0} = 'Packet'
  0x00007f1cb7b308c0:   0x000000011f81bf60 a 'jdk/internal/loader/ClassLoaders$AppClassLoader'{0x000000011f81bf60}
- - - - - - - - - - - - - - - - - - - - - - - - - - - - - - - - - - - - - - - - 
Metadata:
  0x00007f1cb7b308c8:   0x00007f1c5c605690 {method} {0x00007f1c5c605690} 'highleaf' '(I)I' in 'callchain'
  0x00007f1cb7b308d0:   0x00007f1c5c605c60 {method} {0x00007f1c5c605c60} '<init>' '(I)V' in 'Packet'
  0x00007f1cb7b308d8:   0x00007f1c5c605d20 {method} {0x00007f1c5c605d20} 'accum' '()I' in 'Packet'
  0x00007f1cb7b308e0:   0x00000000380c4a10 'Packet'
- - - - - - - - - - - - - - - - - - - - - - - - - - - - - - - - - - - - - - - - 
pc-bytecode offsets:
PcDesc(pc=0x00007f1cb7b3079f offset=ffffffff bits=0):
PcDesc(pc=0x00007f1cb7b307be offset=1e bits=0):
   callchain::highleaf@-1 (line 37)
PcDesc(pc=0x00007f1cb7b307c4 offset=24 bits=0):
   callchain::highleaf@15 (line 38)
PcDesc(pc=0x00007f1cb7b307cd offset=2d bits=0):
   Packet::<init>@29 (line 10)
   callchain::highleaf@27 (line 39)
PcDesc(pc=0x00007f1cb7b307d8 offset=38 bits=0):
   Packet::<init>@13 (line 8)
   callchain::highleaf@27 (line 39)
PcDesc(pc=0x00007f1cb7b307e3 offset=43 bits=0):
   Packet::<init>@29 (line 10)
   callchain::highleaf@16 (line 38)
PcDesc(pc=0x00007f1cb7b307ee offset=4e bits=0):
   Packet::<init>@13 (line 8)
   callchain::highleaf@16 (line 38)
PcDesc(pc=0x00007f1cb7b307f9 offset=59 bits=0):
   Packet::<init>@29 (line 10)
   callchain::highleaf@5 (line 37)
PcDesc(pc=0x00007f1cb7b30804 offset=64 bits=0):
   Packet::<init>@13 (line 8)
   callchain::highleaf@5 (line 37)
PcDesc(pc=0x00007f1cb7b3082c offset=8c bits=0):
   callchain::highleaf@34 (line 40)
   Locals
    - l0: empty
    - l1: obj[22]
    - l2: obj[23]
    - l3: obj[24]
    - l4: empty
   Objects
    - 0: R obj[22], Packet
        Fields: stack[16], stack[20], 0, 0
    - 1: R obj[23], Packet
        Fields: stack[8], stack[12], 0, 0
    - 2: R obj[24], Packet
        Fields: stack[0], stack[4], 0, 0
PcDesc(pc=0x00007f1cb7b30834 offset=94 bits=0):
   callchain::highleaf@34 (line 40)
PcDesc(pc=0x00007f1cb7b30840 offset=a0 bits=0):
   Packet::<init>@29 (line 10)
   callchain::highleaf@16 (line 38)
PcDesc(pc=0x00007f1cb7b3084e offset=ae bits=0):
   callchain::highleaf@60 (line 41)
PcDesc(pc=0x00007f1cb7b30861 offset=c1 bits=0):
   callchain::highleaf@0 (line 37)
PcDesc(pc=0x00007f1cb7b308b9 offset=119 bits=0):
- - - - - - - - - - - - - - - - - - - - - - - - - - - - - - - - - - - - - - - - 
oop maps:ImmutableOopMapSet contains 1 OopMaps

ImmutableOopMap {} pc offsets: 140 
- - - - - - - - - - - - - - - - - - - - - - - - - - - - - - - - - - - - - - - - 
scopes:
ScopeDesc(pc=0x00007f1cb7b307be offset=1e):
   callchain::highleaf@-1 (line 37)
ScopeDesc(pc=0x00007f1cb7b307c4 offset=24):
   callchain::highleaf@15 (line 38)
ScopeDesc(pc=0x00007f1cb7b307cd offset=2d):
   Packet::<init>@29 (line 10)
ScopeDesc(pc=0x00007f1cb7b307cd offset=2d):
   callchain::highleaf@27 (line 39)
ScopeDesc(pc=0x00007f1cb7b307d8 offset=38):
   Packet::<init>@13 (line 8)
ScopeDesc(pc=0x00007f1cb7b307d8 offset=38):
   callchain::highleaf@27 (line 39)
ScopeDesc(pc=0x00007f1cb7b307e3 offset=43):
   Packet::<init>@29 (line 10)
ScopeDesc(pc=0x00007f1cb7b307e3 offset=43):
   callchain::highleaf@16 (line 38)
ScopeDesc(pc=0x00007f1cb7b307ee offset=4e):
   Packet::<init>@13 (line 8)
ScopeDesc(pc=0x00007f1cb7b307ee offset=4e):
   callchain::highleaf@16 (line 38)
ScopeDesc(pc=0x00007f1cb7b307f9 offset=59):
   Packet::<init>@29 (line 10)
ScopeDesc(pc=0x00007f1cb7b307f9 offset=59):
   callchain::highleaf@5 (line 37)
ScopeDesc(pc=0x00007f1cb7b30804 offset=64):
   Packet::<init>@13 (line 8)
ScopeDesc(pc=0x00007f1cb7b30804 offset=64):
   callchain::highleaf@5 (line 37)
ScopeDesc(pc=0x00007f1cb7b3082c offset=8c):
   callchain::highleaf@34 (line 40)
   Locals
    - l0: empty
    - l1: obj[22]
    - l2: obj[23]
    - l3: obj[24]
    - l4: empty
   Objects
    - 0: R obj[22], Packet
        Fields: stack[16], stack[20], 0, 0
    - 1: R obj[23], Packet
        Fields: stack[8], stack[12], 0, 0
    - 2: R obj[24], Packet
        Fields: stack[0], stack[4], 0, 0
ScopeDesc(pc=0x00007f1cb7b30834 offset=94):
   callchain::highleaf@34 (line 40)
ScopeDesc(pc=0x00007f1cb7b30840 offset=a0):
   Packet::<init>@29 (line 10)
ScopeDesc(pc=0x00007f1cb7b30840 offset=a0):
   callchain::highleaf@16 (line 38)
ScopeDesc(pc=0x00007f1cb7b3084e offset=ae):
   callchain::highleaf@60 (line 41)
ScopeDesc(pc=0x00007f1cb7b30861 offset=c1):
   callchain::highleaf@0 (line 37)
- - - - - - - - - - - - - - - - - - - - - - - - - - - - - - - - - - - - - - - - 
relocations:
         @0x00007f1cb7b30778: 2187
relocInfo@0x00007f1cb7b30778 [type=4(static_call) addr=0x00007f1cb7b30827 offset=135 format=1] | [destination=0x00007f1cb7abc1a0 metadata=0x0000000000000000]
         @0x00007f1cb7b3077a: 8005
relocInfo@0x00007f1cb7b3077a [type=16(post_call_nop) addr=0x00007f1cb7b3082c offset=5]
         @0x00007f1cb7b3077c: 5827
relocInfo@0x00007f1cb7b3077c [type=11(poll_return) addr=0x00007f1cb7b30853 offset=39]
         @0x00007f1cb7b3077e: 3116
relocInfo@0x00007f1cb7b3077e [type=6(runtime_call) addr=0x00007f1cb7b30869 offset=22 format=1] | [destination=0x00007f1cb7b01d20]
         @0x00007f1cb7b30780: 781b4005
relocInfo@0x00007f1cb7b30782 [type=8(internal_word) addr=0x00007f1cb7b3086e offset=5 data=27] | [target=0x00007f1cb7b30853]
         @0x00007f1cb7b30784: 3111
relocInfo@0x00007f1cb7b30784 [type=6(runtime_call) addr=0x00007f1cb7b3087f offset=17 format=1] | [destination=0x00007f1cb7ac3f20]
         @0x00007f1cb7b30786: 3105
relocInfo@0x00007f1cb7b30786 [type=6(runtime_call) addr=0x00007f1cb7b30884 offset=5 format=1] | [destination=0x00007f1cb7a08dc0]
         @0x00007f1cb7b30788: 000c
relocInfo@0x00007f1cb7b30788 [type=0(none) addr=0x00007f1cb7b30890 offset=12]
         @0x00007f1cb7b3078a: 7c01ff792800
relocInfo@0x00007f1cb7b3078e [type=5(static_stub) addr=0x00007f1cb7b30890 offset=0 data=-135] | [static_call=0x00007f1cb7b30827]
         @0x00007f1cb7b30790: 6000
relocInfo@0x00007f1cb7b30790 [type=12(metadata) addr=0x00007f1cb7b30890 offset=0] | [metadata_addr=0x00007f1cb7b30892 *=0x0000000000000000 offset=0]
         @0x00007f1cb7b30792: 310a
relocInfo@0x00007f1cb7b30792 [type=6(runtime_call) addr=0x00007f1cb7b3089a offset=10 format=1] | [destination=0xffffffffffffffff]
         @0x00007f1cb7b30794: 3105
relocInfo@0x00007f1cb7b30794 [type=6(runtime_call) addr=0x00007f1cb7b3089f offset=5 format=1] | [destination=0x00007f1cb7ac4620]
         @0x00007f1cb7b30796: 310f
relocInfo@0x00007f1cb7b30796 [type=6(runtime_call) addr=0x00007f1cb7b308ae offset=15 format=1] | [destination=0x00007f1cb7ac56e0]
         @0x00007f1cb7b30798: 
- - - - - - - - - - - - - - - - - - - - - - - - - - - - - - - - - - - - - - - - 
Dependencies:
Dependency of type unique_concrete_method_4
  context = Packet
  method  = {method} {0x00007f1c5c605d20} 'accum' '()I' in 'Packet'
  class   = Packet
  method  = {method} {0x00007f1c5c605d20} 'accum' '()I' in 'Packet'
   [nmethod<=klass]Packet
- - - - - - - - - - - - - - - - - - - - - - - - - - - - - - - - - - - - - - - - 
ExceptionHandlerTable (size = 24 bytes)
catch_pco = 140 (pc=0x00007f1cb7b3082c, 1 entries)
  bci -1 at scope depth 0 -> pco 193 (pc=0x00007f1cb7b30861)
- - - - - - - - - - - - - - - - - - - - - - - - - - - - - - - - - - - - - - - - 
ImplicitExceptionTable is empty
- - - - - - - - - - - - - - - - - - - - - - - - - - - - - - - - - - - - - - - - 
Recorded oops:
#0: 0x0000000000000000 nullptr-oop
#1: 0x000000011f920fa0 a 'java/lang/Class'{0x000000011f920fa0} = 'Packet'
#2: 0x000000011f81bf60 a 'jdk/internal/loader/ClassLoaders$AppClassLoader'{0x000000011f81bf60}
- - - - - - - - - - - - - - - - - - - - - - - - - - - - - - - - - - - - - - - - 
Recorded metadata:
#0: 0x0000000000000000 nullptr-oop
#1: 0x00007f1c5c605690 {method} {0x00007f1c5c605690} 'highleaf' '(I)I' in 'callchain'
#2: 0x00007f1c5c605c60 {method} {0x00007f1c5c605c60} '<init>' '(I)V' in 'Packet'
#3: 0x00007f1c5c605d20 {method} {0x00007f1c5c605d20} 'accum' '()I' in 'Packet'
#4: 0x00000000380c4a10 'Packet'
- - - - - - - - - - - - - - - - - - - - - - - - - - - - - - - - - - - - - - - - 

============================= C2-compiled nmethod ==============================
#r050 rsi   : parm 0: int
# -- Old rsp -- Framesize: 48 --
#r623 rsp+44: in_preserve
#r622 rsp+40: return address
#r621 rsp+36: in_preserve
#r620 rsp+32: saved fp register
#r619 rsp+28: pad2, stack alignment
#r618 rsp+24: pad2, stack alignment
#r617 rsp+20: Fixed slot 1
#r616 rsp+16: Fixed slot 0
#r627 rsp+12: spill
#r626 rsp+ 8: spill
#r625 rsp+ 4: spill
#r624 rsp+ 0: spill
#
----------------------- MetaData before Compile_id = 27 ------------------------
{method}
 - this oop:          0x00007f1c5c6055a0
 - method holder:     'callchain'
 - constants:         0x00007f1c5c605058 constant pool [77]/operands[5] {0x00007f1c5c605058} for 'callchain' cache=0x00007f1c5c6059a8
 - access:            0x9  public static 
 - flags:             0x4080  queued_for_compilation has_loops_flag_init 
 - name:              'midleaf'
 - signature:         '(I)I'
 - max stack:         4
 - max locals:        3
 - size of params:    1
 - method size:       14
 - vtable index:      -2
 - i2i entry:         0x00007f1cb79afbe0
 - adapters:          AHE@0x00007f1cbc24c460: 0xa i2c: 0x00007f1cb7ac0fe0 c2i: 0x00007f1cb7ac1099 c2iUV: 0x00007f1cb7ac1074 c2iNCI: 0x00007f1cb7ac10d3
 - compiled entry     0x00007f1cb7ac1099
 - code size:         23
 - code start:        0x00007f1c5c605580
 - code end (excl):   0x00007f1c5c605597
 - method data:       0x00007f1c5c606810
 - checked ex length: 0
 - linenumber start:  0x00007f1c5c605597
 - localvar length:   0

------------------------ OptoAssembly for Compile_id = 27 -----------------------
#
#  int ( int )
#
000     N1: #	out( B1 ) <- in( B2 B3 )  Freq: 1

000     B1: #	out( B3 B2 ) <- BLOCK HEAD IS JUNK  Freq: 1
000     # stack bang (144 bytes)
	pushq   rbp	# Save rbp
	movq    rbp, rsp	# Save the caller's SP into rbp
	subq    rsp, #32	# Create frame

01e     movl    [rsp + #8], RSI	# spill
022     incl    RSI	# int
024     movl    R10, [rsp + #8]	# spill
029     addl    R10, #30	# int
02d     movl    R16, [rsp + #8]	# spill
033     addl    R16, #10	# int
038     movl    [rsp + #0], R10	# spill
03c     movl    [rsp + #4], R16	# spill
        nop 	# 1 bytes pad for loops and calls
043     call,static  callchain::leaf
        # callchain::midleaf @ bci:12 (line 32) L[0]=_ L[1]=#ScObj0 L[2]=_
        # ScObj0 Packet={ [field1 :0]=rsp + #0, [field2 :1]=rsp + #4, [field3 :2]=#0, [field4 :3]=#0 }
        # OopMap {off=72/0x48}

050     B2: #	out( N1 ) <- in( B1 )  Freq: 0.99998
        # Block is sole successor of call
050     movl    R16, [rsp + #8]	# spill
056     addl    R16, R16	# int
05a     leal RAX, [RAX + R16 + #40]	# int
060     addq    rsp, 32	# Destroy frame
	popq    rbp
	cmpq    rsp, poll_offset[r15_thread] 
	ja      #safepoint_stub	# Safepoint: poll for GC

072     ret

073     B3: #	out( N1 ) <- in( B1 )  Freq: 1e-05
073     # exception oop is in rax; no code emitted
073     movq    RSI, RAX	# spill
076     addq    rsp, 32	# Destroy frame
	popq    rbp

07b     jmp     rethrow_stub

--------------------------------------------------------------------------------
----------------------------------- Assembly -----------------------------------

Compiled method (c2) 25511   27             callchain::midleaf (23 bytes)
 total in heap  [0x00007f1cb7b30b10,0x00007f1cb7b30ea8] = 920
 relocation     [0x00007f1cb7b30c78,0x00007f1cb7b30c98] = 32
 main code      [0x00007f1cb7b30ca0,0x00007f1cb7b30d40] = 160
 stub code      [0x00007f1cb7b30d40,0x00007f1cb7b30d68] = 40
 oops           [0x00007f1cb7b30d68,0x00007f1cb7b30d78] = 16
 metadata       [0x00007f1cb7b30d78,0x00007f1cb7b30d98] = 32
 scopes data    [0x00007f1cb7b30d98,0x00007f1cb7b30de8] = 80
 scopes pcs     [0x00007f1cb7b30de8,0x00007f1cb7b30e88] = 160
 dependencies   [0x00007f1cb7b30e88,0x00007f1cb7b30e90] = 8
 handler table  [0x00007f1cb7b30e90,0x00007f1cb7b30ea8] = 24

[Disassembly]
--------------------------------------------------------------------------------
[Constant Pool (empty)]

--------------------------------------------------------------------------------

[Verified Entry Point]
  # {method} {0x00007f1c5c6055a0} 'midleaf' '(I)I' in 'callchain'
  # parm0:    rsi       = int
  #           [sp+0x30]  (sp of caller)
 ;; N1: #	out( B1 ) <- in( B2 B3 )  Freq: 1
 ;; B1: #	out( B3 B2 ) <- BLOCK HEAD IS JUNK  Freq: 1
  0x00007f1cb7b30ca0:   mov    %eax,-0x18000(%rsp)
  0x00007f1cb7b30ca7:   push   %rbp
  0x00007f1cb7b30ca8:   mov    %rsp,%rbp
  0x00007f1cb7b30cab:   sub    $0x20,%rsp
  0x00007f1cb7b30caf:   nop
  0x00007f1cb7b30cb0:   cmpl   $0x0,0x20(%r15)
  0x00007f1cb7b30cb8:   jne    0x00007f1cb7b30d36           ;*synchronization entry
                                                            ; - callchain::midleaf@-1 (line 31)
  0x00007f1cb7b30cbe:   mov    %esi,0x8(%rsp)
  0x00007f1cb7b30cc2:   inc    %esi                         ;*iadd {reexecute=0 rethrow=0 return_oop=0}
                                                            ; - callchain::midleaf@11 (line 32)
  0x00007f1cb7b30cc4:   mov    0x8(%rsp),%r10d
  0x00007f1cb7b30cc9:   add    $0x1e,%r10d                  ;*iadd {reexecute=0 rethrow=0 return_oop=0}
                                                            ; - Packet::<init>@29 (line 10)
                                                            ; - callchain::midleaf@5 (line 31)
  0x00007f1cb7b30ccd:   (bad)  
  0x00007f1cb7b30cce:   rex mov 0x8(%rsp),%eax
  0x00007f1cb7b30cd3:   (bad)  
  0x00007f1cb7b30cd4:   adc    %al,-0x76bbf540(%rbx)        ;*iadd {reexecute=0 rethrow=0 return_oop=0}
                                                            ; - Packet::<init>@13 (line 8)
                                                            ; - callchain::midleaf@5 (line 31)
  0x00007f1cb7b30cda:   adc    $0x24,%al
  0x00007f1cb7b30cdc:   (bad)  
  0x00007f1cb7b30cdd:   rex mov %eax,0x4(%rsp)
  0x00007f1cb7b30ce2:   nop
  0x00007f1cb7b30ce3:   callq  0x00007f1cb7abc1a0           ; ImmutableOopMap {}
                                                            ;*invokestatic leaf {reexecute=0 rethrow=0 return_oop=0}
                                                            ; - callchain::midleaf@12 (line 32)
                                                            ;   {static_call}
  0x00007f1cb7b30ce8:   nopl   0x1d8(%rax,%rax,1)           ;*invokestatic leaf {reexecute=0 rethrow=0 return_oop=0}
                                                            ; - callchain::midleaf@12 (line 32)
                                                            ;   {other}
 ;; B2: #	out( N1 ) <- in( B1 )  Freq: 0.99998
  0x00007f1cb7b30cf0:   (bad)  
  0x00007f1cb7b30cf1:   rex mov 0x8(%rsp),%eax
  0x00007f1cb7b30cf6:   (bad)  
  0x00007f1cb7b30cf7:   push   %rax
  0x00007f1cb7b30cf8:   add    %eax,%eax
  0x00007f1cb7b30cfa:   (bad)  
  0x00007f1cb7b30cfb:   and    %cl,0x48280044(%rbp)         ;*iadd {reexecute=0 rethrow=0 return_oop=0}
                                                            ; - callchain::midleaf@21 (line 33)
  0x00007f1cb7b30d01:   add    $0x20,%esp
  0x00007f1cb7b30d04:   pop    %rbp
  0x00007f1cb7b30d05:   cmp    0x498(%r15),%rsp             ;   {poll_return}
  0x00007f1cb7b30d0c:   ja     0x00007f1cb7b30d20
  0x00007f1cb7b30d12:   retq                                ;*new {reexecute=0 rethrow=0 return_oop=0}
                                                            ; - callchain::midleaf@0 (line 31)
 ;; B3: #	out( N1 ) <- in( B1 )  Freq: 1e-05
  0x00007f1cb7b30d13:   mov    %rax,%rsi
  0x00007f1cb7b30d16:   add    $0x20,%rsp
  0x00007f1cb7b30d1a:   pop    %rbp
  0x00007f1cb7b30d1b:   jmpq   0x00007f1cb7b01d20           ;   {runtime_call _rethrow_Java}
  0x00007f1cb7b30d20:   movabs $0x7f1cb7b30d05,%r10         ;   {internal_word}
  0x00007f1cb7b30d2a:   mov    %r10,0x4b0(%r15)
  0x00007f1cb7b30d31:   jmpq   0x00007f1cb7ac3f20           ;   {runtime_call SafepointBlob}
  0x00007f1cb7b30d36:   callq  Stub::nmethod_entry_barrier  ;   {runtime_call StubRoutines (final stubs)}
  0x00007f1cb7b30d3b:   jmpq   0x00007f1cb7b30cbe
[Stub Code]
  0x00007f1cb7b30d40:   movabs $0x0,%rbx                    ;   {no_reloc}
  0x00007f1cb7b30d4a:   jmpq   0x00007f1cb7b30d4a           ;   {runtime_call}
[Exception Handler]
  0x00007f1cb7b30d4f:   jmpq   0x00007f1cb7ac4620           ;   {runtime_call ExceptionBlob}
[Deopt Handler Code]
  0x00007f1cb7b30d54:   callq  0x00007f1cb7b30d59
  0x00007f1cb7b30d59:   subq   $0x5,(%rsp)
  0x00007f1cb7b30d5e:   jmpq   0x00007f1cb7ac56e0           ;   {runtime_call DeoptimizationBlob}
  0x00007f1cb7b30d63:   hlt    
  0x00007f1cb7b30d64:   hlt    
  0x00007f1cb7b30d65:   hlt    
  0x00007f1cb7b30d66:   hlt    
  0x00007f1cb7b30d67:   hlt    
--------------------------------------------------------------------------------
[/Disassembly]
- - - - - - - - - - - - - - - - - - - - - - - - - - - - - - - - - - - - - - - - 
Oops:
  0x00007f1cb7b30d68:   0x000000011f920fa0 a 'java/lang/Class'{0x000000011f920fa0} = 'Packet'
  0x00007f1cb7b30d70:   0x000000011f81bf60 a 'jdk/internal/loader/ClassLoaders$AppClassLoader'{0x000000011f81bf60}
- - - - - - - - - - - - - - - - - - - - - - - - - - - - - - - - - - - - - - - - 
Metadata:
  0x00007f1cb7b30d78:   0x00007f1c5c6055a0 {method} {0x00007f1c5c6055a0} 'midleaf' '(I)I' in 'callchain'
  0x00007f1cb7b30d80:   0x00007f1c5c605c60 {method} {0x00007f1c5c605c60} '<init>' '(I)V' in 'Packet'
  0x00007f1cb7b30d88:   0x00007f1c5c605d20 {method} {0x00007f1c5c605d20} 'accum' '()I' in 'Packet'
  0x00007f1cb7b30d90:   0x00000000380c4a10 'Packet'
- - - - - - - - - - - - - - - - - - - - - - - - - - - - - - - - - - - - - - - - 
pc-bytecode offsets:
PcDesc(pc=0x00007f1cb7b30c9f offset=ffffffff bits=0):
PcDesc(pc=0x00007f1cb7b30cbe offset=1e bits=0):
   callchain::midleaf@-1 (line 31)
PcDesc(pc=0x00007f1cb7b30cc4 offset=24 bits=0):
   callchain::midleaf@11 (line 32)
PcDesc(pc=0x00007f1cb7b30ccd offset=2d bits=0):
   Packet::<init>@29 (line 10)
   callchain::midleaf@5 (line 31)
PcDesc(pc=0x00007f1cb7b30cd8 offset=38 bits=0):
   Packet::<init>@13 (line 8)
   callchain::midleaf@5 (line 31)
PcDesc(pc=0x00007f1cb7b30ce8 offset=48 bits=0):
   callchain::midleaf@12 (line 32)
   Locals
    - l0: empty
    - l1: obj[18]
    - l2: empty
   Objects
    - 0: R obj[18], Packet
        Fields: stack[0], stack[4], 0, 0
PcDesc(pc=0x00007f1cb7b30cf0 offset=50 bits=0):
   callchain::midleaf@12 (line 32)
PcDesc(pc=0x00007f1cb7b30d00 offset=60 bits=0):
   callchain::midleaf@21 (line 33)
PcDesc(pc=0x00007f1cb7b30d13 offset=73 bits=0):
   callchain::midleaf@0 (line 31)
PcDesc(pc=0x00007f1cb7b30d69 offset=c9 bits=0):
- - - - - - - - - - - - - - - - - - - - - - - - - - - - - - - - - - - - - - - - 
oop maps:ImmutableOopMapSet contains 1 OopMaps

ImmutableOopMap {} pc offsets: 72 
- - - - - - - - - - - - - - - - - - - - - - - - - - - - - - - - - - - - - - - - 
scopes:
ScopeDesc(pc=0x00007f1cb7b30cbe offset=1e):
   callchain::midleaf@-1 (line 31)
ScopeDesc(pc=0x00007f1cb7b30cc4 offset=24):
   callchain::midleaf@11 (line 32)
ScopeDesc(pc=0x00007f1cb7b30ccd offset=2d):
   Packet::<init>@29 (line 10)
ScopeDesc(pc=0x00007f1cb7b30ccd offset=2d):
   callchain::midleaf@5 (line 31)
ScopeDesc(pc=0x00007f1cb7b30cd8 offset=38):
   Packet::<init>@13 (line 8)
ScopeDesc(pc=0x00007f1cb7b30cd8 offset=38):
   callchain::midleaf@5 (line 31)
ScopeDesc(pc=0x00007f1cb7b30ce8 offset=48):
   callchain::midleaf@12 (line 32)
   Locals
    - l0: empty
    - l1: obj[18]
    - l2: empty
   Objects
    - 0: R obj[18], Packet
        Fields: stack[0], stack[4], 0, 0
ScopeDesc(pc=0x00007f1cb7b30cf0 offset=50):
   callchain::midleaf@12 (line 32)
ScopeDesc(pc=0x00007f1cb7b30d00 offset=60):
   callchain::midleaf@21 (line 33)
ScopeDesc(pc=0x00007f1cb7b30d13 offset=73):
   callchain::midleaf@0 (line 31)
- - - - - - - - - - - - - - - - - - - - - - - - - - - - - - - - - - - - - - - - 
relocations:
         @0x00007f1cb7b30c78: 2143
relocInfo@0x00007f1cb7b30c78 [type=4(static_call) addr=0x00007f1cb7b30ce3 offset=67 format=1] | [destination=0x00007f1cb7abc1a0 metadata=0x0000000000000000]
         @0x00007f1cb7b30c7a: 8005
relocInfo@0x00007f1cb7b30c7a [type=16(post_call_nop) addr=0x00007f1cb7b30ce8 offset=5]
         @0x00007f1cb7b30c7c: 581d
relocInfo@0x00007f1cb7b30c7c [type=11(poll_return) addr=0x00007f1cb7b30d05 offset=29]
         @0x00007f1cb7b30c7e: 3116
relocInfo@0x00007f1cb7b30c7e [type=6(runtime_call) addr=0x00007f1cb7b30d1b offset=22 format=1] | [destination=0x00007f1cb7b01d20]
         @0x00007f1cb7b30c80: 781b4005
relocInfo@0x00007f1cb7b30c82 [type=8(internal_word) addr=0x00007f1cb7b30d20 offset=5 data=27] | [target=0x00007f1cb7b30d05]
         @0x00007f1cb7b30c84: 3111
relocInfo@0x00007f1cb7b30c84 [type=6(runtime_call) addr=0x00007f1cb7b30d31 offset=17 format=1] | [destination=0x00007f1cb7ac3f20]
         @0x00007f1cb7b30c86: 3105
relocInfo@0x00007f1cb7b30c86 [type=6(runtime_call) addr=0x00007f1cb7b30d36 offset=5 format=1] | [destination=0x00007f1cb7a08dc0]
         @0x00007f1cb7b30c88: 000a
relocInfo@0x00007f1cb7b30c88 [type=0(none) addr=0x00007f1cb7b30d40 offset=10]
         @0x00007f1cb7b30c8a: 7c01ffbd2800
relocInfo@0x00007f1cb7b30c8e [type=5(static_stub) addr=0x00007f1cb7b30d40 offset=0 data=-67] | [static_call=0x00007f1cb7b30ce3]
         @0x00007f1cb7b30c90: 6000
relocInfo@0x00007f1cb7b30c90 [type=12(metadata) addr=0x00007f1cb7b30d40 offset=0] | [metadata_addr=0x00007f1cb7b30d42 *=0x0000000000000000 offset=0]
         @0x00007f1cb7b30c92: 310a
relocInfo@0x00007f1cb7b30c92 [type=6(runtime_call) addr=0x00007f1cb7b30d4a offset=10 format=1] | [destination=0xffffffffffffffff]
         @0x00007f1cb7b30c94: 3105
relocInfo@0x00007f1cb7b30c94 [type=6(runtime_call) addr=0x00007f1cb7b30d4f offset=5 format=1] | [destination=0x00007f1cb7ac4620]
         @0x00007f1cb7b30c96: 310f
relocInfo@0x00007f1cb7b30c96 [type=6(runtime_call) addr=0x00007f1cb7b30d5e offset=15 format=1] | [destination=0x00007f1cb7ac56e0]
         @0x00007f1cb7b30c98: 
- - - - - - - - - - - - - - - - - - - - - - - - - - - - - - - - - - - - - - - - 
Dependencies:
Dependency of type unique_concrete_method_4
  context = Packet
  method  = {method} {0x00007f1c5c605d20} 'accum' '()I' in 'Packet'
  class   = Packet
  method  = {method} {0x00007f1c5c605d20} 'accum' '()I' in 'Packet'
   [nmethod<=klass]Packet
- - - - - - - - - - - - - - - - - - - - - - - - - - - - - - - - - - - - - - - - 
ExceptionHandlerTable (size = 24 bytes)
catch_pco = 72 (pc=0x00007f1cb7b30ce8, 1 entries)
  bci -1 at scope depth 0 -> pco 115 (pc=0x00007f1cb7b30d13)
- - - - - - - - - - - - - - - - - - - - - - - - - - - - - - - - - - - - - - - - 
ImplicitExceptionTable is empty
- - - - - - - - - - - - - - - - - - - - - - - - - - - - - - - - - - - - - - - - 
Recorded oops:
#0: 0x0000000000000000 nullptr-oop
#1: 0x000000011f920fa0 a 'java/lang/Class'{0x000000011f920fa0} = 'Packet'
#2: 0x000000011f81bf60 a 'jdk/internal/loader/ClassLoaders$AppClassLoader'{0x000000011f81bf60}
- - - - - - - - - - - - - - - - - - - - - - - - - - - - - - - - - - - - - - - - 
Recorded metadata:
#0: 0x0000000000000000 nullptr-oop
#1: 0x00007f1c5c6055a0 {method} {0x00007f1c5c6055a0} 'midleaf' '(I)I' in 'callchain'
#2: 0x00007f1c5c605c60 {method} {0x00007f1c5c605c60} '<init>' '(I)V' in 'Packet'
#3: 0x00007f1c5c605d20 {method} {0x00007f1c5c605d20} 'accum' '()I' in 'Packet'
#4: 0x00000000380c4a10 'Packet'
- - - - - - - - - - - - - - - - - - - - - - - - - - - - - - - - - - - - - - - - 
------------------------------------------------------------------------
static callchain::midleaf(I)I
  interpreter_invocation_count:        6784
  invocation_counter:                  6784
  backedge_counter:                       0
  decompile_count:                        0
  mdo size: 504 bytes

   0 new 7 <Packet>
   3 dup
   4 iload_0
   5 invokespecial 9 <Packet.<init>(I)V> 
  0    bci: 5    CounterData        count(5121)
   8 astore_1
   9 iload_0
  10 iconst_1
  11 iadd
  12 invokestatic 23 <callchain.leaf(I)I> 
  16   bci: 12   CounterData        count(5121)
  15 istore_2
  16 iload_2
  17 aload_1
  18 invokevirtual 19 <Packet.accum()I> 
  32   bci: 18   VirtualCallData    count(0) entries(1)
                                    'Packet'(5121 1.00)
  21 iadd
  22 ireturn
------------------------------------------------------------------------
static callchain::highleaf(I)I
  interpreter_invocation_count:        6784
  invocation_counter:                  6784
  backedge_counter:                       0
  decompile_count:                        0
  mdo size: 632 bytes

   0 new 7 <Packet>
   3 dup
   4 iload_0
   5 invokespecial 9 <Packet.<init>(I)V> 
  0    bci: 5    CounterData        count(5121)
   8 astore_1
   9 new 7 <Packet>
  12 dup
  13 iload_0
  14 iconst_1
  15 iadd
  16 invokespecial 9 <Packet.<init>(I)V> 
  16   bci: 16   CounterData        count(5121)
  19 astore_2
  20 new 7 <Packet>
  23 dup
  24 iload_0
  25 iconst_2
  26 iadd
  27 invokespecial 9 <Packet.<init>(I)V> 
  32   bci: 27   CounterData        count(5121)
  30 astore_3
  31 iload_0
  32 iconst_1
  33 iadd
  34 invokestatic 29 <callchain.midleaf(I)I> 
  48   bci: 34   CounterData        count(5121)
  37 istore #4
  39 fast_iload #4
  41 aload_1
  42 fast_igetfield 32 <Packet.field1:I> 
  45 iadd
  46 aload_1
  47 invokevirtual 19 <Packet.accum()I> 
  64   bci: 47   VirtualCallData    count(0) entries(1)
                                    'Packet'(5121 1.00)
  50 iadd
  51 aload_2
  52 invokevirtual 19 <Packet.accum()I> 
  112  bci: 52   VirtualCallData    count(0) entries(1)
                                    'Packet'(5121 1.00)
  55 iadd
  56 aload_3
  57 invokevirtual 19 <Packet.accum()I> 
  160  bci: 57   VirtualCallData    count(0) entries(1)
                                    'Packet'(5121 1.00)
  60 iadd
  61 ireturn
------------------------------------------------------------------------
static callchain::leaf(I)I
  interpreter_invocation_count:         205
  invocation_counter:                   205
  backedge_counter:                   20480
  decompile_count:                        1
  mdo size: 592 bytes

   0 iconst_0
   1 istore_1
   2 iconst_0
   3 istore_2
   4 iload_2
   5 bipush 100
   7 if_icmpge 49
  0    bci: 7    BranchData         taken(153) displacement(168)
                                    not taken(15361)
  10 new 7 <Packet>
  13 dup
  14 iload_2
  15 invokespecial 9 <Packet.<init>(I)V> 
  32   bci: 15   CounterData        count(15361)
  18 astore_3
  19 iload_0
  20 sipush 9997
  23 if_icmple 36
  48   bci: 23   BranchData         taken(15360) displacement(48)
                                    not taken(1)
  26 new 12 <java/lang/AssertionError>
  29 dup
  30 fast_aldc "Error"
  32 invokespecial 16 <java/lang/AssertionError.<init>(Ljava/lang/Object;)V> 
  80   bci: 32   CounterData        count(1)
  35 athrow
  36 iload_1
  37 aload_3
  38 invokevirtual 19 <Packet.accum()I> 
  96   bci: 38   VirtualCallData    count(0) entries(1)
                                    'Packet'(15360 1.00)
  41 iadd
  42 istore_1
  43 iinc #2 1
  46 goto 4
  144  bci: 46   JumpData           taken(15360) displacement(-144)
  49 iload_1
  50 ireturn
------------------------------------------------------------------------
static callchain::main([Ljava/lang/String;)V
  interpreter_invocation_count:           1
  invocation_counter:                     1
  backedge_counter:                    9996
  decompile_count:                        0
  mdo size: 576 bytes

   0 iconst_0
   1 istore_1
   2 iconst_0
   3 istore_2
   4 iload_2
   5 sipush 10000
   8 if_icmpge 24
  0    bci: 8    BranchData         taken(0) displacement(72)
                                    not taken(4877)
  11 iload_1
  12 iload_2
  13 invokestatic 36 <callchain.highleaf(I)I> 
  32   bci: 13   CounterData        count(4877)
  16 iadd
  17 istore_1
  18 iinc #2 1
  21 goto 4
  48   bci: 21   JumpData           taken(4876) displacement(-48)
  24 getstatic 39 <java/lang/System.out:Ljava/io/PrintStream;> 
  27 iload_1
  28 invokedynamic bsm=65 45 <makeConcatWithConstants(I)Ljava/lang/String;>
  72   bci: 28   CounterData        count(0)
                return type         none
  33 invokevirtual 49 <java/io/PrintStream.println(Ljava/lang/String;)V> 
  104  bci: 33   VirtualCallData    count(0) entries(0)
  36 return
------------------------------------------------------------------------
Total MDO size: 2304 bytes
